Workbook
Name ВстроеннаяВременнаяШкала_Дата_постановления: #N/A
Name Срез_Статья_КоАП1: #N/A
Name Срез_Тип_лица1: #N/A
Name Срез_Штраф_факт1: #N/A
Name Срез_Штраф_факт2: #N/A

Sheet компании+описание
A1: Номер случая | B1: Дата | C1: Субъект | D1: Описание
A2: 1 | B2: 17.02.2026 | C2: Акционерное общество «Негосударственный пенсионный фонд «Ростех» | D2: По результатам рассмотрения материалов дела об административном правонарушении № ЦА-38-ЮЛ-26-258, возбуждённого за совершение административного правонарушения, ответственность за которое предусмотрена частью 9 статьи 15.29 Кодекса Российской Федерации об административных правонарушениях, АО «НПФ «Ростех» назначено административное наказание в виде штрафа в размере 700 000 рублей. Постановление вступило в законную силу 17.02.2026.
A3: 2 | B3: 17.02.2026 | C3: Общество с ограниченной ответственностью «Управляющая компания_x000D_ «Атон-менеджмент» | D3: По результатам рассмотрения материалов дела об административном правонарушении № ЦА-38-ЮЛ-26-92, возбужденного за совершение административного правонарушения, ответственность за которое предусмотрена частью 6 статьи 15.29 КоАП РФ, Обществу с ограниченной ответственностью «Управляющая компания «Атон-менеджмент» назначено административное наказание в виде штрафа в размере 700 000 рублей. Постановление вступило в законную силу 17.02.2026.По результатам рассмотрения материалов дела об административном правонарушении № ЦА-38-ЮЛ-26-93, возбужденного за совершение административного правонарушения, ответственность за которое предусмотрена частью 12 статьи 15.29 КоАП РФ, Обществу с ограниченной ответственностью «Управляющая компания «Атон-менеджмент» назначено административное наказание в виде штрафа в размере 320 000 рублей. Постановление вступило в законную силу 17.02.2026.
A4: 3 | B4: 13.02.2026 | C4: Акционерное общество_x000D_ Управляющая компания «Центр Эссет Менеджмент» | D4: По результатам рассмотрения материалов дела об административном правонарушении № ЦА-38-ЮЛ-26-12, возбужденного за совершение административного правонарушения, ответственность за которое предусмотрена частью 12 статьи 15.29 КоАП РФ, Акционерному обществу Управляющей компании «Центр Эссет Менеджмент» назначено административное наказание в виде предупреждения. Постановление вступило в законную силу 13.02.2026.
A5: 4 | B5: 10.02.2026 | C5: АО «ИК «РИКОМ-ТРАСТ» | D5: По результатам рассмотрения материалов дела об административном правонарушении № ЦА-34-ЮЛ-26-294, возбужденного за совершение административного правонарушения, ответственность за которое предусмотрена частью 9 статьи 15.29 КоАП РФ, акционерному обществу «Инвестиционная компания «РИКОМ-ТРАСТ» назначено административное наказание в виде штрафа размером 1 000 000 (один миллион) рублей. Постановление от 26.01.2026 № 26-294/3110-1 о назначении административного наказания вступило в законную силу 10.02.2026.
A6: 5 | B6: 10.02.2026 | C6: Акционерное общество ВИМ Инвестиции | D6: По результатам рассмотрения материалов дела об административном правонарушении № ЦА-38-ЮЛ-26-19, возбуждённого за совершение административного правонарушения, ответственность за которое предусмотрена частью 12 статьи 15.29 Кодекса Российской Федерации об административных правонарушениях, АО ВИМ Инвестиции назначено административное наказание в виде штрафа в размере 350 000 рублей. Постановление вступило в законную силу 10.02.2026.
A7: 6 | B7: 10.02.2026 | C7: Общество с ограниченной_x000D_ ответственностью_x000D_ «Управляющая компания_x000D_ «Ресурс» | D7: По результатам рассмотрения материалов дела об административном правонарушении № ЦА-38-ЮЛ-26-2, возбужденного за совершение административного правонарушения, ответственность за которое предусмотрена частью 6 статьи 15.29 КоАП РФ, Обществу с ограниченной ответственностью «Управляющая компания «Ресурс» назначено административное наказание в виде предупреждения. Постановление вступило в законную силу 10.02.2026.
A8: 7 | B8: 10.02.2026 | C8: Общество с ограниченной ответственностью «ТрастЮнион Эссет Менеджмент» | D8: По результатам рассмотрения материалов дела об административном правонарушении № ЦА-38-ЮЛ-26-85, возбужденного за совершение административного правонарушения, ответственность за которое предусмотрена частью 12 статьи 15.29 КоАП РФ, Обществу с ограниченной ответственностью «ТрастЮнион Эссет Менеджмент» назначено административное наказание в виде предупреждения. Постановление вступило в законную силу 10.02.2026.
A9: 8 | B9: 10.02.2026 | C9: Акционерное общество «Управляющая Компания ТРИНФИКО» | D9: По результатам рассмотрения материалов дела об административном правонарушении № ЦА-38-ЮЛ-26-6, возбужденного за совершение административного правонарушения, ответственность за которое предусмотрена частью 5 статьи 15.29 КоАП РФ, Акционерному обществу «Управляющая Компания ТРИНФИКО» назначено административное наказание в виде штрафа в размере 250 000 рублей. Постановление вступило в законную силу 10.02.2026.
A10: 9 | B10: 09.02.2026 | C10: ООО «Цифра брокер» | D10: По результатам рассмотрения материалов дела об административном правонарушении № ЦА-34-ЮЛ-26-191, возбужденного за совершение административного правонарушения, ответственность за которое предусмотрена частью 12 статьи 15.29 КоАП РФ, ООО «Цифра брокер» назначено административное наказание в виде штрафа в размере 300 000 рублей. Постановление № 26-191/3110-1 о назначении административного наказания вступило в законную силу 07.02.2026.
A11: 10 | B11: 06.02.2026 | C11: Голубков Виктор Владимирович | D11: По результатам рассмотрения материалов дела об административном правонарушении № ЦА-34-Гр-25-21433, возбужденного за совершение административного правонарушения, ответственность за которое предусмотрена статьей 15.30 Кодекса Российской Федерации об административных правонарушениях, Голубкову Виктору Владимировичу назначено административное наказание в виде штрафа в размере 3 000 рублей. Постановление от 18.12.2025 № 25-21433/3110-1 о назначении административного наказания вступило в законную силу 03.02.2026.
A12: 11 | B12: 06.02.2026 | C12: генеральный директор общества с ограниченной ответственностью «Тринити Шиппинг» Ярошенко Александр Иванович | D12: По результатам рассмотрения материалов дела об административном правонарушении № ЦА-34-ДЛ-25-20686, возбужденного за совершение административного правонарушения, ответственность за которое предусмотрена статьей 15.30 Кодекса Российской Федерации об административных правонарушениях, генеральному директору общества с ограниченной ответственностью «Тринити Шиппинг» Ярошенко Александру Ивановичу назначено административное наказание в виде штрафа в размере 30 000 рублей. Постановление от 25.12.2025 № 25-20686/3110-1 о назначении административного наказания вступило в законную силу 31.01.2026.
A13: 12 | B13: 06.02.2026 | C13: Гальямова Наталья Александровна | D13: По результатам рассмотрения материалов дела об административном правонарушении № ЦА-34-ГР-25-21130, возбужденного за совершение административного правонарушения, ответственность за которое предусмотрена статьей 15.30 Кодекса Российской Федерации об административных правонарушениях, Гальямовой Наталье Александровне назначено административное наказание в виде штрафа в размере 3 000 рублей. Постановление от 25.12.2025 № 25-21130/3110-1 о назначении административного наказания вступило в законную силу 06.02.2026.
... A438: 437 | B438: 09.01.2025 | C438: Акционерное общество «Управляющая компания «Первая» | D438: По результатам рассмотрения материалов дела об административном правонарушении № ЦА-38-ЮЛ-24-14076 возбужденного за совершение административного правонарушения, ответственность за которое предусмотрена частью 12 статьи 15.29 КоАП РФ, АО УК «Первая» назначено административное наказание в виде штрафа в размере 300 000 рублей. Постановление вступило в законную силу 29.12.2024.

Sheet готовая таблица
A1: Номер случая | B1: Дата постановления | C1: Субъект | D1: Тип лица | E1: Статья КоАП | F1: Штраф факт | G1: мин | H1: макс | I1: Превышышение над мин размером %/min | J1: Описание статьи
A2: 1 | B2: 17.02.2026 | C2: Акционерное общество «Негосударственный пенсионный фонд «Ростех» | D2: Юридическое лицо | E2: ч.9 ст.15.29 КоАП РФ | F2: 700000 | G2: 700000 | H2: 1000000 | I2: {=_xlfn.IFS(F2=H2,1,F2=G2,0,F2<>G2,(F2-G2)/(G2))} -> 0 | J2: =VLOOKUP($E2,статьи!$G$2:$I$24,2,) -> Воспрепятствование профессиональным участником рынка ценных бумаг, клиринговой организацией, лицом, осуществляющим функции центрального контрагента, акционерным инвестиционным фондом, негосударственным пенсионным фондом, управляющей компанией акционерного инвестиционного фонда, паевого инвестиционного фонда или негосударственного пенсионного фонда либо специализированным депозитарием акционерного инвестиционного фонда, паевого инвестиционного фонда или негосударственного пенсионного фонда проведению Банком России проверок либо неисполнение или ненадлежащее исполнение предписаний Банка России
A3: 2 | B3: 17.02.2026 | C3: Общество с ограниченной ответственностью «Управляющая компания_x000D_ «Атон-менеджмент» | D3: Юридическое лицо | E3: ч.6 ст.15.29 КоАП РФ | F3: 700000 | G3: 700000 | H3: 1000000 | I3: {=_xlfn.IFS(F3=H3,1,F3=G3,0,F3<>G3,(F3-G3)/(G3))} -> 0 | J3: =VLOOKUP($E3,статьи!$G$2:$I$24,2,) -> Нарушение управляющей компанией акционерного инвестиционного фонда или паевого инвестиционного фонда предусмотренных федеральными законами и иными нормативными правовыми актами Российской Федерации ограничений ее деятельности -
A4: 2 | B4: 17.02.2026 | C4: Общество с ограниченной ответственностью «Управляющая компания_x000D_ «Атон-менеджмент» | D4: Юридическое лицо | E4: ч.12 ст.15.29 КоАП РФ | F4: 320000 | G4: 300000 | H4: 500000 | I4: {=_xlfn.IFS(F4=H4,1,F4=G4,0,F4<>G4,(F4-G4)/(G4))} -> 0.066666667 | J4: =VLOOKUP($E4,статьи!$G$2:$I$24,2,) -> Иное нарушение профессиональным участником рынка ценных бумаг, репозитарием, клиринговой организацией, лицом, осуществляющим функции центрального контрагента, акционерным инвестиционным фондом, негосударственным пенсионным фондом, управляющей компанией акционерного инвестиционного фонда, паевого инвестиционного фонда или негосударственного пенсионного фонда либо специализированным депозитарием акционерного инвестиционного фонда, паевого инвестиционного фонда или негосударственного пенсионного фонда при осуществлении ими соответствующих видов деятельности установленных законодательством требований к этим видам деятельности, за исключением случаев, предусмотренных частями 1 - 11 настоящей статьи, статьями 13.25, 15.18 - 15.20, 15.22, 15.23.1, 15.24.1, 15.30 и 19.7.3 настоящего Кодекса
A5: 3 | B5: 13.02.2026 | C5: Акционерное общество_x000D_ Управляющая компания «Центр Эссет Менеджмент» | D5: Юридическое лицо | E5: ч.12 ст.15.29 КоАП РФ | F5: предупреждение | G5: 300000 | H5: 500000 | I5: {=_xlfn.IFS(F5=H5,1,F5=G5,0,F5<>G5,(F5-G5)/(G5))} -> #VALUE! | J5: =VLOOKUP($E5,статьи!$G$2:$I$24,2,) -> Иное нарушение профессиональным участником рынка ценных бумаг, репозитарием, клиринговой организацией, лицом, осуществляющим функции центрального контрагента, акционерным инвестиционным фондом, негосударственным пенсионным фондом, управляющей компанией акционерного инвестиционного фонда, паевого инвестиционного фонда или негосударственного пенсионного фонда либо специализированным депозитарием акционерного инвестиционного фонда, паевого инвестиционного фонда или негосударственного пенсионного фонда при осуществлении ими соответствующих видов деятельности установленных законодательством требований к этим видам деятельности, за исключением случаев, предусмотренных частями 1 - 11 настоящей статьи, статьями 13.25, 15.18 - 15.20, 15.22, 15.23.1, 15.24.1, 15.30 и 19.7.3 настоящего Кодекса
A6: 4 | B6: 10.02.2026 | C6: АО «ИК «РИКОМ-ТРАСТ» | D6: Юридическое лицо | E6: ч.9 ст.15.29 КоАП РФ | F6: 1000000 | G6: 700000 | H6: 1000000 | I6: {=_xlfn.IFS(F6=H6,1,F6=G6,0,F6<>G6,(F6-G6)/(G6))} -> 1 | J6: =VLOOKUP($E6,статьи!$G$2:$I$24,2,) -> Воспрепятствование профессиональным участником рынка ценных бумаг, клиринговой организацией, лицом, осуществляющим функции центрального контрагента, акционерным инвестиционным фондом, негосударственным пенсионным фондом, управляющей компанией акционерного инвестиционного фонда, паевого инвестиционного фонда или негосударственного пенсионного фонда либо специализированным депозитарием акционерного инвестиционного фонда, паевого инвестиционного фонда или негосударственного пенсионного фонда проведению Банком России проверок либо неисполнение или ненадлежащее исполнение предписаний Банка России
A7: 5 | B7: 10.02.2026 | C7: Акционерное общество ВИМ Инвестиции | D7: Юридическое лицо | E7: ч.12 ст.15.29 КоАП РФ | F7: 350000 | G7: 300000 | H7: 500000 | I7: {=_xlfn.IFS(F7=H7,1,F7=G7,0,F7<>G7,(F7-G7)/(G7))} -> 0.16666667 | J7: =VLOOKUP($E7,статьи!$G$2:$I$24,2,) -> Иное нарушение профессиональным участником рынка ценных бумаг, репозитарием, клиринговой организацией, лицом, осуществляющим функции центрального контрагента, акционерным инвестиционным фондом, негосударственным пенсионным фондом, управляющей компанией акционерного инвестиционного фонда, паевого инвестиционного фонда или негосударственного пенсионного фонда либо специализированным депозитарием акционерного инвестиционного фонда, паевого инвестиционного фонда или негосударственного пенсионного фонда при осуществлении ими соответствующих видов деятельности установленных законодательством требований к этим видам деятельности, за исключением случаев, предусмотренных частями 1 - 11 настоящей статьи, статьями 13.25, 15.18 - 15.20, 15.22, 15.23.1, 15.24.1, 15.30 и 19.7.3 настоящего Кодекса
A8: 6 | B8: 10.02.2026 | C8: Общество с ограниченной_x000D_ ответственностью_x000D_ «Управляющая компания_x000D_ «Ресурс» | D8: Юридическое лицо | E8: ч.6 ст.15.29 КоАП РФ | F8: предупреждение | G8: 700000 | H8: 1000000 | I8: {=_xlfn.IFS(F8=H8,1,F8=G8,0,F8<>G8,(F8-G8)/(G8))} -> #VALUE! | J8: =VLOOKUP($E8,статьи!$G$2:$I$24,2,) -> Нарушение управляющей компанией акционерного инвестиционного фонда или паевого инвестиционного фонда предусмотренных федеральными законами и иными нормативными правовыми актами Российской Федерации ограничений ее деятельности -
A9: 7 | B9: 10.02.2026 | C9: Общество с ограниченной ответственностью «ТрастЮнион Эссет Менеджмент» | D9: Юридическое лицо | E9: ч.12 ст.15.29 КоАП РФ | F9: предупреждение | G9: 300000 | H9: 500000 | I9: {=_xlfn.IFS(F9=H9,1,F9=G9,0,F9<>G9,(F9-G9)/(G9))} -> #VALUE! | J9: =VLOOKUP($E9,статьи!$G$2:$I$24,2,) -> Иное нарушение профессиональным участником рынка ценных бумаг, репозитарием, клиринговой организацией, лицом, осуществляющим функции центрального контрагента, акционерным инвестиционным фондом, негосударственным пенсионным фондом, управляющей компанией акционерного инвестиционного фонда, паевого инвестиционного фонда или негосударственного пенсионного фонда либо специализированным депозитарием акционерного инвестиционного фонда, паевого инвестиционного фонда или негосударственного пенсионного фонда при осуществлении ими соответствующих видов деятельности установленных законодательством требований к этим видам деятельности, за исключением случаев, предусмотренных частями 1 - 11 настоящей статьи, статьями 13.25, 15.18 - 15.20, 15.22, 15.23.1, 15.24.1, 15.30 и 19.7.3 настоящего Кодекса
A10: 8 | B10: 10.02.2026 | C10: Акционерное общество «Управляющая Компания ТРИНФИКО» | D10: Юридическое лицо | E10: ч.5 ст.15.29 КоАП РФ | F10: 250000 | G10: 500000 | H10: 700000 | I10: {=_xlfn.IFS(F10=H10,1,F10=G10,0,F10<>G10,(F10-G10)/(G10))} -> -0.5 | J10: =VLOOKUP($E10,статьи!$G$2:$I$24,2,) -> Нарушение установленных нормативными правовыми актами Российской Федерации и инвестиционной декларацией акционерного инвестиционного фонда или паевого инвестиционного фонда требований к составу активов акционерных инвестиционных фондов или паевых инвестиционных фондов либо неустранение нарушений в структуре активов акционерных инвестиционных фондов или паевых инвестиционных фондов -
A11: 9 | B11: 09.02.2026 | C11: ООО «Цифра брокер» | D11: Юридическое лицо | E11: ч.12 ст.15.29 КоАП РФ | F11: 300000 | G11: 300000 | H11: 500000 | I11: {=_xlfn.IFS(F11=H11,1,F11=G11,0,F11<>G11,(F11-G11)/(G11))} -> 0 | J11: =VLOOKUP($E11,статьи!$G$2:$I$24,2,) -> Иное нарушение профессиональным участником рынка ценных бумаг, репозитарием, клиринговой организацией, лицом, осуществляющим функции центрального контрагента, акционерным инвестиционным фондом, негосударственным пенсионным фондом, управляющей компанией акционерного инвестиционного фонда, паевого инвестиционного фонда или негосударственного пенсионного фонда либо специализированным депозитарием акционерного инвестиционного фонда, паевого инвестиционного фонда или негосударственного пенсионного фонда при осуществлении ими соответствующих видов деятельности установленных законодательством требований к этим видам деятельности, за исключением случаев, предусмотренных частями 1 - 11 настоящей статьи, статьями 13.25, 15.18 - 15.20, 15.22, 15.23.1, 15.24.1, 15.30 и 19.7.3 настоящего Кодекса
A12: 10 | B12: 06.02.2026 | C12: Голубков Виктор Владимирович | D12: Гражданин | E12: ст.15.30 КоАП РФ | F12: 3000 | G12: 3000 | H12: 5000 | I12: {=_xlfn.IFS(F12=H12,1,F12=G12,0,F12<>G12,(F12-G12)/(G12))} -> 0 | J12: =VLOOKUP($E12,статьи!$G$2:$I$24,2,) -> Манипулирование рынком, если это действие не содержит уголовно наказуемого деяния
A13: 11 | B13: 06.02.2026 | C13: генеральный директор общества с ограниченной ответственностью «Тринити Шиппинг» Ярошенко Александр Иванович | D13: Должностное лицо | E13: ст.15.30 КоАП РФ | F13: 30000 | G13: 30000 | H13: 50000 | I13: {=_xlfn.IFS(F13=H13,1,F13=G13,0,F13<>G13,(F13-G13)/(G13))} -> 0 | J13: =VLOOKUP($E13,статьи!$G$2:$I$24,2,) -> Манипулирование рынком, если это действие не содержит уголовно наказуемого деяния
A14: 12 | B14: 06.02.2026 | C14: Гальямова Наталья Александровна | D14: Гражданин | E14: ст.15.30 КоАП РФ | F14: 3000 | G14: 3000 | H14: 5000 | I14: {=_xlfn.IFS(F14=H14,1,F14=G14,0,F14<>G14,(F14-G14)/(G14))} -> 0 | J14: =VLOOKUP($E14,статьи!$G$2:$I$24,2,) -> Манипулирование рынком, если это действие не содержит уголовно наказуемого деяния
A15: 13 | B15: 03.02.2026 | C15: Чмыхало Юлия Анатольевна | D15: Гражданин | E15: ст.15.30 КоАП РФ | F15: 3000 | G15: 3000 | H15: 5000 | I15: {=_xlfn.IFS(F15=H15,1,F15=G15,0,F15<>G15,(F15-G15)/(G15))} -> 0 | J15: =VLOOKUP($E15,статьи!$G$2:$I$24,2,) -> Манипулирование рынком, если это действие не содержит уголовно наказуемого деяния
A16: 14 | B16: 30.01.2026 | C16: Усольцева Яна Германовна | D16: Гражданин | E16: ст.15.30 КоАП РФ | F16: 3000 | G16: 3000 | H16: 5000 | I16: {=_xlfn.IFS(F16=H16,1,F16=G16,0,F16<>G16,(F16-G16)/(G16))} -> 0 | J16: =VLOOKUP($E16,статьи!$G$2:$I$24,2,) -> Манипулирование рынком, если это действие не содержит уголовно наказуемого деяния
A17: 15 | B17: 30.01.2026 | C17: Краснова Галина Ивановна | D17: Гражданин | E17: ст.15.30 КоАП РФ | F17: 3000 | G17: 3000 | H17: 5000 | I17: {=_xlfn.IFS(F17=H17,1,F17=G17,0,F17<>G17,(F17-G17)/(G17))} -> 0 | J17: =VLOOKUP($E17,статьи!$G$2:$I$24,2,) -> Манипулирование рынком, если это действие не содержит уголовно наказуемого деяния
A18: 16 | B18: 30.01.2026 | C18: Артамонов Валерий Геннадьевич | D18: Гражданин | E18: ст.15.30 КоАП РФ | F18: 3000 | G18: 3000 | H18: 5000 | I18: {=_xlfn.IFS(F18=H18,1,F18=G18,0,F18<>G18,(F18-G18)/(G18))} -> 0 | J18: =VLOOKUP($E18,статьи!$G$2:$I$24,2,) -> Манипулирование рынком, если это действие не содержит уголовно наказуемого деяния
A19: 17 | B19: 30.01.2026 | C19: Манюкова Татьяна Васильевна | D19: Гражданин | E19: ст.15.30 КоАП РФ | F19: 3000 | G19: 3000 | H19: 5000 | I19: {=_xlfn.IFS(F19=H19,1,F19=G19,0,F19<>G19,(F19-G19)/(G19))} -> 0 | J19: =VLOOKUP($E19,статьи!$G$2:$I$24,2,) -> Манипулирование рынком, если это действие не содержит уголовно наказуемого деяния
A20: 18 | B20: 30.01.2026 | C20: Доценко Марина Сергеевна | D20: Гражданин | E20: ст.15.30 КоАП РФ | F20: 3000 | G20: 3000 | H20: 5000 | I20: {=_xlfn.IFS(F20=H20,1,F20=G20,0,F20<>G20,(F20-G20)/(G20))} -> 0 | J20: =VLOOKUP($E20,статьи!$G$2:$I$24,2,) -> Манипулирование рынком, если это действие не содержит уголовно наказуемого деяния
A21: 19 | B21: 30.01.2026 | C21: Гальямов Марсель Геральдович | D21: Гражданин | E21: ст.15.30 КоАП РФ | F21: 3000 | G21: 3000 | H21: 5000 | I21: {=_xlfn.IFS(F21=H21,1,F21=G21,0,F21<>G21,(F21-G21)/(G21))} -> 0 | J21: =VLOOKUP($E21,статьи!$G$2:$I$24,2,) -> Манипулирование рынком, если это действие не содержит уголовно наказуемого деяния
A22: 20 | B22: 30.01.2026 | C22: Садыров Игорь Рашидович | D22: Гражданин | E22: ст.15.30 КоАП РФ | F22: 3000 | G22: 3000 | H22: 5000 | I22: {=_xlfn.IFS(F22=H22,1,F22=G22,0,F22<>G22,(F22-G22)/(G22))} -> 0 | J22: =VLOOKUP($E22,статьи!$G$2:$I$24,2,) -> Манипулирование рынком, если это действие не содержит уголовно наказуемого деяния
A23: 21 | B23: 27.01.2026 | C23: Карчевский Павел Владимирович | D23: Гражданин | E23: ст.15.30 КоАП РФ | F23: 3000 | G23: 3000 | H23: 5000 | I23: {=_xlfn.IFS(F23=H23,1,F23=G23,0,F23<>G23,(F23-G23)/(G23))} -> 0 | J23: =VLOOKUP($E23,статьи!$G$2:$I$24,2,) -> Манипулирование рынком, если это действие не содержит уголовно наказуемого деяния
A24: 22 | B24: 27.01.2026 | C24: Шушин Олег Игоревич | D24: Гражданин | E24: ст.15.30 КоАП РФ | F24: 3000 | G24: 3000 | H24: 5000 | I24: {=_xlfn.IFS(F24=H24,1,F24=G24,0,F24<>G24,(F24-G24)/(G24))} -> 0 | J24: =VLOOKUP($E24,статьи!$G$2:$I$24,2,) -> Манипулирование рынком, если это действие не содержит уголовно наказуемого деяния
A25: 23 | B25: 26.01.2026 | C25: Беломытцева Наталия Сергеевна | D25: Гражданин | E25: ст.15.30 КоАП РФ | F25: 3000 | G25: 3000 | H25: 5000 | I25: {=_xlfn.IFS(F25=H25,1,F25=G25,0,F25<>G25,(F25-G25)/(G25))} -> 0 | J25: =VLOOKUP($E25,статьи!$G$2:$I$24,2,) -> Манипулирование рынком, если это действие не содержит уголовно наказуемого деяния
A26: 24 | B26: 23.01.2026 | C26: Ретровская Нина Борисовна | D26: Гражданин | E26: ст.15.30 КоАП РФ | F26: 3000 | G26: 3000 | H26: 5000 | I26: {=_xlfn.IFS(F26=H26,1,F26=G26,0,F26<>G26,(F26-G26)/(G26))} -> 0 | J26: =VLOOKUP($E26,статьи!$G$2:$I$24,2,) -> Манипулирование рынком, если это действие не содержит уголовно наказуемого деяния
A27: 25 | B27: 23.01.2026 | C27: Исаченко Наталия Николаевна | D27: Гражданин | E27: ст.15.30 КоАП РФ | F27: 3000 | G27: 3000 | H27: 5000 | I27: {=_xlfn.IFS(F27=H27,1,F27=G27,0,F27<>G27,(F27-G27)/(G27))} -> 0 | J27: =VLOOKUP($E27,статьи!$G$2:$I$24,2,) -> Манипулирование рынком, если это действие не содержит уголовно наказуемого деяния
A28: 26 | B28: 23.01.2026 | C28: Беломытцев Павел Анатольевич | D28: Гражданин | E28: ст.15.30 КоАП РФ | F28: 3000 | G28: 3000 | H28: 5000 | I28: {=_xlfn.IFS(F28=H28,1,F28=G28,0,F28<>G28,(F28-G28)/(G28))} -> 0 | J28: =VLOOKUP($E28,статьи!$G$2:$I$24,2,) -> Манипулирование рынком, если это действие не содержит уголовно наказуемого деяния
A29: 27 | B29: 23.01.2026 | C29: Зайцев Александр Олегович | D29: Гражданин | E29: ст.15.30 КоАП РФ | F29: 3000 | G29: 3000 | H29: 5000 | I29: {=_xlfn.IFS(F29=H29,1,F29=G29,0,F29<>G29,(F29-G29)/(G29))} -> 0 | J29: =VLOOKUP($E29,статьи!$G$2:$I$24,2,) -> Манипулирование рынком, если это действие не содержит уголовно наказуемого деяния
A30: 28 | B30: 23.01.2026 | C30: Нарушева Елена Гаптелахатовна | D30: Гражданин | E30: ст.15.30 КоАП РФ | F30: 3000 | G30: 3000 | H30: 5000 | I30: {=_xlfn.IFS(F30=H30,1,F30=G30,0,F30<>G30,(F30-G30)/(G30))} -> 0 | J30: =VLOOKUP($E30,статьи!$G$2:$I$24,2,) -> Манипулирование рынком, если это действие не содержит уголовно наказуемого деяния
A31: 29 | B31: 23.01.2026 | C31: Нарушев Андрей Иванович | D31: Гражданин | E31: ст.15.30 КоАП РФ | F31: 3000 | G31: 3000 | H31: 5000 | I31: {=_xlfn.IFS(F31=H31,1,F31=G31,0,F31<>G31,(F31-G31)/(G31))} -> 0 | J31: =VLOOKUP($E31,статьи!$G$2:$I$24,2,) -> Манипулирование рынком, если это действие не содержит уголовно наказуемого деяния
A32: 30 | B32: 19.01.2026 | C32: ИП Панов Александр Константинович | D32: Гражданин | E32: ст.15.30 КоАП РФ | F32: 30000 | G32: 3000 | H32: 5000 | I32: {=_xlfn.IFS(F32=H32,1,F32=G32,0,F32<>G32,(F32-G32)/(G32))} -> 9 | J32: =VLOOKUP($E32,статьи!$G$2:$I$24,2,) -> Манипулирование рынком, если это действие не содержит уголовно наказуемого деяния
A33: 31 | B33: 19.01.2026 | C33: ИП Панов Владимир Константинович | D33: Гражданин | E33: ст.15.30 КоАП РФ | F33: 30000 | G33: 3000 | H33: 5000 | I33: {=_xlfn.IFS(F33=H33,1,F33=G33,0,F33<>G33,(F33-G33)/(G33))} -> 9 | J33: =VLOOKUP($E33,статьи!$G$2:$I$24,2,) -> Манипулирование рынком, если это действие не содержит уголовно наказуемого деяния
A34: 32 | B34: 19.01.2026 | C34: Оганезян Роман Рафикович | D34: Гражданин | E34: ст.15.30 КоАП РФ | F34: 3000 | G34: 3000 | H34: 5000 | I34: {=_xlfn.IFS(F34=H34,1,F34=G34,0,F34<>G34,(F34-G34)/(G34))} -> 0 | J34: =VLOOKUP($E34,статьи!$G$2:$I$24,2,) -> Манипулирование рынком, если это действие не содержит уголовно наказуемого деяния
A35: 33 | B35: 19.01.2026 | C35: Клименко Артем Валерьевич | D35: Гражданин | E35: ст.15.30 КоАП РФ | F35: 3000 | G35: 3000 | H35: 5000 | I35: {=_xlfn.IFS(F35=H35,1,F35=G35,0,F35<>G35,(F35-G35)/(G35))} -> 0 | J35: =VLOOKUP($E35,статьи!$G$2:$I$24,2,) -> Манипулирование рынком, если это действие не содержит уголовно наказуемого деяния
A36: 34 | B36: 19.01.2026 | C36: Тихомиров Вадим Владимирович | D36: Гражданин | E36: ст.15.30 КоАП РФ | F36: 3000 | G36: 3000 | H36: 5000 | I36: {=_xlfn.IFS(F36=H36,1,F36=G36,0,F36<>G36,(F36-G36)/(G36))} -> 0 | J36: =VLOOKUP($E36,статьи!$G$2:$I$24,2,) -> Манипулирование рынком, если это действие не содержит уголовно наказуемого деяния
A37: 35 | B37: 15.01.2026 | C37: ООО "Тринити Шиппинг" | D37: Юридическое лицо | E37: ст.15.30 КоАП РФ | F37: 700000 | G37: 700000 | H37: в размере суммы излишнего дохода… но не менее 700 000 рублей | I37: {=_xlfn.IFS(F37=H37,1,F37=G37,0,F37<>G37,(F37-G37)/(G37))} -> 0 | J37: =VLOOKUP($E37,статьи!$G$2:$I$24,2,) -> Манипулирование рынком, если это действие не содержит уголовно наказуемого деяния
A38: 36 | B38: 15.01.2026 | C38: Бурыкин Иван Терентьевич | D38: Гражданин | E38: ст.15.30 КоАП РФ | F38: 3000 | G38: 3000 | H38: 5000 | I38: {=_xlfn.IFS(F38=H38,1,F38=G38,0,F38<>G38,(F38-G38)/(G38))} -> 0 | J38: =VLOOKUP($E38,статьи!$G$2:$I$24,2,) -> Манипулирование рынком, если это действие не содержит уголовно наказуемого деяния
A39: 37 | B39: 13.01.2026 | C39: Колесникова Надежда Вячеславовна | D39: Гражданин | E39: ст.15.30 КоАП РФ | F39: 3000 | G39: 3000 | H39: 5000 | I39: {=_xlfn.IFS(F39=H39,1,F39=G39,0,F39<>G39,(F39-G39)/(G39))} -> 0 | J39: =VLOOKUP($E39,статьи!$G$2:$I$24,2,) -> Манипулирование рынком, если это действие не содержит уголовно наказуемого деяния
A40: 38 | B40: 13.01.2026 | C40: Мазнев Андрей Вячеславович | D40: Гражданин | E40: ст.15.30 КоАП РФ | F40: 3000 | G40: 3000 | H40: 5000 | I40: {=_xlfn.IFS(F40=H40,1,F40=G40,0,F40<>G40,(F40-G40)/(G40))} -> 0 | J40: =VLOOKUP($E40,статьи!$G$2:$I$24,2,) -> Манипулирование рынком, если это действие не содержит уголовно наказуемого деяния
A41: 39 | B41: 13.01.2026 | C41: Мазнев Сергей Вячеславович | D41: Гражданин | E41: ст.15.30 КоАП РФ | F41: 3000 | G41: 3000 | H41: 5000 | I41: {=_xlfn.IFS(F41=H41,1,F41=G41,0,F41<>G41,(F41-G41)/(G41))} -> 0 | J41: =VLOOKUP($E41,статьи!$G$2:$I$24,2,) -> Манипулирование рынком, если это действие не содержит уголовно наказуемого деяния
A42: 40 | B42: 13.01.2026 | C42: Дмитриев Андрей Николаевич | D42: Гражданин | E42: ст.15.30 КоАП РФ | F42: 3000 | G42: 3000 | H42: 5000 | I42: {=_xlfn.IFS(F42=H42,1,F42=G42,0,F42<>G42,(F42-G42)/(G42))} -> 0 | J42: =VLOOKUP($E42,статьи!$G$2:$I$24,2,) -> Манипулирование рынком, если это действие не содержит уголовно наказуемого деяния
A43: 41 | B43: 13.01.2026 | C43: Малык Герман Андреевич | D43: Гражданин | E43: ст.15.30 КоАП РФ | F43: 3000 | G43: 3000 | H43: 5000 | I43: {=_xlfn.IFS(F43=H43,1,F43=G43,0,F43<>G43,(F43-G43)/(G43))} -> 0 | J43: =VLOOKUP($E43,статьи!$G$2:$I$24,2,) -> Манипулирование рынком, если это действие не содержит уголовно наказуемого деяния
A44: 42 | B44: 13.01.2026 | C44: Усачев Андрей Николаевич | D44: Гражданин | E44: ст.15.30 КоАП РФ | F44: 3000 | G44: 3000 | H44: 5000 | I44: {=_xlfn.IFS(F44=H44,1,F44=G44,0,F44<>G44,(F44-G44)/(G44))} -> 0 | J44: =VLOOKUP($E44,статьи!$G$2:$I$24,2,) -> Манипулирование рынком, если это действие не содержит уголовно наказуемого деяния
A45: 43 | B45: 13.01.2026 | C45: Шушин Игорь Борисович | D45: Гражданин | E45: ст.15.30 КоАП РФ | F45: 3000 | G45: 3000 | H45: 5000 | I45: {=_xlfn.IFS(F45=H45,1,F45=G45,0,F45<>G45,(F45-G45)/(G45))} -> 0 | J45: =VLOOKUP($E45,статьи!$G$2:$I$24,2,) -> Манипулирование рынком, если это действие не содержит уголовно наказуемого деяния
A46: 44 | B46: 13.01.2026 | C46: Шушина Татьяна Геннадьевна | D46: Гражданин | E46: ст.15.30 КоАП РФ | F46: 3000 | G46: 3000 | H46: 5000 | I46: {=_xlfn.IFS(F46=H46,1,F46=G46,0,F46<>G46,(F46-G46)/(G46))} -> 0 | J46: =VLOOKUP($E46,статьи!$G$2:$I$24,2,) -> Манипулирование рынком, если это действие не содержит уголовно наказуемого деяния
A47: 45 | B47: 13.01.2026 | C47: Богачев Вячеслав Анатольевич | D47: Гражданин | E47: ст.15.30 КоАП РФ | F47: 3000 | G47: 3000 | H47: 5000 | I47: {=_xlfn.IFS(F47=H47,1,F47=G47,0,F47<>G47,(F47-G47)/(G47))} -> 0 | J47: =VLOOKUP($E47,статьи!$G$2:$I$24,2,) -> Манипулирование рынком, если это действие не содержит уголовно наказуемого деяния
A48: 46 | B48: 13.01.2026 | C48: Султанаева Эльвира Дамировна | D48: Гражданин | E48: ст.15.30 КоАП РФ | F48: 3000 | G48: 3000 | H48: 5000 | I48: {=_xlfn.IFS(F48=H48,1,F48=G48,0,F48<>G48,(F48-G48)/(G48))} -> 0 | J48: =VLOOKUP($E48,статьи!$G$2:$I$24,2,) -> Манипулирование рынком, если это действие не содержит уголовно наказуемого деяния
A49: 47 | B49: 13.01.2026 | C49: Бурыкин Иван Иванович | D49: Гражданин | E49: ст.15.30 КоАП РФ | F49: 3000 | G49: 3000 | H49: 5000 | I49: {=_xlfn.IFS(F49=H49,1,F49=G49,0,F49<>G49,(F49-G49)/(G49))} -> 0 | J49: =VLOOKUP($E49,статьи!$G$2:$I$24,2,) -> Манипулирование рынком, если это действие не содержит уголовно наказуемого деяния
... A53: 51 | B53: 13.01.2026 | C53: ООО «ПФЛ НОВЫЕ ИНВЕСТИЦИИ» | D53: Юридическое лицо | E53: ч.1 ст.19.7.3 КоАП РФ | F53: 350000 | G53: 500000 | H53: 700000 | I53: {=_xlfn.IFS(F53=H53,1,F53=G53,0,F53<>G53,(F53-G53)/(G53))} -> -0.3 | J53: =VLOOKUP($E53,статьи!$G$2:$I$24,2,) -> 1. Непредставление или нарушение порядка либо сроков представления в Банк России отчетов, уведомлений и иной информации, предусмотренной законодательством и (или) необходимой для осуществления этим органом (должностным лицом) его законной деятельности, либо представление информации не в полном объеме и (или) недостоверной информации, за исключением случаев, если в соответствии со страховым законодательством, законодательством Российской Федерации о кредитной кооперации, о сельскохозяйственной кооперации, о микрофинансовой деятельности и микрофинансовых организациях или о ломбардах Банком России дается законное предписание об устранении нарушения страхового законодательства, законодательства Российской Федерации о кредитной кооперации, о сельскохозяйственной кооперации, о микрофинансовой деятельности и микрофинансовых организациях или о ломбардах, и случаев, указанных в части 2 настоящей статьи, если эти действия (бездействие) не содержат признаков уголовно наказуемого деяния
A54: 52 | B54: 13.01.2026 | C54: ООО «ТОЧКА ИНВЕСТИЦИИ» | D54: Юридическое лицо | E54: ч.1 ст.19.7.3 КоАП РФ | F54: предупреждение | G54: 500000 | H54: 700000 | I54: {=_xlfn.IFS(F54=H54,1,F54=G54,0,F54<>G54,(F54-G54)/(G54))} -> #VALUE! | J54: =VLOOKUP($E54,статьи!$G$2:$I$24,2,) -> 1. Непредставление или нарушение порядка либо сроков представления в Банк России отчетов, уведомлений и иной информации, предусмотренной законодательством и (или) необходимой для осуществления этим органом (должностным лицом) его законной деятельности, либо представление информации не в полном объеме и (или) недостоверной информации, за исключением случаев, если в соответствии со страховым законодательством, законодательством Российской Федерации о кредитной кооперации, о сельскохозяйственной кооперации, о микрофинансовой деятельности и микрофинансовых организациях или о ломбардах Банком России дается законное предписание об устранении нарушения страхового законодательства, законодательства Российской Федерации о кредитной кооперации, о сельскохозяйственной кооперации, о микрофинансовой деятельности и микрофинансовых организациях или о ломбардах, и случаев, указанных в части 2 настоящей статьи, если эти действия (бездействие) не содержат признаков уголовно наказуемого деяния
A55: 53 | B55: 13.01.2026 | C55: Акционерное общество "Частные Активы" | D55: Юридическое лицо | E55: ч.12 ст.15.29 КоАП РФ | F55: предупреждение | G55: 300000 | H55: 500000 | I55: {=_xlfn.IFS(F55=H55,1,F55=G55,0,F55<>G55,(F55-G55)/(G55))} -> #VALUE! | J55: =VLOOKUP($E55,статьи!$G$2:$I$24,2,) -> Иное нарушение профессиональным участником рынка ценных бумаг, репозитарием, клиринговой организацией, лицом, осуществляющим функции центрального контрагента, акционерным инвестиционным фондом, негосударственным пенсионным фондом, управляющей компанией акционерного инвестиционного фонда, паевого инвестиционного фонда или негосударственного пенсионного фонда либо специализированным депозитарием акционерного инвестиционного фонда, паевого инвестиционного фонда или негосударственного пенсионного фонда при осуществлении ими соответствующих видов деятельности установленных законодательством требований к этим видам деятельности, за исключением случаев, предусмотренных частями 1 - 11 настоящей статьи, статьями 13.25, 15.18 - 15.20, 15.22, 15.23.1, 15.24.1, 15.30 и 19.7.3 настоящего Кодекса
A56: 54 | B56: 13.01.2026 | C56: Общество с ограниченной ответственностью Управляющая Компания "Юнион Инвест Групп" | D56: Юридическое лицо | E56: ч.9 ст.15.29 КоАП РФ | F56: 350000 | G56: 700000 | H56: 1000000 | I56: {=_xlfn.IFS(F56=H56,1,F56=G56,0,F56<>G56,(F56-G56)/(G56))} -> -0.5 | J56: =VLOOKUP($E56,статьи!$G$2:$I$24,2,) -> Воспрепятствование профессиональным участником рынка ценных бумаг, клиринговой организацией, лицом, осуществляющим функции центрального контрагента, акционерным инвестиционным фондом, негосударственным пенсионным фондом, управляющей компанией акционерного инвестиционного фонда, паевого инвестиционного фонда или негосударственного пенсионного фонда либо специализированным депозитарием акционерного инвестиционного фонда, паевого инвестиционного фонда или негосударственного пенсионного фонда проведению Банком России проверок либо неисполнение или ненадлежащее исполнение предписаний Банка России
A57: 54 | B57: 13.01.2026 | C57: Общество с ограниченной ответственностью Управляющая Компания "Юнион Инвест Групп" | D57: Юридическое лицо | E57: ч.12 ст.15.29 КоАП РФ | F57: 150000 | G57: 300000 | H57: 500000 | I57: {=_xlfn.IFS(F57=H57,1,F57=G57,0,F57<>G57,(F57-G57)/(G57))} -> -0.5 | J57: =VLOOKUP($E57,статьи!$G$2:$I$24,2,) -> Иное нарушение профессиональным участником рынка ценных бумаг, репозитарием, клиринговой организацией, лицом, осуществляющим функции центрального контрагента, акционерным инвестиционным фондом, негосударственным пенсионным фондом, управляющей компанией акционерного инвестиционного фонда, паевого инвестиционного фонда или негосударственного пенсионного фонда либо специализированным депозитарием акционерного инвестиционного фонда, паевого инвестиционного фонда или негосударственного пенсионного фонда при осуществлении ими соответствующих видов деятельности установленных законодательством требований к этим видам деятельности, за исключением случаев, предусмотренных частями 1 - 11 настоящей статьи, статьями 13.25, 15.18 - 15.20, 15.22, 15.23.1, 15.24.1, 15.30 и 19.7.3 настоящего Кодекса
A58: 55 | B58: 13.01.2026 | C58: Акционерное общество Негосударственный пенсионный фонд ВТБ Пенсионный фонд | D58: Юридическое лицо | E58: ч.9 ст.15.29 КоАП РФ | F58: 700000 | G58: 700000 | H58: 1000000 | I58: {=_xlfn.IFS(F58=H58,1,F58=G58,0,F58<>G58,(F58-G58)/(G58))} -> 0 | J58: =VLOOKUP($E58,статьи!$G$2:$I$24,2,) -> Воспрепятствование профессиональным участником рынка ценных бумаг, клиринговой организацией, лицом, осуществляющим функции центрального контрагента, акционерным инвестиционным фондом, негосударственным пенсионным фондом, управляющей компанией акционерного инвестиционного фонда, паевого инвестиционного фонда или негосударственного пенсионного фонда либо специализированным депозитарием акционерного инвестиционного фонда, паевого инвестиционного фонда или негосударственного пенсионного фонда проведению Банком России проверок либо неисполнение или ненадлежащее исполнение предписаний Банка России
A59: 56 | B59: 13.01.2026 | C59: Акционерное общество «Управляющая Компания ТРИНФИКО» | D59: Юридическое лицо | E59: ч.2 ст.15.19 КоАП РФ | F59: предупреждение | G59: 700000 | H59: 1000000 | I59: {=_xlfn.IFS(F59=H59,1,F59=G59,0,F59<>G59,(F59-G59)/(G59))} -> #VALUE! | J59: =VLOOKUP($E59,статьи!$G$2:$I$24,2,) -> 2. Нераскрытие или нарушение эмитентом, профессиональным участником рынка ценных бумаг, клиринговой организацией, акционерным инвестиционным фондом, управляющей компанией акционерного инвестиционного фонда, паевого инвестиционного фонда или негосударственного пенсионного фонда, специализированным депозитарием акционерного инвестиционного фонда, паевого инвестиционного фонда или негосударственного пенсионного фонда либо лицом, оказывающим услуги по публичному представлению раскрываемой информации, порядка и сроков раскрытия информации, предусмотренной федеральными законами и принятыми в соответствии с ними иными нормативными правовыми актами, а равно раскрытие информации не в полном объеме, и (или) недостоверной информации, и (или) вводящей в заблуждение информации
A60: 57 | B60: 13.01.2026 | C60: Акционерное общество «АБ Капитал» | D60: Юридическое лицо | E60: ч.2 ст.15.19 КоАП РФ | F60: предупреждение | G60: 700000 | H60: 1000000 | I60: {=_xlfn.IFS(F60=H60,1,F60=G60,0,F60<>G60,(F60-G60)/(G60))} -> #VALUE! | J60: =VLOOKUP($E60,статьи!$G$2:$I$24,2,) -> 2. Нераскрытие или нарушение эмитентом, профессиональным участником рынка ценных бумаг, клиринговой организацией, акционерным инвестиционным фондом, управляющей компанией акционерного инвестиционного фонда, паевого инвестиционного фонда или негосударственного пенсионного фонда, специализированным депозитарием акционерного инвестиционного фонда, паевого инвестиционного фонда или негосударственного пенсионного фонда либо лицом, оказывающим услуги по публичному представлению раскрываемой информации, порядка и сроков раскрытия информации, предусмотренной федеральными законами и принятыми в соответствии с ними иными нормативными правовыми актами, а равно раскрытие информации не в полном объеме, и (или) недостоверной информации, и (или) вводящей в заблуждение информации
A61: 58 | B61: 13.01.2026 | C61: Акционерное общество «Инвестиционная компания «РИКОМ-ТРАСТ» | D61: Юридическое лицо | E61: ч.2 ст.15.29 КоАП РФ | F61: 500000 | G61: 500000 | H61: 700000 | I61: {=_xlfn.IFS(F61=H61,1,F61=G61,0,F61<>G61,(F61-G61)/(G61))} -> 0 | J61: =VLOOKUP($E61,статьи!$G$2:$I$24,2,) -> Нарушение профессиональным участником рынка ценных бумаг, осуществляющим брокерскую или дилерскую деятельность либо деятельность по управлению ценными бумагами, установленных нормативными правовыми актами Российской Федерации правил ведения учета и составления отчетности
A62: 59 | B62: 13.01.2026 | C62: Общество с ограниченной ответственностью «Т-Капитал» | D62: Юридическое лицо | E62: ч.2 ст.15.19 КоАП РФ | F62: 700000 | G62: 700000 | H62: 1000000 | I62: {=_xlfn.IFS(F62=H62,1,F62=G62,0,F62<>G62,(F62-G62)/(G62))} -> 0 | J62: =VLOOKUP($E62,статьи!$G$2:$I$24,2,) -> 2. Нераскрытие или нарушение эмитентом, профессиональным участником рынка ценных бумаг, клиринговой организацией, акционерным инвестиционным фондом, управляющей компанией акционерного инвестиционного фонда, паевого инвестиционного фонда или негосударственного пенсионного фонда, специализированным депозитарием акционерного инвестиционного фонда, паевого инвестиционного фонда или негосударственного пенсионного фонда либо лицом, оказывающим услуги по публичному представлению раскрываемой информации, порядка и сроков раскрытия информации, предусмотренной федеральными законами и принятыми в соответствии с ними иными нормативными правовыми актами, а равно раскрытие информации не в полном объеме, и (или) недостоверной информации, и (или) вводящей в заблуждение информации
A63: 60 | B63: 13.01.2026 | C63: Общество с ограниченной ответственностью «РСХБ Управление Активами» | D63: Юридическое лицо | E63: ч.12 ст.15.29 КоАП РФ | F63: 400000 | G63: 300000 | H63: 500000 | I63: {=_xlfn.IFS(F63=H63,1,F63=G63,0,F63<>G63,(F63-G63)/(G63))} -> 0.33333333 | J63: =VLOOKUP($E63,статьи!$G$2:$I$24,2,) -> Иное нарушение профессиональным участником рынка ценных бумаг, репозитарием, клиринговой организацией, лицом, осуществляющим функции центрального контрагента, акционерным инвестиционным фондом, негосударственным пенсионным фондом, управляющей компанией акционерного инвестиционного фонда, паевого инвестиционного фонда или негосударственного пенсионного фонда либо специализированным депозитарием акционерного инвестиционного фонда, паевого инвестиционного фонда или негосударственного пенсионного фонда при осуществлении ими соответствующих видов деятельности установленных законодательством требований к этим видам деятельности, за исключением случаев, предусмотренных частями 1 - 11 настоящей статьи, статьями 13.25, 15.18 - 15.20, 15.22, 15.23.1, 15.24.1, 15.30 и 19.7.3 настоящего Кодекса
A64: 61 | B64: 30.12.2025 | C64: Акционерное общество «Объединенное кредитное бюро» | D64: Юридическое лицо | E64: ч.1 ст.19.7.3 КоАП РФ | F64: 700000 | G64: 500000 | H64: 700000 | I64: {=_xlfn.IFS(F64=H64,1,F64=G64,0,F64<>G64,(F64-G64)/(G64))} -> 1 | J64: =VLOOKUP($E64,статьи!$G$2:$I$24,2,) -> 1. Непредставление или нарушение порядка либо сроков представления в Банк России отчетов, уведомлений и иной информации, предусмотренной законодательством и (или) необходимой для осуществления этим органом (должностным лицом) его законной деятельности, либо представление информации не в полном объеме и (или) недостоверной информации, за исключением случаев, если в соответствии со страховым законодательством, законодательством Российской Федерации о кредитной кооперации, о сельскохозяйственной кооперации, о микрофинансовой деятельности и микрофинансовых организациях или о ломбардах Банком России дается законное предписание об устранении нарушения страхового законодательства, законодательства Российской Федерации о кредитной кооперации, о сельскохозяйственной кооперации, о микрофинансовой деятельности и микрофинансовых организациях или о ломбардах, и случаев, указанных в части 2 настоящей статьи, если эти действия (бездействие) не содержат признаков уголовно наказуемого деяния
A65: 62 | B65: 30.12.2025 | C65: Пивень Наталья Анатольевна | D65: Гражданин | E65: ст.15.30 КоАП РФ | F65: 3000 | G65: 3000 | H65: 5000 | I65: {=_xlfn.IFS(F65=H65,1,F65=G65,0,F65<>G65,(F65-G65)/(G65))} -> 0 | J65: =VLOOKUP($E65,статьи!$G$2:$I$24,2,) -> Манипулирование рынком, если это действие не содержит уголовно наказуемого деяния
A66: 63 | B66: 30.12.2025 | C66: Акционерное общество «Объединенное кредитное бюро» | D66: Юридическое лицо | E66: ч.1 ст.19.7.3 КоАП РФ | F66: 700000 | G66: 500000 | H66: 700000 | I66: {=_xlfn.IFS(F66=H66,1,F66=G66,0,F66<>G66,(F66-G66)/(G66))} -> 1 | J66: =VLOOKUP($E66,статьи!$G$2:$I$24,2,) -> 1. Непредставление или нарушение порядка либо сроков представления в Банк России отчетов, уведомлений и иной информации, предусмотренной законодательством и (или) необходимой для осуществления этим органом (должностным лицом) его законной деятельности, либо представление информации не в полном объеме и (или) недостоверной информации, за исключением случаев, если в соответствии со страховым законодательством, законодательством Российской Федерации о кредитной кооперации, о сельскохозяйственной кооперации, о микрофинансовой деятельности и микрофинансовых организациях или о ломбардах Банком России дается законное предписание об устранении нарушения страхового законодательства, законодательства Российской Федерации о кредитной кооперации, о сельскохозяйственной кооперации, о микрофинансовой деятельности и микрофинансовых организациях или о ломбардах, и случаев, указанных в части 2 настоящей статьи, если эти действия (бездействие) не содержат признаков уголовно наказуемого деяния
A67: 64 | B67: 30.12.2025 | C67: Пивень Демид Романович | D67: Гражданин | E67: ст.15.30 КоАП РФ | F67: 3000 | G67: 3000 | H67: 5000 | I67: {=_xlfn.IFS(F67=H67,1,F67=G67,0,F67<>G67,(F67-G67)/(G67))} -> 0 | J67: =VLOOKUP($E67,статьи!$G$2:$I$24,2,) -> Манипулирование рынком, если это действие не содержит уголовно наказуемого деяния
A68: 65 | B68: 29.12.2025 | C68: Акционерное общество "Инвестиционная компания "Лидер" | D68: Юридическое лицо | E68: ч.2 ст.15.29 КоАП РФ | F68: предупреждение | G68: 500000 | H68: 700000 | I68: {=_xlfn.IFS(F68=H68,1,F68=G68,0,F68<>G68,(F68-G68)/(G68))} -> #VALUE! | J68: =VLOOKUP($E68,статьи!$G$2:$I$24,2,) -> Нарушение профессиональным участником рынка ценных бумаг, осуществляющим брокерскую или дилерскую деятельность либо деятельность по управлению ценными бумагами, установленных нормативными правовыми актами Российской Федерации правил ведения учета и составления отчетности
A69: 66 | B69: 23.12.2025 | C69: Кувшинова Анна Викторовна | D69: Гражданин | E69: ст.15.30 КоАП РФ | F69: 3000 | G69: 3000 | H69: 5000 | I69: {=_xlfn.IFS(F69=H69,1,F69=G69,0,F69<>G69,(F69-G69)/(G69))} -> 0 | J69: =VLOOKUP($E69,статьи!$G$2:$I$24,2,) -> Манипулирование рынком, если это действие не содержит уголовно наказуемого деяния
A70: 67 | B70: 23.12.2025 | C70: Кувшинов Роман Сергеевич | D70: Гражданин | E70: ст.15.30 КоАП РФ | F70: 3000 | G70: 3000 | H70: 5000 | I70: {=_xlfn.IFS(F70=H70,1,F70=G70,0,F70<>G70,(F70-G70)/(G70))} -> 0 | J70: =VLOOKUP($E70,статьи!$G$2:$I$24,2,) -> Манипулирование рынком, если это действие не содержит уголовно наказуемого деяния
A71: 68 | B71: 23.12.2025 | C71: Чамкин Михаил Александрович | D71: Гражданин | E71: ст.15.30 КоАП РФ | F71: 30000 | G71: 3000 | H71: 5000 | I71: {=_xlfn.IFS(F71=H71,1,F71=G71,0,F71<>G71,(F71-G71)/(G71))} -> 9 | J71: =VLOOKUP($E71,статьи!$G$2:$I$24,2,) -> Манипулирование рынком, если это действие не содержит уголовно наказуемого деяния
A72: 69 | B72: 23.12.2025 | C72: ОБЩЕСТВО С ОГРАНИЧЕННОЙ ОТВЕТСТВЕННОСТЬЮ "НАРОДНАЯ ИНВЕСТИЦИОННАЯ ПЛАТФОРМА" | D72: Юридическое лицо | E72: ч.9 ст.19.5 КоАП РФ | F72: 250000 | G72: 500000 | H72: 700000 | I72: {=_xlfn.IFS(F72=H72,1,F72=G72,0,F72<>G72,(F72-G72)/(G72))} -> -0.5 | J72: =VLOOKUP($E72,статьи!$G$2:$I$24,2,) -> 9. Невыполнение в установленный срок законного предписания Банка России, за исключением случаев, предусмотренных частью 9.1 настоящей статьи, -
A73: 70 | B73: 23.12.2025 | C73: Акционерное общество «Управляющая компания «Первая» | D73: Юридическое лицо | E73: ч.6 ст.15.29 КоАП РФ | F73: 700000 | G73: 700000 | H73: 1000000 | I73: {=_xlfn.IFS(F73=H73,1,F73=G73,0,F73<>G73,(F73-G73)/(G73))} -> 0 | J73: =VLOOKUP($E73,статьи!$G$2:$I$24,2,) -> Нарушение управляющей компанией акционерного инвестиционного фонда или паевого инвестиционного фонда предусмотренных федеральными законами и иными нормативными правовыми актами Российской Федерации ограничений ее деятельности -
A74: 71 | B74: 23.12.2025 | C74: Акционерное общество_x000D_ «Контрада Капитал» | D74: Юридическое лицо | E74: ч.12 ст.15.29 КоАП РФ | F74: 150000 | G74: 300000 | H74: 500000 | I74: {=_xlfn.IFS(F74=H74,1,F74=G74,0,F74<>G74,(F74-G74)/(G74))} -> -0.5 | J74: =VLOOKUP($E74,статьи!$G$2:$I$24,2,) -> Иное нарушение профессиональным участником рынка ценных бумаг, репозитарием, клиринговой организацией, лицом, осуществляющим функции центрального контрагента, акционерным инвестиционным фондом, негосударственным пенсионным фондом, управляющей компанией акционерного инвестиционного фонда, паевого инвестиционного фонда или негосударственного пенсионного фонда либо специализированным депозитарием акционерного инвестиционного фонда, паевого инвестиционного фонда или негосударственного пенсионного фонда при осуществлении ими соответствующих видов деятельности установленных законодательством требований к этим видам деятельности, за исключением случаев, предусмотренных частями 1 - 11 настоящей статьи, статьями 13.25, 15.18 - 15.20, 15.22, 15.23.1, 15.24.1, 15.30 и 19.7.3 настоящего Кодекса
A75: 71 | B75: 23.12.2025 | C75: Акционерное общество_x000D_ «Контрада Капитал» | D75: Юридическое лицо | E75: ч.6 ст.15.29 КоАП РФ | F75: 350000 | G75: 700000 | H75: 1000000 | I75: {=_xlfn.IFS(F75=H75,1,F75=G75,0,F75<>G75,(F75-G75)/(G75))} -> -0.5 | J75: =VLOOKUP($E75,статьи!$G$2:$I$24,2,) -> Нарушение управляющей компанией акционерного инвестиционного фонда или паевого инвестиционного фонда предусмотренных федеральными законами и иными нормативными правовыми актами Российской Федерации ограничений ее деятельности -
A76: 72 | B76: 19.12.2025 | C76: Общество с ограниченной ответственностью "ТОРГОВАЯ СИСТЕМА" | D76: Юридическое лицо | E76: ст.15.30 КоАП РФ | F76: 350000 | G76: 700000 | H76: в размере суммы излишнего дохода… но не менее 700 000 рублей | I76: {=_xlfn.IFS(F76=H76,1,F76=G76,0,F76<>G76,(F76-G76)/(G76))} -> -0.5 | J76: =VLOOKUP($E76,статьи!$G$2:$I$24,2,) -> Манипулирование рынком, если это действие не содержит уголовно наказуемого деяния
A77: 73 | B77: 19.12.2025 | C77: Кривова Надежда Юнусовна | D77: Гражданин | E77: ст.15.30 КоАП РФ | F77: 3000 | G77: 3000 | H77: 5000 | I77: {=_xlfn.IFS(F77=H77,1,F77=G77,0,F77<>G77,(F77-G77)/(G77))} -> 0 | J77: =VLOOKUP($E77,статьи!$G$2:$I$24,2,) -> Манипулирование рынком, если это действие не содержит уголовно наказуемого деяния
A78: 74 | B78: 19.12.2025 | C78: Кривов Вадим Иванович | D78: Гражданин | E78: ст.15.30 КоАП РФ | F78: 3000 | G78: 3000 | H78: 5000 | I78: {=_xlfn.IFS(F78=H78,1,F78=G78,0,F78<>G78,(F78-G78)/(G78))} -> 0 | J78: =VLOOKUP($E78,статьи!$G$2:$I$24,2,) -> Манипулирование рынком, если это действие не содержит уголовно наказуемого деяния
A79: 75 | B79: 19.12.2025 | C79: Общество с ограниченной_x000D_ ответственностью_x000D_ «Совкомбанк Управление_x000D_ Активами» | D79: Юридическое лицо | E79: ч.12 ст.15.29 КоАП РФ | F79: предупреждение | G79: 300000 | H79: 500000 | I79: {=_xlfn.IFS(F79=H79,1,F79=G79,0,F79<>G79,(F79-G79)/(G79))} -> #VALUE! | J79: =VLOOKUP($E79,статьи!$G$2:$I$24,2,) -> Иное нарушение профессиональным участником рынка ценных бумаг, репозитарием, клиринговой организацией, лицом, осуществляющим функции центрального контрагента, акционерным инвестиционным фондом, негосударственным пенсионным фондом, управляющей компанией акционерного инвестиционного фонда, паевого инвестиционного фонда или негосударственного пенсионного фонда либо специализированным депозитарием акционерного инвестиционного фонда, паевого инвестиционного фонда или негосударственного пенсионного фонда при осуществлении ими соответствующих видов деятельности установленных законодательством требований к этим видам деятельности, за исключением случаев, предусмотренных частями 1 - 11 настоящей статьи, статьями 13.25, 15.18 - 15.20, 15.22, 15.23.1, 15.24.1, 15.30 и 19.7.3 настоящего Кодекса
A80: 76 | B80: 16.12.2025 | C80: Общество с ограниченной ответственностью "Зитрон" | D80: Юридическое лицо | E80: ст.15.30 КоАП РФ | F80: 350000 | G80: 700000 | H80: в размере суммы излишнего дохода… но не менее 700 000 рублей | I80: {=_xlfn.IFS(F80=H80,1,F80=G80,0,F80<>G80,(F80-G80)/(G80))} -> -0.5 | J80: =VLOOKUP($E80,статьи!$G$2:$I$24,2,) -> Манипулирование рынком, если это действие не содержит уголовно наказуемого деяния
A81: 77 | B81: 16.12.2025 | C81: Акционерное общество «НРК-Р.О.С.Т.» | D81: Юридическое лицо | E81: ч.7 ст.15.29 КоАП РФ | F81: 500000 | G81: 500000 | H81: 700000 | I81: {=_xlfn.IFS(F81=H81,1,F81=G81,0,F81<>G81,(F81-G81)/(G81))} -> 0 | J81: =VLOOKUP($E81,статьи!$G$2:$I$24,2,) -> Неисполнение или ненадлежащее исполнение специализированным депозитарием акционерного инвестиционного фонда, паевого инвестиционного фонда или негосударственного пенсионного фонда установленных федеральными законами и иными нормативными правовыми актами Российской Федерации обязанностей по учету и хранению имущества, а также по осуществлению контроля за распоряжением имуществом, за исключением случая, предусмотренного частью 8 настоящей статьи
A82: 78 | B82: 16.12.2025 | C82: Общество с ограниченной ответственностью «Бюро кредитных историй КредитИнфо» | D82: Юридическое лицо | E82: ч.1 ст.19.7.3 КоАП РФ | F82: 500000 | G82: 500000 | H82: 700000 | I82: {=_xlfn.IFS(F82=H82,1,F82=G82,0,F82<>G82,(F82-G82)/(G82))} -> 0 | J82: =VLOOKUP($E82,статьи!$G$2:$I$24,2,) -> 1. Непредставление или нарушение порядка либо сроков представления в Банк России отчетов, уведомлений и иной информации, предусмотренной законодательством и (или) необходимой для осуществления этим органом (должностным лицом) его законной деятельности, либо представление информации не в полном объеме и (или) недостоверной информации, за исключением случаев, если в соответствии со страховым законодательством, законодательством Российской Федерации о кредитной кооперации, о сельскохозяйственной кооперации, о микрофинансовой деятельности и микрофинансовых организациях или о ломбардах Банком России дается законное предписание об устранении нарушения страхового законодательства, законодательства Российской Федерации о кредитной кооперации, о сельскохозяйственной кооперации, о микрофинансовой деятельности и микрофинансовых организациях или о ломбардах, и случаев, указанных в части 2 настоящей статьи, если эти действия (бездействие) не содержат признаков уголовно наказуемого деяния
A83: 79 | B83: 16.12.2025 | C83: Общество с ограниченной ответственностью «Апрель Капитал Брокер» | D83: Юридическое лицо | E83: ч.2 ст.15.29 КоАП РФ | F83: предупреждение | G83: 500000 | H83: 700000 | I83: {=_xlfn.IFS(F83=H83,1,F83=G83,0,F83<>G83,(F83-G83)/(G83))} -> #VALUE! | J83: =VLOOKUP($E83,статьи!$G$2:$I$24,2,) -> Нарушение профессиональным участником рынка ценных бумаг, осуществляющим брокерскую или дилерскую деятельность либо деятельность по управлению ценными бумагами, установленных нормативными правовыми актами Российской Федерации правил ведения учета и составления отчетности
A84: 80 | B84: 15.12.2025 | C84: Акционерное общество_x000D_ «Всероссийский банк_x000D_ развития регионов» | D84: Юридическое лицо | E84: ч.12 ст.15.29 КоАП РФ | F84: предупреждение | G84: 300000 | H84: 500000 | I84: {=_xlfn.IFS(F84=H84,1,F84=G84,0,F84<>G84,(F84-G84)/(G84))} -> #VALUE! | J84: =VLOOKUP($E84,статьи!$G$2:$I$24,2,) -> Иное нарушение профессиональным участником рынка ценных бумаг, репозитарием, клиринговой организацией, лицом, осуществляющим функции центрального контрагента, акционерным инвестиционным фондом, негосударственным пенсионным фондом, управляющей компанией акционерного инвестиционного фонда, паевого инвестиционного фонда или негосударственного пенсионного фонда либо специализированным депозитарием акционерного инвестиционного фонда, паевого инвестиционного фонда или негосударственного пенсионного фонда при осуществлении ими соответствующих видов деятельности установленных законодательством требований к этим видам деятельности, за исключением случаев, предусмотренных частями 1 - 11 настоящей статьи, статьями 13.25, 15.18 - 15.20, 15.22, 15.23.1, 15.24.1, 15.30 и 19.7.3 настоящего Кодекса
A85: 81 | B85: 12.12.2025 | C85: Денисова Екатерина Алексеевна | D85: Гражданин | E85: ст.15.30 КоАП РФ | F85: 3000 | G85: 3000 | H85: 5000 | I85: {=_xlfn.IFS(F85=H85,1,F85=G85,0,F85<>G85,(F85-G85)/(G85))} -> 0 | J85: =VLOOKUP($E85,статьи!$G$2:$I$24,2,) -> Манипулирование рынком, если это действие не содержит уголовно наказуемого деяния
A86: 82 | B86: 11.12.2025 | C86: Абхаликов Марсель Абдулвалеевич | D86: Гражданин | E86: ст.15.30 КоАП РФ | F86: 3000 | G86: 3000 | H86: 5000 | I86: {=_xlfn.IFS(F86=H86,1,F86=G86,0,F86<>G86,(F86-G86)/(G86))} -> 0 | J86: =VLOOKUP($E86,статьи!$G$2:$I$24,2,) -> Манипулирование рынком, если это действие не содержит уголовно наказуемого деяния
A87: 83 | B87: 10.12.2025 | C87: Богачев Алексей Анатольевич | D87: Гражданин | E87: ст.15.30 КоАП РФ | F87: 3000 | G87: 3000 | H87: 5000 | I87: {=_xlfn.IFS(F87=H87,1,F87=G87,0,F87<>G87,(F87-G87)/(G87))} -> 0 | J87: =VLOOKUP($E87,статьи!$G$2:$I$24,2,) -> Манипулирование рынком, если это действие не содержит уголовно наказуемого деяния
A88: 84 | B88: 09.12.2025 | C88: Акционерное общество «Управляющая компания «Парадигма» | D88: Юридическое лицо | E88: ч.12 ст.15.29 КоАП РФ | F88: предупреждение | G88: 300000 | H88: 500000 | I88: {=_xlfn.IFS(F88=H88,1,F88=G88,0,F88<>G88,(F88-G88)/(G88))} -> #VALUE! | J88: =VLOOKUP($E88,статьи!$G$2:$I$24,2,) -> Иное нарушение профессиональным участником рынка ценных бумаг, репозитарием, клиринговой организацией, лицом, осуществляющим функции центрального контрагента, акционерным инвестиционным фондом, негосударственным пенсионным фондом, управляющей компанией акционерного инвестиционного фонда, паевого инвестиционного фонда или негосударственного пенсионного фонда либо специализированным депозитарием акционерного инвестиционного фонда, паевого инвестиционного фонда или негосударственного пенсионного фонда при осуществлении ими соответствующих видов деятельности установленных законодательством требований к этим видам деятельности, за исключением случаев, предусмотренных частями 1 - 11 настоящей статьи, статьями 13.25, 15.18 - 15.20, 15.22, 15.23.1, 15.24.1, 15.30 и 19.7.3 настоящего Кодекса
A89: 85 | B89: 08.12.2025 | C89: Сысун Константин Валерьевич | D89: Гражданин | E89: ст.15.30 КоАП РФ | F89: 3000 | G89: 3000 | H89: 5000 | I89: {=_xlfn.IFS(F89=H89,1,F89=G89,0,F89<>G89,(F89-G89)/(G89))} -> 0 | J89: =VLOOKUP($E89,статьи!$G$2:$I$24,2,) -> Манипулирование рынком, если это действие не содержит уголовно наказуемого деяния
A90: 86 | B90: 08.12.2025 | C90: Краснов Борис Владимирович | D90: Гражданин | E90: ст.15.30 КоАП РФ | F90: 3000 | G90: 3000 | H90: 5000 | I90: {=_xlfn.IFS(F90=H90,1,F90=G90,0,F90<>G90,(F90-G90)/(G90))} -> 0 | J90: =VLOOKUP($E90,статьи!$G$2:$I$24,2,) -> Манипулирование рынком, если это действие не содержит уголовно наказуемого деяния
A91: 87 | B91: 05.12.2025 | C91: Общество с ограниченной ответственностью «МКБ Инвестиции» | D91: Юридическое лицо | E91: ч.9 ст.15.29 КоАП РФ | F91: 700000 | G91: 700000 | H91: 1000000 | I91: {=_xlfn.IFS(F91=H91,1,F91=G91,0,F91<>G91,(F91-G91)/(G91))} -> 0 | J91: =VLOOKUP($E91,статьи!$G$2:$I$24,2,) -> Воспрепятствование профессиональным участником рынка ценных бумаг, клиринговой организацией, лицом, осуществляющим функции центрального контрагента, акционерным инвестиционным фондом, негосударственным пенсионным фондом, управляющей компанией акционерного инвестиционного фонда, паевого инвестиционного фонда или негосударственного пенсионного фонда либо специализированным депозитарием акционерного инвестиционного фонда, паевого инвестиционного фонда или негосударственного пенсионного фонда проведению Банком России проверок либо неисполнение или ненадлежащее исполнение предписаний Банка России
A92: 88 | B92: 05.12.2025 | C92: Акционерное общество «Негосударственный пенсионный фонд «БЛАГОСОСТОЯНИЕ» | D92: Юридическое лицо | E92: ч.9 ст.15.29 КоАП РФ | F92: 700000 | G92: 700000 | H92: 1000000 | I92: {=_xlfn.IFS(F92=H92,1,F92=G92,0,F92<>G92,(F92-G92)/(G92))} -> 0 | J92: =VLOOKUP($E92,статьи!$G$2:$I$24,2,) -> Воспрепятствование профессиональным участником рынка ценных бумаг, клиринговой организацией, лицом, осуществляющим функции центрального контрагента, акционерным инвестиционным фондом, негосударственным пенсионным фондом, управляющей компанией акционерного инвестиционного фонда, паевого инвестиционного фонда или негосударственного пенсионного фонда либо специализированным депозитарием акционерного инвестиционного фонда, паевого инвестиционного фонда или негосударственного пенсионного фонда проведению Банком России проверок либо неисполнение или ненадлежащее исполнение предписаний Банка России
A93: 89 | B93: 02.12.2025 | C93: Акционерное общество «Инвестиционная компания «РИКОМ-ТРАСТ» | D93: Юридическое лицо | E93: ч.2 ст.15.19 КоАП РФ | F93: 700000 | G93: 700000 | H93: 1000000 | I93: {=_xlfn.IFS(F93=H93,1,F93=G93,0,F93<>G93,(F93-G93)/(G93))} -> 0 | J93: =VLOOKUP($E93,статьи!$G$2:$I$24,2,) -> 2. Нераскрытие или нарушение эмитентом, профессиональным участником рынка ценных бумаг, клиринговой организацией, акционерным инвестиционным фондом, управляющей компанией акционерного инвестиционного фонда, паевого инвестиционного фонда или негосударственного пенсионного фонда, специализированным депозитарием акционерного инвестиционного фонда, паевого инвестиционного фонда или негосударственного пенсионного фонда либо лицом, оказывающим услуги по публичному представлению раскрываемой информации, порядка и сроков раскрытия информации, предусмотренной федеральными законами и принятыми в соответствии с ними иными нормативными правовыми актами, а равно раскрытие информации не в полном объеме, и (или) недостоверной информации, и (или) вводящей в заблуждение информации
A94: 90 | B94: 28.11.2025 | C94: Акционерное общество "Национальное бюро кредитных историй! | D94: Юридическое лицо | E94: ст.14.30 КоАП РФ | F94: 10000 | G94: 10000 | H94: 20000 | I94: {=_xlfn.IFS(F94=H94,1,F94=G94,0,F94<>G94,(F94-G94)/(G94))} -> 0 | J94: =VLOOKUP($E94,статьи!$G$2:$I$24,2,) -> Нарушение бюро кредитных историй установленного порядка сбора, хранения, защиты и обработки сведений, составляющих кредитную историю
A95: 91 | B95: 25.11.2025 | C95: Акционерное общество «Инвестиционная компания «РИКОМ-ТРАСТ» | D95: Юридическое лицо | E95: ч.1 ст.19.7.3 КоАП РФ | F95: 700000 | G95: 500000 | H95: 700000 | I95: {=_xlfn.IFS(F95=H95,1,F95=G95,0,F95<>G95,(F95-G95)/(G95))} -> 1 | J95: =VLOOKUP($E95,статьи!$G$2:$I$24,2,) -> 1. Непредставление или нарушение порядка либо сроков представления в Банк России отчетов, уведомлений и иной информации, предусмотренной законодательством и (или) необходимой для осуществления этим органом (должностным лицом) его законной деятельности, либо представление информации не в полном объеме и (или) недостоверной информации, за исключением случаев, если в соответствии со страховым законодательством, законодательством Российской Федерации о кредитной кооперации, о сельскохозяйственной кооперации, о микрофинансовой деятельности и микрофинансовых организациях или о ломбардах Банком России дается законное предписание об устранении нарушения страхового законодательства, законодательства Российской Федерации о кредитной кооперации, о сельскохозяйственной кооперации, о микрофинансовой деятельности и микрофинансовых организациях или о ломбардах, и случаев, указанных в части 2 настоящей статьи, если эти действия (бездействие) не содержат признаков уголовно наказуемого деяния
A96: 92 | B96: 25.11.2025 | C96: Акционерное общество «ТБанк» | D96: Юридическое лицо | E96: ч.2 ст.15.19 КоАП РФ | F96: 700000 | G96: 700000 | H96: 1000000 | I96: {=_xlfn.IFS(F96=H96,1,F96=G96,0,F96<>G96,(F96-G96)/(G96))} -> 0 | J96: =VLOOKUP($E96,статьи!$G$2:$I$24,2,) -> 2. Нераскрытие или нарушение эмитентом, профессиональным участником рынка ценных бумаг, клиринговой организацией, акционерным инвестиционным фондом, управляющей компанией акционерного инвестиционного фонда, паевого инвестиционного фонда или негосударственного пенсионного фонда, специализированным депозитарием акционерного инвестиционного фонда, паевого инвестиционного фонда или негосударственного пенсионного фонда либо лицом, оказывающим услуги по публичному представлению раскрываемой информации, порядка и сроков раскрытия информации, предусмотренной федеральными законами и принятыми в соответствии с ними иными нормативными правовыми актами, а равно раскрытие информации не в полном объеме, и (или) недостоверной информации, и (или) вводящей в заблуждение информации
A97: 93 | B97: 25.11.2025 | C97: Акционерное общество «Райффайзенбанк» | D97: Юридическое лицо | E97: ч.2 ст.15.19 КоАП РФ | F97: 700000 | G97: 700000 | H97: 1000000 | I97: {=_xlfn.IFS(F97=H97,1,F97=G97,0,F97<>G97,(F97-G97)/(G97))} -> 0 | J97: =VLOOKUP($E97,статьи!$G$2:$I$24,2,) -> 2. Нераскрытие или нарушение эмитентом, профессиональным участником рынка ценных бумаг, клиринговой организацией, акционерным инвестиционным фондом, управляющей компанией акционерного инвестиционного фонда, паевого инвестиционного фонда или негосударственного пенсионного фонда, специализированным депозитарием акционерного инвестиционного фонда, паевого инвестиционного фонда или негосударственного пенсионного фонда либо лицом, оказывающим услуги по публичному представлению раскрываемой информации, порядка и сроков раскрытия информации, предусмотренной федеральными законами и принятыми в соответствии с ними иными нормативными правовыми актами, а равно раскрытие информации не в полном объеме, и (или) недостоверной информации, и (или) вводящей в заблуждение информации
A98: 94 | B98: 25.11.2025 | C98: Общество с ограниченной ответственностью Управляющая компания «Надежное управление» | D98: Юридическое лицо | E98: ч.12 ст.15.29 КоАП РФ | F98: 160000 | G98: 300000 | H98: 500000 | I98: {=_xlfn.IFS(F98=H98,1,F98=G98,0,F98<>G98,(F98-G98)/(G98))} -> -0.46666667 | J98: =VLOOKUP($E98,статьи!$G$2:$I$24,2,) -> Иное нарушение профессиональным участником рынка ценных бумаг, репозитарием, клиринговой организацией, лицом, осуществляющим функции центрального контрагента, акционерным инвестиционным фондом, негосударственным пенсионным фондом, управляющей компанией акционерного инвестиционного фонда, паевого инвестиционного фонда или негосударственного пенсионного фонда либо специализированным депозитарием акционерного инвестиционного фонда, паевого инвестиционного фонда или негосударственного пенсионного фонда при осуществлении ими соответствующих видов деятельности установленных законодательством требований к этим видам деятельности, за исключением случаев, предусмотренных частями 1 - 11 настоящей статьи, статьями 13.25, 15.18 - 15.20, 15.22, 15.23.1, 15.24.1, 15.30 и 19.7.3 настоящего Кодекса
A99: 95 | B99: 24.11.2025 | C99: Агамирова Ламара Бегларовна | D99: Гражданин | E99: ст.15.30 КоАП РФ | F99: 3000 | G99: 3000 | H99: 5000 | I99: {=_xlfn.IFS(F99=H99,1,F99=G99,0,F99<>G99,(F99-G99)/(G99))} -> 0 | J99: =VLOOKUP($E99,статьи!$G$2:$I$24,2,) -> Манипулирование рынком, если это действие не содержит уголовно наказуемого деяния
A100: 96 | B100: 24.11.2025 | C100: Третьякова Надежда Яковлевна | D100: Гражданин | E100: ст.15.30 КоАП РФ | F100: 3000 | G100: 3000 | H100: 5000 | I100: {=_xlfn.IFS(F100=H100,1,F100=G100,0,F100<>G100,(F100-G100)/(G100))} -> 0 | J100: =VLOOKUP($E100,статьи!$G$2:$I$24,2,) -> Манипулирование рынком, если это действие не содержит уголовно наказуемого деяния
A101: 97 | B101: 24.11.2025 | C101: ООО УК «ФИН-Партнер» | D101: Юридическое лицо | E101: ч.12 ст.15.29 КоАП РФ | F101: предупреждение | G101: 300000 | H101: 500000 | I101: {=_xlfn.IFS(F101=H101,1,F101=G101,0,F101<>G101,(F101-G101)/(G101))} -> #VALUE! | J101: =VLOOKUP($E101,статьи!$G$2:$I$24,2,) -> Иное нарушение профессиональным участником рынка ценных бумаг, репозитарием, клиринговой организацией, лицом, осуществляющим функции центрального контрагента, акционерным инвестиционным фондом, негосударственным пенсионным фондом, управляющей компанией акционерного инвестиционного фонда, паевого инвестиционного фонда или негосударственного пенсионного фонда либо специализированным депозитарием акционерного инвестиционного фонда, паевого инвестиционного фонда или негосударственного пенсионного фонда при осуществлении ими соответствующих видов деятельности установленных законодательством требований к этим видам деятельности, за исключением случаев, предусмотренных частями 1 - 11 настоящей статьи, статьями 13.25, 15.18 - 15.20, 15.22, 15.23.1, 15.24.1, 15.30 и 19.7.3 настоящего Кодекса
A102: 98 | B102: 24.11.2025 | C102: Акционерное общество «СОЛИД Менеджмент» | D102: Юридическое лицо | E102: ч.2 ст.15.19 КоАП РФ | F102: 350000 | G102: 700000 | H102: 1000000 | I102: {=_xlfn.IFS(F102=H102,1,F102=G102,0,F102<>G102,(F102-G102)/(G102))} -> -0.5 | J102: =VLOOKUP($E102,статьи!$G$2:$I$24,2,) -> 2. Нераскрытие или нарушение эмитентом, профессиональным участником рынка ценных бумаг, клиринговой организацией, акционерным инвестиционным фондом, управляющей компанией акционерного инвестиционного фонда, паевого инвестиционного фонда или негосударственного пенсионного фонда, специализированным депозитарием акционерного инвестиционного фонда, паевого инвестиционного фонда или негосударственного пенсионного фонда либо лицом, оказывающим услуги по публичному представлению раскрываемой информации, порядка и сроков раскрытия информации, предусмотренной федеральными законами и принятыми в соответствии с ними иными нормативными правовыми актами, а равно раскрытие информации не в полном объеме, и (или) недостоверной информации, и (или) вводящей в заблуждение информации
A103: 98 | B103: 24.11.2025 | C103: Акционерное общество «СОЛИД Менеджмент» | D103: Юридическое лицо | E103: ч.2 ст.15.19 КоАП РФ | F103: 350000 | G103: 700000 | H103: 1000000 | I103: {=_xlfn.IFS(F103=H103,1,F103=G103,0,F103<>G103,(F103-G103)/(G103))} -> -0.5 | J103: =VLOOKUP($E103,статьи!$G$2:$I$24,2,) -> 2. Нераскрытие или нарушение эмитентом, профессиональным участником рынка ценных бумаг, клиринговой организацией, акционерным инвестиционным фондом, управляющей компанией акционерного инвестиционного фонда, паевого инвестиционного фонда или негосударственного пенсионного фонда, специализированным депозитарием акционерного инвестиционного фонда, паевого инвестиционного фонда или негосударственного пенсионного фонда либо лицом, оказывающим услуги по публичному представлению раскрываемой информации, порядка и сроков раскрытия информации, предусмотренной федеральными законами и принятыми в соответствии с ними иными нормативными правовыми актами, а равно раскрытие информации не в полном объеме, и (или) недостоверной информации, и (или) вводящей в заблуждение информации
...

Sheet статьи
G2: статья | H2: содержание | I2: ссылка
G3: ч.9 ст.15.29 КоАП РФ | H3: Воспрепятствование профессиональным участником рынка ценных бумаг, клиринговой организацией, лицом, осуществляющим функции центрального контрагента, акционерным инвестиционным фондом, негосударственным пенсионным фондом, управляющей компанией акционерного инвестиционного фонда, паевого инвестиционного фонда или негосударственного пенсионного фонда либо специализированным депозитарием акционерного инвестиционного фонда, паевого инвестиционного фонда или негосударственного пенсионного фонда проведению Банком России проверок либо неисполнение или ненадлежащее исполнение предписаний Банка России | I3: 15.29
G4: ч.6 ст.15.29 КоАП РФ | H4: Нарушение управляющей компанией акционерного инвестиционного фонда или паевого инвестиционного фонда предусмотренных федеральными законами и иными нормативными правовыми актами Российской Федерации ограничений ее деятельности - | I4: 15.29
G5: ч.12 ст.15.29 КоАП РФ | H5: Иное нарушение профессиональным участником рынка ценных бумаг, репозитарием, клиринговой организацией, лицом, осуществляющим функции центрального контрагента, акционерным инвестиционным фондом, негосударственным пенсионным фондом, управляющей компанией акционерного инвестиционного фонда, паевого инвестиционного фонда или негосударственного пенсионного фонда либо специализированным депозитарием акционерного инвестиционного фонда, паевого инвестиционного фонда или негосударственного пенсионного фонда при осуществлении ими соответствующих видов деятельности установленных законодательством требований к этим видам деятельности, за исключением случаев, предусмотренных частями 1 - 11 настоящей статьи, статьями 13.25, 15.18 - 15.20, 15.22, 15.23.1, 15.24.1, 15.30 и 19.7.3 настоящего Кодекса | I5: 15.29
G6: ч.5 ст.15.29 КоАП РФ | H6: Нарушение установленных нормативными правовыми актами Российской Федерации и инвестиционной декларацией акционерного инвестиционного фонда или паевого инвестиционного фонда требований к составу активов акционерных инвестиционных фондов или паевых инвестиционных фондов либо неустранение нарушений в структуре активов акционерных инвестиционных фондов или паевых инвестиционных фондов - | I6: 15.29
G7: ст.15.30 КоАП РФ | H7: Манипулирование рынком, если это действие не содержит уголовно наказуемого деяния | I7: 15.30
G8: ч.9 ст.19.5 КоАП РФ | H8: 9. Невыполнение в установленный срок законного предписания Банка России, за исключением случаев, предусмотренных частью 9.1 настоящей статьи, - | I8: 19.5
G9: ч.1 ст.19.7.3 КоАП РФ | H9: 1. Непредставление или нарушение порядка либо сроков представления в Банк России отчетов, уведомлений и иной информации, предусмотренной законодательством и (или) необходимой для осуществления этим органом (должностным лицом) его законной деятельности, либо представление информации не в полном объеме и (или) недостоверной информации, за исключением случаев, если в соответствии со страховым законодательством, законодательством Российской Федерации о кредитной кооперации, о сельскохозяйственной кооперации, о микрофинансовой деятельности и микрофинансовых организациях или о ломбардах Банком России дается законное предписание об устранении нарушения страхового законодательства, законодательства Российской Федерации о кредитной кооперации, о сельскохозяйственной кооперации, о микрофинансовой деятельности и микрофинансовых организациях или о ломбардах, и случаев, указанных в части 2 настоящей статьи, если эти действия (бездействие) не содержат признаков уголовно наказуемого деяния | I9: 19,7,3
G10: ч.2 ст.15.19 КоАП РФ | H10: 2. Нераскрытие или нарушение эмитентом, профессиональным участником рынка ценных бумаг, клиринговой организацией, акционерным инвестиционным фондом, управляющей компанией акционерного инвестиционного фонда, паевого инвестиционного фонда или негосударственного пенсионного фонда, специализированным депозитарием акционерного инвестиционного фонда, паевого инвестиционного фонда или негосударственного пенсионного фонда либо лицом, оказывающим услуги по публичному представлению раскрываемой информации, порядка и сроков раскрытия информации, предусмотренной федеральными законами и принятыми в соответствии с ними иными нормативными правовыми актами, а равно раскрытие информации не в полном объеме, и (или) недостоверной информации, и (или) вводящей в заблуждение информации | I10: 15.19
G11: ч.2 ст.15.29 КоАП РФ | H11: Нарушение профессиональным участником рынка ценных бумаг, осуществляющим брокерскую или дилерскую деятельность либо деятельность по управлению ценными бумагами, установленных нормативными правовыми актами Российской Федерации правил ведения учета и составления отчетности | I11: 15.29
G12: ч.7 ст.15.29 КоАП РФ | H12: Неисполнение или ненадлежащее исполнение специализированным депозитарием акционерного инвестиционного фонда, паевого инвестиционного фонда или негосударственного пенсионного фонда установленных федеральными законами и иными нормативными правовыми актами Российской Федерации обязанностей по учету и хранению имущества, а также по осуществлению контроля за распоряжением имуществом, за исключением случая, предусмотренного частью 8 настоящей статьи | I12: 15.29
G13: ст.14.30 КоАП РФ | H13: Нарушение бюро кредитных историй установленного порядка сбора, хранения, защиты и обработки сведений, составляющих кредитную историю | I13: 14.30
G14: ч.2 ст.5.54 КоАП РФ | H14: 2. Незаконный отказ бюро кредитных историй в исправлении недостоверной информации или неисполнение обязанности по исправлению недостоверной информации, содержащейся в кредитной истории (кредитном отчете) | I14: 5.54
G15: ч.1 ст.5.54 КоАП РФ | H15: 1. Непроведение проверки или несвоевременное проведение по требованию субъекта кредитной истории проверки бюро кредитных историй информации, содержащейся в кредитной истории (кредитном отчете) | I15: 5.54
G16: ч.4 ст.15.35 КоАП РФ | H16: 4. Неисполнение или ненадлежащее исполнение лицом обязанностей по принятию установленных законодательством мер, направленных на предотвращение, выявление и пресечение злоупотреблений на финансовых и товарных рынках | I16: 15.35
G17: ч.2 ст.15.35 КоАП РФ | H17: 2. Неисполнение или ненадлежащее исполнение лицами, обязанными вести список инсайдеров, обязанностей по ведению списка инсайдеров и уведомлению лиц, включенных в список инсайдеров. | I17: 15.35
G18: ч.7 ст.14.24 КоАП РФ | H18: 7. Нарушение организатором торговли правил организованных торгов, зарегистрированных в установленном законодательством об организованных торгах порядке | I18: 14.24
G19: ст.15.21 КоАП РФ | H19: Неправомерное использование инсайдерской информации, если это действие не содержит уголовно наказуемого деяния | I19: 15.21
G20: ст.5.55 КоАП РФ | H20: Непредоставление бюро кредитных историй кредитного отчета, предоставление неполного или недостоверного кредитного отчета, а также несвоевременное предоставление кредитного отчета в случаях, если такое предоставление осуществляется или должно осуществляться в соответствии с Федеральным законом "О кредитных историях" | I20: 5.55
... G24: ч.1 ст.13.25 КоАП РФ | H24: 1. Неисполнение акционерным обществом, профессиональным участником рынка ценных бумаг, управляющей компанией акционерного инвестиционного фонда, паевого инвестиционного фонда или негосударственного пенсионного фонда либо специализированным депозитарием акционерного инвестиционного фонда, паевого инвестиционного фонда или негосударственного пенсионного фонда обязанности по хранению документов, которые предусмотрены законодательством об акционерных обществах, о рынке ценных бумаг, об инвестиционных фондах и принятыми в соответствии с ним нормативными правовыми актами и хранение которых является обязательным, а также нарушение установленных порядка и сроков хранения таких документов | I24: 13.25

Sheet дашборды
A2: Тип лица | B2: (Все) | C2: указать год, проблема с объединением янв 2025 и 2026 года
A3: Штраф факт | B3: (Все)
A5: Названия строк | B5: Количество по полю Штраф факт
A6: 2025 | B6: 387
A7: янв | B7: 17
A8: февр | B8: 20
A9: март | B9: 33
A10: апр | B10: 33
A11: май | B11: 36
A12: июнь | B12: 22
A13: июль | B13: 29
A14: авг | B14: 31
A15: сент | B15: 24
A16: окт | B16: 51
A17: нояб | B17: 61
... A22: Общий итог | B22: 449
C23: объеденить самые нечастые и указать что их доля крайне мала, тоже круговая | N23: Штраф факт | O23: (Все)
N24: Тип лица | O24: Юридическое лицо | X24: в прочие входят
N26: Названия строк | O26: Количество по полю Штраф факт | X26: ч.6 ст.15.29 КоАП РФ | Y26: 10
A27: Тип лица | B27: Юридическое лицо | N27: ч.12 ст.15.29 КоАП РФ | O27: 68 | X27: ч.1 ст.5.54 КоАП РФ | Y27: 9
A28: Штраф факт | B28: (Все) | N28: Прочие ≤10 | O28: 46 | X28: ст.15.30 КоАП РФ | Y28: 5
N29: ч.9 ст.15.29 КоАП РФ | O29: 29 | X29: ч.5 ст.15.29 КоАП РФ | Y29: 5
A30: Названия строк | B30: Количество по полю Штраф факт | N30: ч.1 ст.19.7.3 КоАП РФ | O30: 28 | X30: ст.14.30 КоАП РФ | Y30: 3
A31: ч.12 ст.15.29 КоАП РФ | B31: 68 | N31: ч.2 ст.15.19 КоАП РФ | O31: 23 | X31: ст.5.55 КоАП РФ | Y31: 3
A32: ч.9 ст.15.29 КоАП РФ | B32: 29 | N32: ч.2 ст.15.29 КоАП РФ | O32: 23 | X32: ч.7 ст.15.29 КоАП РФ | Y32: 2
A33: ч.1 ст.19.7.3 КоАП РФ | B33: 28 | N33: ч.9 ст.19.5 КоАП РФ | O33: 20 | X33: ч.7 ст.14.24 КоАП РФ | Y33: 2
A34: ч.2 ст.15.19 КоАП РФ | B34: 23 | N34: Общий итог | O34: 237 | X34: ч.2 ст.15.35 КоАП РФ | Y34: 1
A35: ч.2 ст.15.29 КоАП РФ | B35: 23 | X35: ч.10 ст.15.29 КоАП РФ | Y35: 1
A36: ч.9 ст.19.5 КоАП РФ | B36: 20 | X36: ч.2 ст.5.54 КоАП РФ | Y36: 1
A37: ч.6 ст.15.29 КоАП РФ | B37: 10 | X37: ч.4 ст.15.35 КоАП РФ | Y37: 1
A38: ч.1 ст.5.54 КоАП РФ | B38: 9 | X38: ст.14.29 КоАП РФ | Y38: 1
A39: ст.15.30 КоАП РФ | B39: 5 | X39: ч.1 ст.13.25 КоАП РФ | Y39: 1
A40: ч.5 ст.15.29 КоАП РФ | B40: 5 | X40: ч.4 ст.15.19 КоАП РФ | Y40: 1
A41: ст.14.30 КоАП РФ | B41: 3
A42: ст.5.55 КоАП РФ | B42: 3
A43: ч.7 ст.15.29 КоАП РФ | B43: 2
A44: ч.7 ст.14.24 КоАП РФ | B44: 2
A45: ч.2 ст.15.35 КоАП РФ | B45: 1 | N45: Названия строк | O45: Сумма по полю Штраф факт
A46: ч.10 ст.15.29 КоАП РФ | B46: 1 | N46: Должностное лицо | O46: 30000
A47: ч.2 ст.5.54 КоАП РФ | B47: 1 | N47: Гражданин | O47: 821000
A48: ч.4 ст.15.35 КоАП РФ | B48: 1 | N48: Юридическое лицо | O48: 68820000
A49: ст.14.29 КоАП РФ | B49: 1 | N49: Общий итог | O49: 69671000
A50: ч.1 ст.13.25 КоАП РФ | B50: 1
A51: ч.4 ст.15.19 КоАП РФ | B51: 1
A52: Общий итог | B52: 237
C53: Круговая, доля выплат юриков среди всех админок
A55: Тип лица | B55: Юридическое лицо
A56: Штраф факт | B56: (несколько элементов)
A58: Названия строк | B58: Сумма по полю Штраф факт
A59: ч.9 ст.15.29 КоАП РФ | B59: 15300000
A60: ч.2 ст.15.19 КоАП РФ | B60: 11900000
A61: ч.12 ст.15.29 КоАП РФ | B61: 11630000
A62: ч.1 ст.19.7.3 КоАП РФ | B62: 9200000
A63: ч.2 ст.15.29 КоАП РФ | B63: 5300000
A64: ч.9 ст.19.5 КоАП РФ | B64: 5250000
A65: ч.6 ст.15.29 КоАП РФ | B65: 4550000
A66: ст.15.30 КоАП РФ | B66: 2450000
A67: ч.5 ст.15.29 КоАП РФ | B67: 1500000
A68: ч.7 ст.15.29 КоАП РФ | B68: 1000000
A69: ч.4 ст.15.35 КоАП РФ | B69: 300000
A70: ч.1 ст.5.54 КоАП РФ | B70: 180000 | Q70: Тип лица | R70: Юридическое лицо
A71: ч.1 ст.13.25 КоАП РФ | B71: 100000 | Q71: Штраф факт | R71: (Все)
A72: ст.5.55 КоАП РФ | B72: 50000
A73: ч.2 ст.5.54 КоАП РФ | B73: 50000 | Q73: Названия строк | R73: Количество по полю вид штрафа
A74: ст.14.29 КоАП РФ | B74: 30000 | Q74: В диапазоне | R74: 6
A75: ст.14.30 КоАП РФ | B75: 30000 | Q75: Минимум | R75: 86
A76: Общий итог | B76: 68820000 | Q76: Ниже минимума | R76: 63
Q77: Предупреждение | R77: 63
Q78: Максимум | R78: 19
Q79: Общий итог | R79: 237
A81: Тип лица | B81: Юридическое лицо
A82: Штраф факт | B82: (несколько элементов)
A84: Названия строк | B84: Среднее по полю мин | C84: Среднее по полю макс
A85: ст.14.29 КоАП РФ | B85: 30000 | C85: 50000
A86: ст.14.30 КоАП РФ | B86: 10000 | C86: 20000
A87: ст.15.30 КоАП РФ | B87: 700000 | C87: #DIV/0! | Q87: Названия строк | R87: Количество по полю Штраф факт
A88: ст.5.55 КоАП РФ | B88: 20000 | C88: 50000 | Q88: Гражданин | R88: 211
A89: ч.1 ст.13.25 КоАП РФ | B89: 200000 | C89: 300000 | Q89: Должностное лицо | R89: 1
A90: ч.1 ст.19.7.3 КоАП РФ | B90: 500000 | C90: 700000 | Q90: Юридическое лицо | R90: 237
A91: ч.1 ст.5.54 КоАП РФ | B91: 10000 | C91: 20000 | Q91: Общий итог | R91: 449
A92: ч.12 ст.15.29 КоАП РФ | B92: 300000 | C92: 500000
A93: ч.2 ст.15.19 КоАП РФ | B93: 700000 | C93: 1000000
A94: ч.2 ст.15.29 КоАП РФ | B94: 500000 | C94: 700000
A95: ч.2 ст.5.54 КоАП РФ | B95: 30000 | C95: 50000
A96: ч.4 ст.15.35 КоАП РФ | B96: 300000 | C96: 700000
A97: ч.5 ст.15.29 КоАП РФ | B97: 500000 | C97: 700000
A98: ч.6 ст.15.29 КоАП РФ | B98: 700000 | C98: 1000000
A99: ч.7 ст.15.29 КоАП РФ | B99: 500000 | C99: 700000
A100: ч.9 ст.15.29 КоАП РФ | B100: 700000 | C100: 1000000
A101: ч.9 ст.19.5 КоАП РФ | B101: 500000 | C101: 700000
A102: Общий итог | B102: 470114.94 | C102: 677455.62
A106: Тип лица | B106: Юридическое лицо | D106: сделать в виде круговой диаграммы с количеством случаев по категориям : Предупреждения, мин, макс и в диапозоне
A107: Штраф факт | B107: (несколько элементов)
A109: Названия строк | B109: Среднее по полю Превышышение над мин размером %/min
A110: ст.14.29 КоАП РФ | B110: 0
A111: ст.14.30 КоАП РФ | B111: 0
A112: ст.15.30 КоАП РФ | B112: -0.3
A113: ст.5.55 КоАП РФ | B113: 1
A114: ч.1 ст.13.25 КоАП РФ | B114: -0.5
A115: ч.1 ст.19.7.3 КоАП РФ | B115: 0.047619048
...

Sheet впр
B1: Статья | C1: Тип лица | D1: Мин штраф | E1: Макс штраф
A2: =B2&C2 -> ч.9 ст.15.29 КоАП РФЮридическое лицо | B2: ч.9 ст.15.29 КоАП РФ | C2: Юридическое лицо | D2: 700000 | E2: 1000000
A3: =B3&C3 -> ч.9 ст.15.29 КоАП РФДолжностное лицо | B3: ч.9 ст.15.29 КоАП РФ | C3: Должностное лицо | D3: 30000 | E3: 50000
A4: =B4&C4 -> ч.6 ст.15.29 КоАП РФЮридическое лицо | B4: ч.6 ст.15.29 КоАП РФ | C4: Юридическое лицо | D4: 700000 | E4: 1000000
A5: =B5&C5 -> ч.6 ст.15.29 КоАП РФДолжностное лицо | B5: ч.6 ст.15.29 КоАП РФ | C5: Должностное лицо | D5: 30000 | E5: 50000
A6: =B6&C6 -> ч.12 ст.15.29 КоАП РФГражданин | B6: ч.12 ст.15.29 КоАП РФ | C6: Гражданин | D6: 1000 | E6: 3000
A7: =B7&C7 -> ч.12 ст.15.29 КоАП РФДолжностное лицо | B7: ч.12 ст.15.29 КоАП РФ | C7: Должностное лицо | D7: 10000 | E7: 20000
A8: =B8&C8 -> ч.12 ст.15.29 КоАП РФЮридическое лицо | B8: ч.12 ст.15.29 КоАП РФ | C8: Юридическое лицо | D8: 300000 | E8: 500000
A9: =B9&C9 -> ч.5 ст.15.29 КоАП РФДолжностное лицо | B9: ч.5 ст.15.29 КоАП РФ | C9: Должностное лицо | D9: 20000 | E9: 30000
A10: =B10&C10 -> ч.5 ст.15.29 КоАП РФЮридическое лицо | B10: ч.5 ст.15.29 КоАП РФ | C10: Юридическое лицо | D10: 500000 | E10: 700000
A11: =B11&C11 -> ч.2 ст.15.29 КоАП РФДолжностное лицо | B11: ч.2 ст.15.29 КоАП РФ | C11: Должностное лицо | D11: 20000 | E11: 30000
A12: =B12&C12 -> ч.2 ст.15.29 КоАП РФЮридическое лицо | B12: ч.2 ст.15.29 КоАП РФ | C12: Юридическое лицо | D12: 500000 | E12: 700000
A13: =B13&C13 -> ч.7 ст.15.29 КоАП РФДолжностное лицо | B13: ч.7 ст.15.29 КоАП РФ | C13: Должностное лицо | D13: 20000 | E13: 30000
... A18: =B18&C18 -> ст.15.30 КоАП РФДолжностное лицо | B18: ст.15.30 КоАП РФ | C18: Должностное лицо | D18: 30000 | E18: 50000
A19: =B19&C19 -> ст.15.30 КоАП РФЮридическое лицо | B19: ст.15.30 КоАП РФ | C19: Юридическое лицо | D19: 700000 | E19: в размере суммы излишнего дохода… но не менее 700 000 рублей
A20: =B20&C20 -> ч.9 ст.19.5 КоАП РФДолжностное лицо | B20: ч.9 ст.19.5 КоАП РФ | C20: Должностное лицо | D20: 20000 | E20: 30000
A21: =B21&C21 -> ч.9 ст.19.5 КоАП РФЮридическое лицо | B21: ч.9 ст.19.5 КоАП РФ | C21: Юридическое лицо | D21: 500000 | E21: 700000
A22: =B22&C22 -> ч.1 ст.19.7.3 КоАП РФГражданин | B22: ч.1 ст.19.7.3 КоАП РФ | C22: Гражданин | D22: 2000 | E22: 4000
A23: =B23&C23 -> ч.1 ст.19.7.3 КоАП РФДолжностное лицо | B23: ч.1 ст.19.7.3 КоАП РФ | C23: Должностное лицо | D23: 20000 | E23: 30000
A24: =B24&C24 -> ч.1 ст.19.7.3 КоАП РФЮридическое лицо | B24: ч.1 ст.19.7.3 КоАП РФ | C24: Юридическое лицо | D24: 500000 | E24: 700000
A25: =B25&C25 -> ч.2 ст.15.19 КоАП РФДолжностное лицо | B25: ч.2 ст.15.19 КоАП РФ | C25: Должностное лицо | D25: 30000 | E25: 50000
A26: =B26&C26 -> ч.2 ст.15.19 КоАП РФЮридическое лицо | B26: ч.2 ст.15.19 КоАП РФ | C26: Юридическое лицо | D26: 700000 | E26: 1000000
A27: =B27&C27 -> ч.4 ст.15.19 КоАП РФДолжностное лицо | B27: ч.4 ст.15.19 КоАП РФ | C27: Должностное лицо | D27: 20000 | E27: 30000
A28: =B28&C28 -> ч.4 ст.15.19 КоАП РФЮридическое лицо | B28: ч.4 ст.15.19 КоАП РФ | C28: Юридическое лицо | D28: 300000 | E28: 500000
A29: =B29&C29 -> ст.14.30 КоАП РФДолжностное лицо | B29: ст.14.30 КоАП РФ | C29: Должностное лицо | D29: 2500 | E29: 5000
A30: =B30&C30 -> ст.14.30 КоАП РФЮридическое лицо | B30: ст.14.30 КоАП РФ | C30: Юридическое лицо | D30: 10000 | E30: 20000
A31: =B31&C31 -> ч.2 ст.5.54 КоАП РФДолжностное лицо | B31: ч.2 ст.5.54 КоАП РФ | C31: Должностное лицо | D31: 2000 | E31: 5000
... A42: =B42&C42 -> ст.15.21 КоАП РФДолжностное лицо | B42: ст.15.21 КоАП РФ | C42: Должностное лицо | D42: 30000 | E42: 50000
A43: =B43&C43 -> ст.15.21 КоАП РФЮридическое лицо | B43: ст.15.21 КоАП РФ | C43: Юридическое лицо | D43: 700000 | E43: в размере суммы излишнего дохода… но не менее 700 000 рублей
A44: =B44&C44 -> ст.5.55 КоАП РФДолжностное лицо | B44: ст.5.55 КоАП РФ | C44: Должностное лицо | D44: 1000 | E44: 2500
A45: =B45&C45 -> ст.5.55 КоАП РФЮридическое лицо | B45: ст.5.55 КоАП РФ | C45: Юридическое лицо | D45: 20000 | E45: 50000
A46: =B46&C46 -> ст.14.29 КоАП РФГражданин | B46: ст.14.29 КоАП РФ | C46: Гражданин | D46: 1000 | E46: 2500
A47: =B47&C47 -> ст.14.29 КоАП РФДолжностное лицо | B47: ст.14.29 КоАП РФ | C47: Должностное лицо | D47: 2500 | E47: 5000
A48: =B48&C48 -> ст.14.29 КоАП РФЮридическое лицо | B48: ст.14.29 КоАП РФ | C48: Юридическое лицо | D48: 30000 | E48: 50000
A49: =B49&C49 -> ч.1 ст.13.25 КоАП РФДолжностное лицо | B49: ч.1 ст.13.25 КоАП РФ | C49: Должностное лицо | D49: 2500 | E49: 5000
A50: =B50&C50 -> ч.1 ст.13.25 КоАП РФЮридическое лицо | B50: ч.1 ст.13.25 КоАП РФ | C50: Юридическое лицо | D50: 200000 | E50: 300000

Sheet копия
A1: Номер случая | B1: Дата постановления | C1: Субъект | D1: Тип лица | E1: Статья КоАП | F1: Штраф факт | G1: мин | H1: макс | I1: Превышышение над мин размером %/min | J1: вид штрафа
A2: 1 | B2: 46070 | C2: Акционерное общество «Негосударственный пенсионный фонд «Ростех» | D2: Юридическое лицо | E2: ч.9 ст.15.29 КоАП РФ | F2: 700000 | G2: 700000 | H2: 1000000 | I2: {=_xlfn.IFS(F2=H2,1,F2=G2,0,F2<>G2,(F2-G2)/(G2))} -> 0 | J2: =IF(ISERROR(I2),"Предупреждение", IF(I2<0,"Ниже минимума", IF(I2=0,"Минимум", IF(I2<1,"В диапазоне", IF(I2=1,"Максимум", "Выше максимума"))))) -> Минимум
A3: 2 | B3: 46070 | C3: Общество с ограниченной ответственностью «Управляющая компания_x000D_ «Атон-менеджмент» | D3: Юридическое лицо | E3: ч.6 ст.15.29 КоАП РФ | F3: 700000 | G3: 700000 | H3: 1000000 | I3: {=_xlfn.IFS(F3=H3,1,F3=G3,0,F3<>G3,(F3-G3)/(G3))} -> 0 | J3: =IF(ISERROR(I3),"Предупреждение", IF(I3<0,"Ниже минимума", IF(I3=0,"Минимум", IF(I3<1,"В диапазоне", IF(I3=1,"Максимум", "Выше максимума"))))) -> Минимум
A4: 2 | B4: 46070 | C4: Общество с ограниченной ответственностью «Управляющая компания_x000D_ «Атон-менеджмент» | D4: Юридическое лицо | E4: ч.12 ст.15.29 КоАП РФ | F4: 320000 | G4: 300000 | H4: 500000 | I4: {=_xlfn.IFS(F4=H4,1,F4=G4,0,F4<>G4,(F4-G4)/(G4))} -> 0.066666667 | J4: =IF(ISERROR(I4),"Предупреждение", IF(I4<0,"Ниже минимума", IF(I4=0,"Минимум", IF(I4<1,"В диапазоне", IF(I4=1,"Максимум", "Выше максимума"))))) -> В диапазоне
A5: 3 | B5: 46066 | C5: Акционерное общество_x000D_ Управляющая компания «Центр Эссет Менеджмент» | D5: Юридическое лицо | E5: ч.12 ст.15.29 КоАП РФ | F5: предупреждение | G5: 300000 | H5: 500000 | I5: {=_xlfn.IFS(F5=H5,1,F5=G5,0,F5<>G5,(F5-G5)/(G5))} -> #VALUE! | J5: =IF(ISERROR(I5),"Предупреждение", IF(I5<0,"Ниже минимума", IF(I5=0,"Минимум", IF(I5<1,"В диапазоне", IF(I5=1,"Максимум", "Выше максимума"))))) -> Предупреждение
A6: 4 | B6: 46063 | C6: АО «ИК «РИКОМ-ТРАСТ» | D6: Юридическое лицо | E6: ч.9 ст.15.29 КоАП РФ | F6: 1000000 | G6: 700000 | H6: 1000000 | I6: {=_xlfn.IFS(F6=H6,1,F6=G6,0,F6<>G6,(F6-G6)/(G6))} -> 1 | J6: =IF(ISERROR(I6),"Предупреждение", IF(I6<0,"Ниже минимума", IF(I6=0,"Минимум", IF(I6<1,"В диапазоне", IF(I6=1,"Максимум", "Выше максимума"))))) -> Максимум
A7: 5 | B7: 46063 | C7: Акционерное общество ВИМ Инвестиции | D7: Юридическое лицо | E7: ч.12 ст.15.29 КоАП РФ | F7: 350000 | G7: 300000 | H7: 500000 | I7: {=_xlfn.IFS(F7=H7,1,F7=G7,0,F7<>G7,(F7-G7)/(G7))} -> 0.16666667 | J7: =IF(ISERROR(I7),"Предупреждение", IF(I7<0,"Ниже минимума", IF(I7=0,"Минимум", IF(I7<1,"В диапазоне", IF(I7=1,"Максимум", "Выше максимума"))))) -> В диапазоне
A8: 6 | B8: 46063 | C8: Общество с ограниченной_x000D_ ответственностью_x000D_ «Управляющая компания_x000D_ «Ресурс» | D8: Юридическое лицо | E8: ч.6 ст.15.29 КоАП РФ | F8: предупреждение | G8: 700000 | H8: 1000000 | I8: {=_xlfn.IFS(F8=H8,1,F8=G8,0,F8<>G8,(F8-G8)/(G8))} -> #VALUE! | J8: =IF(ISERROR(I8),"Предупреждение", IF(I8<0,"Ниже минимума", IF(I8=0,"Минимум", IF(I8<1,"В диапазоне", IF(I8=1,"Максимум", "Выше максимума"))))) -> Предупреждение
A9: 7 | B9: 46063 | C9: Общество с ограниченной ответственностью «ТрастЮнион Эссет Менеджмент» | D9: Юридическое лицо | E9: ч.12 ст.15.29 КоАП РФ | F9: предупреждение | G9: 300000 | H9: 500000 | I9: {=_xlfn.IFS(F9=H9,1,F9=G9,0,F9<>G9,(F9-G9)/(G9))} -> #VALUE! | J9: =IF(ISERROR(I9),"Предупреждение", IF(I9<0,"Ниже минимума", IF(I9=0,"Минимум", IF(I9<1,"В диапазоне", IF(I9=1,"Максимум", "Выше максимума"))))) -> Предупреждение
A10: 8 | B10: 46063 | C10: Акционерное общество «Управляющая Компания ТРИНФИКО» | D10: Юридическое лицо | E10: ч.5 ст.15.29 КоАП РФ | F10: 250000 | G10: 500000 | H10: 700000 | I10: {=_xlfn.IFS(F10=H10,1,F10=G10,0,F10<>G10,(F10-G10)/(G10))} -> -0.5 | J10: =IF(ISERROR(I10),"Предупреждение", IF(I10<0,"Ниже минимума", IF(I10=0,"Минимум", IF(I10<1,"В диапазоне", IF(I10=1,"Максимум", "Выше максимума"))))) -> Ниже минимума
A11: 9 | B11: 46062 | C11: ООО «Цифра брокер» | D11: Юридическое лицо | E11: ч.12 ст.15.29 КоАП РФ | F11: 300000 | G11: 300000 | H11: 500000 | I11: {=_xlfn.IFS(F11=H11,1,F11=G11,0,F11<>G11,(F11-G11)/(G11))} -> 0 | J11: =IF(ISERROR(I11),"Предупреждение", IF(I11<0,"Ниже минимума", IF(I11=0,"Минимум", IF(I11<1,"В диапазоне", IF(I11=1,"Максимум", "Выше максимума"))))) -> Минимум
A12: 10 | B12: 46059 | C12: Голубков Виктор Владимирович | D12: Гражданин | E12: ст.15.30 КоАП РФ | F12: 3000 | G12: 3000 | H12: 5000 | I12: {=_xlfn.IFS(F12=H12,1,F12=G12,0,F12<>G12,(F12-G12)/(G12))} -> 0 | J12: =IF(ISERROR(I12),"Предупреждение", IF(I12<0,"Ниже минимума", IF(I12=0,"Минимум", IF(I12<1,"В диапазоне", IF(I12=1,"Максимум", "Выше максимума"))))) -> Минимум
A13: 11 | B13: 46059 | C13: генеральный директор общества с ограниченной ответственностью «Тринити Шиппинг» Ярошенко Александр Иванович | D13: Должностное лицо | E13: ст.15.30 КоАП РФ | F13: 30000 | G13: 30000 | H13: 50000 | I13: {=_xlfn.IFS(F13=H13,1,F13=G13,0,F13<>G13,(F13-G13)/(G13))} -> 0 | J13: =IF(ISERROR(I13),"Предупреждение", IF(I13<0,"Ниже минимума", IF(I13=0,"Минимум", IF(I13<1,"В диапазоне", IF(I13=1,"Максимум", "Выше максимума"))))) -> Минимум
A14: 12 | B14: 46059 | C14: Гальямова Наталья Александровна | D14: Гражданин | E14: ст.15.30 КоАП РФ | F14: 3000 | G14: 3000 | H14: 5000 | I14: {=_xlfn.IFS(F14=H14,1,F14=G14,0,F14<>G14,(F14-G14)/(G14))} -> 0 | J14: =IF(ISERROR(I14),"Предупреждение", IF(I14<0,"Ниже минимума", IF(I14=0,"Минимум", IF(I14<1,"В диапазоне", IF(I14=1,"Максимум", "Выше максимума"))))) -> Минимум
A15: 13 | B15: 46056 | C15: Чмыхало Юлия Анатольевна | D15: Гражданин | E15: ст.15.30 КоАП РФ | F15: 3000 | G15: 3000 | H15: 5000 | I15: {=_xlfn.IFS(F15=H15,1,F15=G15,0,F15<>G15,(F15-G15)/(G15))} -> 0 | J15: =IF(ISERROR(I15),"Предупреждение", IF(I15<0,"Ниже минимума", IF(I15=0,"Минимум", IF(I15<1,"В диапазоне", IF(I15=1,"Максимум", "Выше максимума"))))) -> Минимум
A16: 14 | B16: 46052 | C16: Усольцева Яна Германовна | D16: Гражданин | E16: ст.15.30 КоАП РФ | F16: 3000 | G16: 3000 | H16: 5000 | I16: {=_xlfn.IFS(F16=H16,1,F16=G16,0,F16<>G16,(F16-G16)/(G16))} -> 0 | J16: =IF(ISERROR(I16),"Предупреждение", IF(I16<0,"Ниже минимума", IF(I16=0,"Минимум", IF(I16<1,"В диапазоне", IF(I16=1,"Максимум", "Выше максимума"))))) -> Минимум
A17: 15 | B17: 46052 | C17: Краснова Галина Ивановна | D17: Гражданин | E17: ст.15.30 КоАП РФ | F17: 3000 | G17: 3000 | H17: 5000 | I17: {=_xlfn.IFS(F17=H17,1,F17=G17,0,F17<>G17,(F17-G17)/(G17))} -> 0 | J17: =IF(ISERROR(I17),"Предупреждение", IF(I17<0,"Ниже минимума", IF(I17=0,"Минимум", IF(I17<1,"В диапазоне", IF(I17=1,"Максимум", "Выше максимума"))))) -> Минимум
A18: 16 | B18: 46052 | C18: Артамонов Валерий Геннадьевич | D18: Гражданин | E18: ст.15.30 КоАП РФ | F18: 3000 | G18: 3000 | H18: 5000 | I18: {=_xlfn.IFS(F18=H18,1,F18=G18,0,F18<>G18,(F18-G18)/(G18))} -> 0 | J18: =IF(ISERROR(I18),"Предупреждение", IF(I18<0,"Ниже минимума", IF(I18=0,"Минимум", IF(I18<1,"В диапазоне", IF(I18=1,"Максимум", "Выше максимума"))))) -> Минимум
A19: 17 | B19: 46052 | C19: Манюкова Татьяна Васильевна | D19: Гражданин | E19: ст.15.30 КоАП РФ | F19: 3000 | G19: 3000 | H19: 5000 | I19: {=_xlfn.IFS(F19=H19,1,F19=G19,0,F19<>G19,(F19-G19)/(G19))} -> 0 | J19: =IF(ISERROR(I19),"Предупреждение", IF(I19<0,"Ниже минимума", IF(I19=0,"Минимум", IF(I19<1,"В диапазоне", IF(I19=1,"Максимум", "Выше максимума"))))) -> Минимум
A20: 18 | B20: 46052 | C20: Доценко Марина Сергеевна | D20: Гражданин | E20: ст.15.30 КоАП РФ | F20: 3000 | G20: 3000 | H20: 5000 | I20: {=_xlfn.IFS(F20=H20,1,F20=G20,0,F20<>G20,(F20-G20)/(G20))} -> 0 | J20: =IF(ISERROR(I20),"Предупреждение", IF(I20<0,"Ниже минимума", IF(I20=0,"Минимум", IF(I20<1,"В диапазоне", IF(I20=1,"Максимум", "Выше максимума"))))) -> Минимум
A21: 19 | B21: 46052 | C21: Гальямов Марсель Геральдович | D21: Гражданин | E21: ст.15.30 КоАП РФ | F21: 3000 | G21: 3000 | H21: 5000 | I21: {=_xlfn.IFS(F21=H21,1,F21=G21,0,F21<>G21,(F21-G21)/(G21))} -> 0 | J21: =IF(ISERROR(I21),"Предупреждение", IF(I21<0,"Ниже минимума", IF(I21=0,"Минимум", IF(I21<1,"В диапазоне", IF(I21=1,"Максимум", "Выше максимума"))))) -> Минимум
... A36: 34 | B36: 46041 | C36: Тихомиров Вадим Владимирович | D36: Гражданин | E36: ст.15.30 КоАП РФ | F36: 3000 | G36: 3000 | H36: 5000 | I36: {=_xlfn.IFS(F36=H36,1,F36=G36,0,F36<>G36,(F36-G36)/(G36))} -> 0 | J36: =IF(ISERROR(I36),"Предупреждение", IF(I36<0,"Ниже минимума", IF(I36=0,"Минимум", IF(I36<1,"В диапазоне", IF(I36=1,"Максимум", "Выше максимума"))))) -> Минимум
A37: 35 | B37: 46037 | C37: ООО "Тринити Шиппинг" | D37: Юридическое лицо | E37: ст.15.30 КоАП РФ | F37: 700000 | G37: 700000 | H37: в размере суммы излишнего дохода… но не менее 700 000 рублей | I37: {=_xlfn.IFS(F37=H37,1,F37=G37,0,F37<>G37,(F37-G37)/(G37))} -> 0 | J37: =IF(ISERROR(I37),"Предупреждение", IF(I37<0,"Ниже минимума", IF(I37=0,"Минимум", IF(I37<1,"В диапазоне", IF(I37=1,"Максимум", "Выше максимума"))))) -> Минимум
A38: 36 | B38: 46037 | C38: Бурыкин Иван Терентьевич | D38: Гражданин | E38: ст.15.30 КоАП РФ | F38: 3000 | G38: 3000 | H38: 5000 | I38: {=_xlfn.IFS(F38=H38,1,F38=G38,0,F38<>G38,(F38-G38)/(G38))} -> 0 | J38: =IF(ISERROR(I38),"Предупреждение", IF(I38<0,"Ниже минимума", IF(I38=0,"Минимум", IF(I38<1,"В диапазоне", IF(I38=1,"Максимум", "Выше максимума"))))) -> Минимум
A39: 37 | B39: 46035 | C39: Колесникова Надежда Вячеславовна | D39: Гражданин | E39: ст.15.30 КоАП РФ | F39: 3000 | G39: 3000 | H39: 5000 | I39: {=_xlfn.IFS(F39=H39,1,F39=G39,0,F39<>G39,(F39-G39)/(G39))} -> 0 | J39: =IF(ISERROR(I39),"Предупреждение", IF(I39<0,"Ниже минимума", IF(I39=0,"Минимум", IF(I39<1,"В диапазоне", IF(I39=1,"Максимум", "Выше максимума"))))) -> Минимум
A40: 38 | B40: 46035 | C40: Мазнев Андрей Вячеславович | D40: Гражданин | E40: ст.15.30 КоАП РФ | F40: 3000 | G40: 3000 | H40: 5000 | I40: {=_xlfn.IFS(F40=H40,1,F40=G40,0,F40<>G40,(F40-G40)/(G40))} -> 0 | J40: =IF(ISERROR(I40),"Предупреждение", IF(I40<0,"Ниже минимума", IF(I40=0,"Минимум", IF(I40<1,"В диапазоне", IF(I40=1,"Максимум", "Выше максимума"))))) -> Минимум
A41: 39 | B41: 46035 | C41: Мазнев Сергей Вячеславович | D41: Гражданин | E41: ст.15.30 КоАП РФ | F41: 3000 | G41: 3000 | H41: 5000 | I41: {=_xlfn.IFS(F41=H41,1,F41=G41,0,F41<>G41,(F41-G41)/(G41))} -> 0 | J41: =IF(ISERROR(I41),"Предупреждение", IF(I41<0,"Ниже минимума", IF(I41=0,"Минимум", IF(I41<1,"В диапазоне", IF(I41=1,"Максимум", "Выше максимума"))))) -> Минимум
A42: 40 | B42: 46035 | C42: Дмитриев Андрей Николаевич | D42: Гражданин | E42: ст.15.30 КоАП РФ | F42: 3000 | G42: 3000 | H42: 5000 | I42: {=_xlfn.IFS(F42=H42,1,F42=G42,0,F42<>G42,(F42-G42)/(G42))} -> 0 | J42: =IF(ISERROR(I42),"Предупреждение", IF(I42<0,"Ниже минимума", IF(I42=0,"Минимум", IF(I42<1,"В диапазоне", IF(I42=1,"Максимум", "Выше максимума"))))) -> Минимум
A43: 41 | B43: 46035 | C43: Малык Герман Андреевич | D43: Гражданин | E43: ст.15.30 КоАП РФ | F43: 3000 | G43: 3000 | H43: 5000 | I43: {=_xlfn.IFS(F43=H43,1,F43=G43,0,F43<>G43,(F43-G43)/(G43))} -> 0 | J43: =IF(ISERROR(I43),"Предупреждение", IF(I43<0,"Ниже минимума", IF(I43=0,"Минимум", IF(I43<1,"В диапазоне", IF(I43=1,"Максимум", "Выше максимума"))))) -> Минимум
A44: 42 | B44: 46035 | C44: Усачев Андрей Николаевич | D44: Гражданин | E44: ст.15.30 КоАП РФ | F44: 3000 | G44: 3000 | H44: 5000 | I44: {=_xlfn.IFS(F44=H44,1,F44=G44,0,F44<>G44,(F44-G44)/(G44))} -> 0 | J44: =IF(ISERROR(I44),"Предупреждение", IF(I44<0,"Ниже минимума", IF(I44=0,"Минимум", IF(I44<1,"В диапазоне", IF(I44=1,"Максимум", "Выше максимума"))))) -> Минимум
A45: 43 | B45: 46035 | C45: Шушин Игорь Борисович | D45: Гражданин | E45: ст.15.30 КоАП РФ | F45: 3000 | G45: 3000 | H45: 5000 | I45: {=_xlfn.IFS(F45=H45,1,F45=G45,0,F45<>G45,(F45-G45)/(G45))} -> 0 | J45: =IF(ISERROR(I45),"Предупреждение", IF(I45<0,"Ниже минимума", IF(I45=0,"Минимум", IF(I45<1,"В диапазоне", IF(I45=1,"Максимум", "Выше максимума"))))) -> Минимум
A46: 44 | B46: 46035 | C46: Шушина Татьяна Геннадьевна | D46: Гражданин | E46: ст.15.30 КоАП РФ | F46: 3000 | G46: 3000 | H46: 5000 | I46: {=_xlfn.IFS(F46=H46,1,F46=G46,0,F46<>G46,(F46-G46)/(G46))} -> 0 | J46: =IF(ISERROR(I46),"Предупреждение", IF(I46<0,"Ниже минимума", IF(I46=0,"Минимум", IF(I46<1,"В диапазоне", IF(I46=1,"Максимум", "Выше максимума"))))) -> Минимум
A47: 45 | B47: 46035 | C47: Богачев Вячеслав Анатольевич | D47: Гражданин | E47: ст.15.30 КоАП РФ | F47: 3000 | G47: 3000 | H47: 5000 | I47: {=_xlfn.IFS(F47=H47,1,F47=G47,0,F47<>G47,(F47-G47)/(G47))} -> 0 | J47: =IF(ISERROR(I47),"Предупреждение", IF(I47<0,"Ниже минимума", IF(I47=0,"Минимум", IF(I47<1,"В диапазоне", IF(I47=1,"Максимум", "Выше максимума"))))) -> Минимум
A48: 46 | B48: 46035 | C48: Султанаева Эльвира Дамировна | D48: Гражданин | E48: ст.15.30 КоАП РФ | F48: 3000 | G48: 3000 | H48: 5000 | I48: {=_xlfn.IFS(F48=H48,1,F48=G48,0,F48<>G48,(F48-G48)/(G48))} -> 0 | J48: =IF(ISERROR(I48),"Предупреждение", IF(I48<0,"Ниже минимума", IF(I48=0,"Минимум", IF(I48<1,"В диапазоне", IF(I48=1,"Максимум", "Выше максимума"))))) -> Минимум
A49: 47 | B49: 46035 | C49: Бурыкин Иван Иванович | D49: Гражданин | E49: ст.15.30 КоАП РФ | F49: 3000 | G49: 3000 | H49: 5000 | I49: {=_xlfn.IFS(F49=H49,1,F49=G49,0,F49<>G49,(F49-G49)/(G49))} -> 0 | J49: =IF(ISERROR(I49),"Предупреждение", IF(I49<0,"Ниже минимума", IF(I49=0,"Минимум", IF(I49<1,"В диапазоне", IF(I49=1,"Максимум", "Выше максимума"))))) -> Минимум
... A53: 51 | B53: 46035 | C53: ООО «ПФЛ НОВЫЕ ИНВЕСТИЦИИ» | D53: Юридическое лицо | E53: ч.1 ст.19.7.3 КоАП РФ | F53: 350000 | G53: 500000 | H53: 700000 | I53: {=_xlfn.IFS(F53=H53,1,F53=G53,0,F53<>G53,(F53-G53)/(G53))} -> -0.3 | J53: =IF(ISERROR(I53),"Предупреждение", IF(I53<0,"Ниже минимума", IF(I53=0,"Минимум", IF(I53<1,"В диапазоне", IF(I53=1,"Максимум", "Выше максимума"))))) -> Ниже минимума
A54: 52 | B54: 46035 | C54: ООО «ТОЧКА ИНВЕСТИЦИИ» | D54: Юридическое лицо | E54: ч.1 ст.19.7.3 КоАП РФ | F54: предупреждение | G54: 500000 | H54: 700000 | I54: {=_xlfn.IFS(F54=H54,1,F54=G54,0,F54<>G54,(F54-G54)/(G54))} -> #VALUE! | J54: =IF(ISERROR(I54),"Предупреждение", IF(I54<0,"Ниже минимума", IF(I54=0,"Минимум", IF(I54<1,"В диапазоне", IF(I54=1,"Максимум", "Выше максимума"))))) -> Предупреждение
A55: 53 | B55: 46035 | C55: Акционерное общество "Частные Активы" | D55: Юридическое лицо | E55: ч.12 ст.15.29 КоАП РФ | F55: предупреждение | G55: 300000 | H55: 500000 | I55: {=_xlfn.IFS(F55=H55,1,F55=G55,0,F55<>G55,(F55-G55)/(G55))} -> #VALUE! | J55: =IF(ISERROR(I55),"Предупреждение", IF(I55<0,"Ниже минимума", IF(I55=0,"Минимум", IF(I55<1,"В диапазоне", IF(I55=1,"Максимум", "Выше максимума"))))) -> Предупреждение
A56: 54 | B56: 46035 | C56: Общество с ограниченной ответственностью Управляющая Компания "Юнион Инвест Групп" | D56: Юридическое лицо | E56: ч.9 ст.15.29 КоАП РФ | F56: 350000 | G56: 700000 | H56: 1000000 | I56: {=_xlfn.IFS(F56=H56,1,F56=G56,0,F56<>G56,(F56-G56)/(G56))} -> -0.5 | J56: =IF(ISERROR(I56),"Предупреждение", IF(I56<0,"Ниже минимума", IF(I56=0,"Минимум", IF(I56<1,"В диапазоне", IF(I56=1,"Максимум", "Выше максимума"))))) -> Ниже минимума
A57: 54 | B57: 46035 | C57: Общество с ограниченной ответственностью Управляющая Компания "Юнион Инвест Групп" | D57: Юридическое лицо | E57: ч.12 ст.15.29 КоАП РФ | F57: 150000 | G57: 300000 | H57: 500000 | I57: {=_xlfn.IFS(F57=H57,1,F57=G57,0,F57<>G57,(F57-G57)/(G57))} -> -0.5 | J57: =IF(ISERROR(I57),"Предупреждение", IF(I57<0,"Ниже минимума", IF(I57=0,"Минимум", IF(I57<1,"В диапазоне", IF(I57=1,"Максимум", "Выше максимума"))))) -> Ниже минимума
A58: 55 | B58: 46035 | C58: Акционерное общество Негосударственный пенсионный фонд ВТБ Пенсионный фонд | D58: Юридическое лицо | E58: ч.9 ст.15.29 КоАП РФ | F58: 700000 | G58: 700000 | H58: 1000000 | I58: {=_xlfn.IFS(F58=H58,1,F58=G58,0,F58<>G58,(F58-G58)/(G58))} -> 0 | J58: =IF(ISERROR(I58),"Предупреждение", IF(I58<0,"Ниже минимума", IF(I58=0,"Минимум", IF(I58<1,"В диапазоне", IF(I58=1,"Максимум", "Выше максимума"))))) -> Минимум
A59: 56 | B59: 46035 | C59: Акционерное общество «Управляющая Компания ТРИНФИКО» | D59: Юридическое лицо | E59: ч.2 ст.15.19 КоАП РФ | F59: предупреждение | G59: 700000 | H59: 1000000 | I59: {=_xlfn.IFS(F59=H59,1,F59=G59,0,F59<>G59,(F59-G59)/(G59))} -> #VALUE! | J59: =IF(ISERROR(I59),"Предупреждение", IF(I59<0,"Ниже минимума", IF(I59=0,"Минимум", IF(I59<1,"В диапазоне", IF(I59=1,"Максимум", "Выше максимума"))))) -> Предупреждение
A60: 57 | B60: 46035 | C60: Акционерное общество «АБ Капитал» | D60: Юридическое лицо | E60: ч.2 ст.15.19 КоАП РФ | F60: предупреждение | G60: 700000 | H60: 1000000 | I60: {=_xlfn.IFS(F60=H60,1,F60=G60,0,F60<>G60,(F60-G60)/(G60))} -> #VALUE! | J60: =IF(ISERROR(I60),"Предупреждение", IF(I60<0,"Ниже минимума", IF(I60=0,"Минимум", IF(I60<1,"В диапазоне", IF(I60=1,"Максимум", "Выше максимума"))))) -> Предупреждение
A61: 58 | B61: 46035 | C61: Акционерное общество «Инвестиционная компания «РИКОМ-ТРАСТ» | D61: Юридическое лицо | E61: ч.2 ст.15.29 КоАП РФ | F61: 500000 | G61: 500000 | H61: 700000 | I61: {=_xlfn.IFS(F61=H61,1,F61=G61,0,F61<>G61,(F61-G61)/(G61))} -> 0 | J61: =IF(ISERROR(I61),"Предупреждение", IF(I61<0,"Ниже минимума", IF(I61=0,"Минимум", IF(I61<1,"В диапазоне", IF(I61=1,"Максимум", "Выше максимума"))))) -> Минимум
A62: 59 | B62: 46035 | C62: Общество с ограниченной ответственностью «Т-Капитал» | D62: Юридическое лицо | E62: ч.2 ст.15.19 КоАП РФ | F62: 700000 | G62: 700000 | H62: 1000000 | I62: {=_xlfn.IFS(F62=H62,1,F62=G62,0,F62<>G62,(F62-G62)/(G62))} -> 0 | J62: =IF(ISERROR(I62),"Предупреждение", IF(I62<0,"Ниже минимума", IF(I62=0,"Минимум", IF(I62<1,"В диапазоне", IF(I62=1,"Максимум", "Выше максимума"))))) -> Минимум
A63: 60 | B63: 46035 | C63: Общество с ограниченной ответственностью «РСХБ Управление Активами» | D63: Юридическое лицо | E63: ч.12 ст.15.29 КоАП РФ | F63: 400000 | G63: 300000 | H63: 500000 | I63: {=_xlfn.IFS(F63=H63,1,F63=G63,0,F63<>G63,(F63-G63)/(G63))} -> 0.33333333 | J63: =IF(ISERROR(I63),"Предупреждение", IF(I63<0,"Ниже минимума", IF(I63=0,"Минимум", IF(I63<1,"В диапазоне", IF(I63=1,"Максимум", "Выше максимума"))))) -> В диапазоне
A64: 61 | B64: 46021 | C64: Акционерное общество «Объединенное кредитное бюро» | D64: Юридическое лицо | E64: ч.1 ст.19.7.3 КоАП РФ | F64: 700000 | G64: 500000 | H64: 700000 | I64: {=_xlfn.IFS(F64=H64,1,F64=G64,0,F64<>G64,(F64-G64)/(G64))} -> 1 | J64: =IF(ISERROR(I64),"Предупреждение", IF(I64<0,"Ниже минимума", IF(I64=0,"Минимум", IF(I64<1,"В диапазоне", IF(I64=1,"Максимум", "Выше максимума"))))) -> Максимум
A65: 62 | B65: 46021 | C65: Пивень Наталья Анатольевна | D65: Гражданин | E65: ст.15.30 КоАП РФ | F65: 3000 | G65: 3000 | H65: 5000 | I65: {=_xlfn.IFS(F65=H65,1,F65=G65,0,F65<>G65,(F65-G65)/(G65))} -> 0 | J65: =IF(ISERROR(I65),"Предупреждение", IF(I65<0,"Ниже минимума", IF(I65=0,"Минимум", IF(I65<1,"В диапазоне", IF(I65=1,"Максимум", "Выше максимума"))))) -> Минимум
A66: 63 | B66: 46021 | C66: Акционерное общество «Объединенное кредитное бюро» | D66: Юридическое лицо | E66: ч.1 ст.19.7.3 КоАП РФ | F66: 700000 | G66: 500000 | H66: 700000 | I66: {=_xlfn.IFS(F66=H66,1,F66=G66,0,F66<>G66,(F66-G66)/(G66))} -> 1 | J66: =IF(ISERROR(I66),"Предупреждение", IF(I66<0,"Ниже минимума", IF(I66=0,"Минимум", IF(I66<1,"В диапазоне", IF(I66=1,"Максимум", "Выше максимума"))))) -> Максимум
A67: 64 | B67: 46021 | C67: Пивень Демид Романович | D67: Гражданин | E67: ст.15.30 КоАП РФ | F67: 3000 | G67: 3000 | H67: 5000 | I67: {=_xlfn.IFS(F67=H67,1,F67=G67,0,F67<>G67,(F67-G67)/(G67))} -> 0 | J67: =IF(ISERROR(I67),"Предупреждение", IF(I67<0,"Ниже минимума", IF(I67=0,"Минимум", IF(I67<1,"В диапазоне", IF(I67=1,"Максимум", "Выше максимума"))))) -> Минимум
A68: 65 | B68: 46020 | C68: Акционерное общество "Инвестиционная компания "Лидер" | D68: Юридическое лицо | E68: ч.2 ст.15.29 КоАП РФ | F68: предупреждение | G68: 500000 | H68: 700000 | I68: {=_xlfn.IFS(F68=H68,1,F68=G68,0,F68<>G68,(F68-G68)/(G68))} -> #VALUE! | J68: =IF(ISERROR(I68),"Предупреждение", IF(I68<0,"Ниже минимума", IF(I68=0,"Минимум", IF(I68<1,"В диапазоне", IF(I68=1,"Максимум", "Выше максимума"))))) -> Предупреждение
A69: 66 | B69: 46014 | C69: Кувшинова Анна Викторовна | D69: Гражданин | E69: ст.15.30 КоАП РФ | F69: 3000 | G69: 3000 | H69: 5000 | I69: {=_xlfn.IFS(F69=H69,1,F69=G69,0,F69<>G69,(F69-G69)/(G69))} -> 0 | J69: =IF(ISERROR(I69),"Предупреждение", IF(I69<0,"Ниже минимума", IF(I69=0,"Минимум", IF(I69<1,"В диапазоне", IF(I69=1,"Максимум", "Выше максимума"))))) -> Минимум
A70: 67 | B70: 46014 | C70: Кувшинов Роман Сергеевич | D70: Гражданин | E70: ст.15.30 КоАП РФ | F70: 3000 | G70: 3000 | H70: 5000 | I70: {=_xlfn.IFS(F70=H70,1,F70=G70,0,F70<>G70,(F70-G70)/(G70))} -> 0 | J70: =IF(ISERROR(I70),"Предупреждение", IF(I70<0,"Ниже минимума", IF(I70=0,"Минимум", IF(I70<1,"В диапазоне", IF(I70=1,"Максимум", "Выше максимума"))))) -> Минимум
A71: 68 | B71: 46014 | C71: Чамкин Михаил Александрович | D71: Гражданин | E71: ст.15.30 КоАП РФ | F71: 30000 | G71: 3000 | H71: 5000 | I71: {=_xlfn.IFS(F71=H71,1,F71=G71,0,F71<>G71,(F71-G71)/(G71))} -> 9 | J71: =IF(ISERROR(I71),"Предупреждение", IF(I71<0,"Ниже минимума", IF(I71=0,"Минимум", IF(I71<1,"В диапазоне", IF(I71=1,"Максимум", "Выше максимума"))))) -> Выше максимума
A72: 69 | B72: 46014 | C72: ОБЩЕСТВО С ОГРАНИЧЕННОЙ ОТВЕТСТВЕННОСТЬЮ "НАРОДНАЯ ИНВЕСТИЦИОННАЯ ПЛАТФОРМА" | D72: Юридическое лицо | E72: ч.9 ст.19.5 КоАП РФ | F72: 250000 | G72: 500000 | H72: 700000 | I72: {=_xlfn.IFS(F72=H72,1,F72=G72,0,F72<>G72,(F72-G72)/(G72))} -> -0.5 | J72: =IF(ISERROR(I72),"Предупреждение", IF(I72<0,"Ниже минимума", IF(I72=0,"Минимум", IF(I72<1,"В диапазоне", IF(I72=1,"Максимум", "Выше максимума"))))) -> Ниже минимума
A73: 70 | B73: 46014 | C73: Акционерное общество «Управляющая компания «Первая» | D73: Юридическое лицо | E73: ч.6 ст.15.29 КоАП РФ | F73: 700000 | G73: 700000 | H73: 1000000 | I73: {=_xlfn.IFS(F73=H73,1,F73=G73,0,F73<>G73,(F73-G73)/(G73))} -> 0 | J73: =IF(ISERROR(I73),"Предупреждение", IF(I73<0,"Ниже минимума", IF(I73=0,"Минимум", IF(I73<1,"В диапазоне", IF(I73=1,"Максимум", "Выше максимума"))))) -> Минимум
A74: 71 | B74: 46014 | C74: Акционерное общество_x000D_ «Контрада Капитал» | D74: Юридическое лицо | E74: ч.12 ст.15.29 КоАП РФ | F74: 150000 | G74: 300000 | H74: 500000 | I74: {=_xlfn.IFS(F74=H74,1,F74=G74,0,F74<>G74,(F74-G74)/(G74))} -> -0.5 | J74: =IF(ISERROR(I74),"Предупреждение", IF(I74<0,"Ниже минимума", IF(I74=0,"Минимум", IF(I74<1,"В диапазоне", IF(I74=1,"Максимум", "Выше максимума"))))) -> Ниже минимума
A75: 71 | B75: 46014 | C75: Акционерное общество_x000D_ «Контрада Капитал» | D75: Юридическое лицо | E75: ч.6 ст.15.29 КоАП РФ | F75: 350000 | G75: 700000 | H75: 1000000 | I75: {=_xlfn.IFS(F75=H75,1,F75=G75,0,F75<>G75,(F75-G75)/(G75))} -> -0.5 | J75: =IF(ISERROR(I75),"Предупреждение", IF(I75<0,"Ниже минимума", IF(I75=0,"Минимум", IF(I75<1,"В диапазоне", IF(I75=1,"Максимум", "Выше максимума"))))) -> Ниже минимума
A76: 72 | B76: 46010 | C76: Общество с ограниченной ответственностью "ТОРГОВАЯ СИСТЕМА" | D76: Юридическое лицо | E76: ст.15.30 КоАП РФ | F76: 350000 | G76: 700000 | H76: в размере суммы излишнего дохода… но не менее 700 000 рублей | I76: {=_xlfn.IFS(F76=H76,1,F76=G76,0,F76<>G76,(F76-G76)/(G76))} -> -0.5 | J76: =IF(ISERROR(I76),"Предупреждение", IF(I76<0,"Ниже минимума", IF(I76=0,"Минимум", IF(I76<1,"В диапазоне", IF(I76=1,"Максимум", "Выше максимума"))))) -> Ниже минимума
A77: 73 | B77: 46010 | C77: Кривова Надежда Юнусовна | D77: Гражданин | E77: ст.15.30 КоАП РФ | F77: 3000 | G77: 3000 | H77: 5000 | I77: {=_xlfn.IFS(F77=H77,1,F77=G77,0,F77<>G77,(F77-G77)/(G77))} -> 0 | J77: =IF(ISERROR(I77),"Предупреждение", IF(I77<0,"Ниже минимума", IF(I77=0,"Минимум", IF(I77<1,"В диапазоне", IF(I77=1,"Максимум", "Выше максимума"))))) -> Минимум
A78: 74 | B78: 46010 | C78: Кривов Вадим Иванович | D78: Гражданин | E78: ст.15.30 КоАП РФ | F78: 3000 | G78: 3000 | H78: 5000 | I78: {=_xlfn.IFS(F78=H78,1,F78=G78,0,F78<>G78,(F78-G78)/(G78))} -> 0 | J78: =IF(ISERROR(I78),"Предупреждение", IF(I78<0,"Ниже минимума", IF(I78=0,"Минимум", IF(I78<1,"В диапазоне", IF(I78=1,"Максимум", "Выше максимума"))))) -> Минимум
A79: 75 | B79: 46010 | C79: Общество с ограниченной_x000D_ ответственностью_x000D_ «Совкомбанк Управление_x000D_ Активами» | D79: Юридическое лицо | E79: ч.12 ст.15.29 КоАП РФ | F79: предупреждение | G79: 300000 | H79: 500000 | I79: {=_xlfn.IFS(F79=H79,1,F79=G79,0,F79<>G79,(F79-G79)/(G79))} -> #VALUE! | J79: =IF(ISERROR(I79),"Предупреждение", IF(I79<0,"Ниже минимума", IF(I79=0,"Минимум", IF(I79<1,"В диапазоне", IF(I79=1,"Максимум", "Выше максимума"))))) -> Предупреждение
A80: 76 | B80: 46007 | C80: Общество с ограниченной ответственностью "Зитрон" | D80: Юридическое лицо | E80: ст.15.30 КоАП РФ | F80: 350000 | G80: 700000 | H80: в размере суммы излишнего дохода… но не менее 700 000 рублей | I80: {=_xlfn.IFS(F80=H80,1,F80=G80,0,F80<>G80,(F80-G80)/(G80))} -> -0.5 | J80: =IF(ISERROR(I80),"Предупреждение", IF(I80<0,"Ниже минимума", IF(I80=0,"Минимум", IF(I80<1,"В диапазоне", IF(I80=1,"Максимум", "Выше максимума"))))) -> Ниже минимума
A81: 77 | B81: 46007 | C81: Акционерное общество «НРК-Р.О.С.Т.» | D81: Юридическое лицо | E81: ч.7 ст.15.29 КоАП РФ | F81: 500000 | G81: 500000 | H81: 700000 | I81: {=_xlfn.IFS(F81=H81,1,F81=G81,0,F81<>G81,(F81-G81)/(G81))} -> 0 | J81: =IF(ISERROR(I81),"Предупреждение", IF(I81<0,"Ниже минимума", IF(I81=0,"Минимум", IF(I81<1,"В диапазоне", IF(I81=1,"Максимум", "Выше максимума"))))) -> Минимум
A82: 78 | B82: 46007 | C82: Общество с ограниченной ответственностью «Бюро кредитных историй КредитИнфо» | D82: Юридическое лицо | E82: ч.1 ст.19.7.3 КоАП РФ | F82: 500000 | G82: 500000 | H82: 700000 | I82: {=_xlfn.IFS(F82=H82,1,F82=G82,0,F82<>G82,(F82-G82)/(G82))} -> 0 | J82: =IF(ISERROR(I82),"Предупреждение", IF(I82<0,"Ниже минимума", IF(I82=0,"Минимум", IF(I82<1,"В диапазоне", IF(I82=1,"Максимум", "Выше максимума"))))) -> Минимум
A83: 79 | B83: 46007 | C83: Общество с ограниченной ответственностью «Апрель Капитал Брокер» | D83: Юридическое лицо | E83: ч.2 ст.15.29 КоАП РФ | F83: предупреждение | G83: 500000 | H83: 700000 | I83: {=_xlfn.IFS(F83=H83,1,F83=G83,0,F83<>G83,(F83-G83)/(G83))} -> #VALUE! | J83: =IF(ISERROR(I83),"Предупреждение", IF(I83<0,"Ниже минимума", IF(I83=0,"Минимум", IF(I83<1,"В диапазоне", IF(I83=1,"Максимум", "Выше максимума"))))) -> Предупреждение
A84: 80 | B84: 46006 | C84: Акционерное общество_x000D_ «Всероссийский банк_x000D_ развития регионов» | D84: Юридическое лицо | E84: ч.12 ст.15.29 КоАП РФ | F84: предупреждение | G84: 300000 | H84: 500000 | I84: {=_xlfn.IFS(F84=H84,1,F84=G84,0,F84<>G84,(F84-G84)/(G84))} -> #VALUE! | J84: =IF(ISERROR(I84),"Предупреждение", IF(I84<0,"Ниже минимума", IF(I84=0,"Минимум", IF(I84<1,"В диапазоне", IF(I84=1,"Максимум", "Выше максимума"))))) -> Предупреждение
A85: 81 | B85: 46003 | C85: Денисова Екатерина Алексеевна | D85: Гражданин | E85: ст.15.30 КоАП РФ | F85: 3000 | G85: 3000 | H85: 5000 | I85: {=_xlfn.IFS(F85=H85,1,F85=G85,0,F85<>G85,(F85-G85)/(G85))} -> 0 | J85: =IF(ISERROR(I85),"Предупреждение", IF(I85<0,"Ниже минимума", IF(I85=0,"Минимум", IF(I85<1,"В диапазоне", IF(I85=1,"Максимум", "Выше максимума"))))) -> Минимум
A86: 82 | B86: 46002 | C86: Абхаликов Марсель Абдулвалеевич | D86: Гражданин | E86: ст.15.30 КоАП РФ | F86: 3000 | G86: 3000 | H86: 5000 | I86: {=_xlfn.IFS(F86=H86,1,F86=G86,0,F86<>G86,(F86-G86)/(G86))} -> 0 | J86: =IF(ISERROR(I86),"Предупреждение", IF(I86<0,"Ниже минимума", IF(I86=0,"Минимум", IF(I86<1,"В диапазоне", IF(I86=1,"Максимум", "Выше максимума"))))) -> Минимум
A87: 83 | B87: 46001 | C87: Богачев Алексей Анатольевич | D87: Гражданин | E87: ст.15.30 КоАП РФ | F87: 3000 | G87: 3000 | H87: 5000 | I87: {=_xlfn.IFS(F87=H87,1,F87=G87,0,F87<>G87,(F87-G87)/(G87))} -> 0 | J87: =IF(ISERROR(I87),"Предупреждение", IF(I87<0,"Ниже минимума", IF(I87=0,"Минимум", IF(I87<1,"В диапазоне", IF(I87=1,"Максимум", "Выше максимума"))))) -> Минимум
A88: 84 | B88: 46000 | C88: Акционерное общество «Управляющая компания «Парадигма» | D88: Юридическое лицо | E88: ч.12 ст.15.29 КоАП РФ | F88: предупреждение | G88: 300000 | H88: 500000 | I88: {=_xlfn.IFS(F88=H88,1,F88=G88,0,F88<>G88,(F88-G88)/(G88))} -> #VALUE! | J88: =IF(ISERROR(I88),"Предупреждение", IF(I88<0,"Ниже минимума", IF(I88=0,"Минимум", IF(I88<1,"В диапазоне", IF(I88=1,"Максимум", "Выше максимума"))))) -> Предупреждение
A89: 85 | B89: 45999 | C89: Сысун Константин Валерьевич | D89: Гражданин | E89: ст.15.30 КоАП РФ | F89: 3000 | G89: 3000 | H89: 5000 | I89: {=_xlfn.IFS(F89=H89,1,F89=G89,0,F89<>G89,(F89-G89)/(G89))} -> 0 | J89: =IF(ISERROR(I89),"Предупреждение", IF(I89<0,"Ниже минимума", IF(I89=0,"Минимум", IF(I89<1,"В диапазоне", IF(I89=1,"Максимум", "Выше максимума"))))) -> Минимум
A90: 86 | B90: 45999 | C90: Краснов Борис Владимирович | D90: Гражданин | E90: ст.15.30 КоАП РФ | F90: 3000 | G90: 3000 | H90: 5000 | I90: {=_xlfn.IFS(F90=H90,1,F90=G90,0,F90<>G90,(F90-G90)/(G90))} -> 0 | J90: =IF(ISERROR(I90),"Предупреждение", IF(I90<0,"Ниже минимума", IF(I90=0,"Минимум", IF(I90<1,"В диапазоне", IF(I90=1,"Максимум", "Выше максимума"))))) -> Минимум
A91: 87 | B91: 45996 | C91: Общество с ограниченной ответственностью «МКБ Инвестиции» | D91: Юридическое лицо | E91: ч.9 ст.15.29 КоАП РФ | F91: 700000 | G91: 700000 | H91: 1000000 | I91: {=_xlfn.IFS(F91=H91,1,F91=G91,0,F91<>G91,(F91-G91)/(G91))} -> 0 | J91: =IF(ISERROR(I91),"Предупреждение", IF(I91<0,"Ниже минимума", IF(I91=0,"Минимум", IF(I91<1,"В диапазоне", IF(I91=1,"Максимум", "Выше максимума"))))) -> Минимум
A92: 88 | B92: 45996 | C92: Акционерное общество «Негосударственный пенсионный фонд «БЛАГОСОСТОЯНИЕ» | D92: Юридическое лицо | E92: ч.9 ст.15.29 КоАП РФ | F92: 700000 | G92: 700000 | H92: 1000000 | I92: {=_xlfn.IFS(F92=H92,1,F92=G92,0,F92<>G92,(F92-G92)/(G92))} -> 0 | J92: =IF(ISERROR(I92),"Предупреждение", IF(I92<0,"Ниже минимума", IF(I92=0,"Минимум", IF(I92<1,"В диапазоне", IF(I92=1,"Максимум", "Выше максимума"))))) -> Минимум
A93: 89 | B93: 45993 | C93: Акционерное общество «Инвестиционная компания «РИКОМ-ТРАСТ» | D93: Юридическое лицо | E93: ч.2 ст.15.19 КоАП РФ | F93: 700000 | G93: 700000 | H93: 1000000 | I93: {=_xlfn.IFS(F93=H93,1,F93=G93,0,F93<>G93,(F93-G93)/(G93))} -> 0 | J93: =IF(ISERROR(I93),"Предупреждение", IF(I93<0,"Ниже минимума", IF(I93=0,"Минимум", IF(I93<1,"В диапазоне", IF(I93=1,"Максимум", "Выше максимума"))))) -> Минимум
A94: 90 | B94: 45989 | C94: Акционерное общество "Национальное бюро кредитных историй! | D94: Юридическое лицо | E94: ст.14.30 КоАП РФ | F94: 10000 | G94: 10000 | H94: 20000 | I94: {=_xlfn.IFS(F94=H94,1,F94=G94,0,F94<>G94,(F94-G94)/(G94))} -> 0 | J94: =IF(ISERROR(I94),"Предупреждение", IF(I94<0,"Ниже минимума", IF(I94=0,"Минимум", IF(I94<1,"В диапазоне", IF(I94=1,"Максимум", "Выше максимума"))))) -> Минимум
A95: 91 | B95: 45986 | C95: Акционерное общество «Инвестиционная компания «РИКОМ-ТРАСТ» | D95: Юридическое лицо | E95: ч.1 ст.19.7.3 КоАП РФ | F95: 700000 | G95: 500000 | H95: 700000 | I95: {=_xlfn.IFS(F95=H95,1,F95=G95,0,F95<>G95,(F95-G95)/(G95))} -> 1 | J95: =IF(ISERROR(I95),"Предупреждение", IF(I95<0,"Ниже минимума", IF(I95=0,"Минимум", IF(I95<1,"В диапазоне", IF(I95=1,"Максимум", "Выше максимума"))))) -> Максимум
A96: 92 | B96: 45986 | C96: Акционерное общество «ТБанк» | D96: Юридическое лицо | E96: ч.2 ст.15.19 КоАП РФ | F96: 700000 | G96: 700000 | H96: 1000000 | I96: {=_xlfn.IFS(F96=H96,1,F96=G96,0,F96<>G96,(F96-G96)/(G96))} -> 0 | J96: =IF(ISERROR(I96),"Предупреждение", IF(I96<0,"Ниже минимума", IF(I96=0,"Минимум", IF(I96<1,"В диапазоне", IF(I96=1,"Максимум", "Выше максимума"))))) -> Минимум
A97: 93 | B97: 45986 | C97: Акционерное общество «Райффайзенбанк» | D97: Юридическое лицо | E97: ч.2 ст.15.19 КоАП РФ | F97: 700000 | G97: 700000 | H97: 1000000 | I97: {=_xlfn.IFS(F97=H97,1,F97=G97,0,F97<>G97,(F97-G97)/(G97))} -> 0 | J97: =IF(ISERROR(I97),"Предупреждение", IF(I97<0,"Ниже минимума", IF(I97=0,"Минимум", IF(I97<1,"В диапазоне", IF(I97=1,"Максимум", "Выше максимума"))))) -> Минимум
A98: 94 | B98: 45986 | C98: Общество с ограниченной ответственностью Управляющая компания «Надежное управление» | D98: Юридическое лицо | E98: ч.12 ст.15.29 КоАП РФ | F98: 160000 | G98: 300000 | H98: 500000 | I98: {=_xlfn.IFS(F98=H98,1,F98=G98,0,F98<>G98,(F98-G98)/(G98))} -> -0.46666667 | J98: =IF(ISERROR(I98),"Предупреждение", IF(I98<0,"Ниже минимума", IF(I98=0,"Минимум", IF(I98<1,"В диапазоне", IF(I98=1,"Максимум", "Выше максимума"))))) -> Ниже минимума
A99: 95 | B99: 45985 | C99: Агамирова Ламара Бегларовна | D99: Гражданин | E99: ст.15.30 КоАП РФ | F99: 3000 | G99: 3000 | H99: 5000 | I99: {=_xlfn.IFS(F99=H99,1,F99=G99,0,F99<>G99,(F99-G99)/(G99))} -> 0 | J99: =IF(ISERROR(I99),"Предупреждение", IF(I99<0,"Ниже минимума", IF(I99=0,"Минимум", IF(I99<1,"В диапазоне", IF(I99=1,"Максимум", "Выше максимума"))))) -> Минимум
A100: 96 | B100: 45985 | C100: Третьякова Надежда Яковлевна | D100: Гражданин | E100: ст.15.30 КоАП РФ | F100: 3000 | G100: 3000 | H100: 5000 | I100: {=_xlfn.IFS(F100=H100,1,F100=G100,0,F100<>G100,(F100-G100)/(G100))} -> 0 | J100: =IF(ISERROR(I100),"Предупреждение", IF(I100<0,"Ниже минимума", IF(I100=0,"Минимум", IF(I100<1,"В диапазоне", IF(I100=1,"Максимум", "Выше максимума"))))) -> Минимум
A101: 97 | B101: 45985 | C101: ООО УК «ФИН-Партнер» | D101: Юридическое лицо | E101: ч.12 ст.15.29 КоАП РФ | F101: предупреждение | G101: 300000 | H101: 500000 | I101: {=_xlfn.IFS(F101=H101,1,F101=G101,0,F101<>G101,(F101-G101)/(G101))} -> #VALUE! | J101: =IF(ISERROR(I101),"Предупреждение", IF(I101<0,"Ниже минимума", IF(I101=0,"Минимум", IF(I101<1,"В диапазоне", IF(I101=1,"Максимум", "Выше максимума"))))) -> Предупреждение
A102: 98 | B102: 45985 | C102: Акционерное общество «СОЛИД Менеджмент» | D102: Юридическое лицо | E102: ч.2 ст.15.19 КоАП РФ | F102: 350000 | G102: 700000 | H102: 1000000 | I102: {=_xlfn.IFS(F102=H102,1,F102=G102,0,F102<>G102,(F102-G102)/(G102))} -> -0.5 | J102: =IF(ISERROR(I102),"Предупреждение", IF(I102<0,"Ниже минимума", IF(I102=0,"Минимум", IF(I102<1,"В диапазоне", IF(I102=1,"Максимум", "Выше максимума"))))) -> Ниже минимума
A103: 98 | B103: 45985 | C103: Акционерное общество «СОЛИД Менеджмент» | D103: Юридическое лицо | E103: ч.2 ст.15.19 КоАП РФ | F103: 350000 | G103: 700000 | H103: 1000000 | I103: {=_xlfn.IFS(F103=H103,1,F103=G103,0,F103<>G103,(F103-G103)/(G103))} -> -0.5 | J103: =IF(ISERROR(I103),"Предупреждение", IF(I103<0,"Ниже минимума", IF(I103=0,"Минимум", IF(I103<1,"В диапазоне", IF(I103=1,"Максимум", "Выше максимума"))))) -> Ниже минимума
A104: 99 | B104: 45983 | C104: АО «НРК-Р.О.С.Т.» | D104: Юридическое лицо | E104: ч.1 ст.19.7.3 КоАП РФ | F104: предупреждение | G104: 500000 | H104: 700000 | I104: {=_xlfn.IFS(F104=H104,1,F104=G104,0,F104<>G104,(F104-G104)/(G104))} -> #VALUE! | J104: =IF(ISERROR(I104),"Предупреждение", IF(I104<0,"Ниже минимума", IF(I104=0,"Минимум", IF(I104<1,"В диапазоне", IF(I104=1,"Максимум", "Выше максимума"))))) -> Предупреждение
A105: 100 | B105: 45982 | C105: ОБЩЕСТВО С ОГРАНИЧЕННОЙ ОТВЕТСТВЕННОСТЬЮ «НАРОДНАЯ ИНВЕСТИЦИОННАЯ ПЛАТФОРМА» | D105: Юридическое лицо | E105: ч.9 ст.19.5 КоАП РФ | F105: 250000 | G105: 500000 | H105: 700000 | I105: {=_xlfn.IFS(F105=H105,1,F105=G105,0,F105<>G105,(F105-G105)/(G105))} -> -0.5 | J105: =IF(ISERROR(I105),"Предупреждение", IF(I105<0,"Ниже минимума", IF(I105=0,"Минимум", IF(I105<1,"В диапазоне", IF(I105=1,"Максимум", "Выше максимума"))))) -> Ниже минимума
A106: 101 | B106: 45982 | C106: Общество с ограниченной ответственностью ВИМ Сбережения | D106: Юридическое лицо | E106: ч.9 ст.15.29 КоАП РФ | F106: 700000 | G106: 700000 | H106: 1000000 | I106: {=_xlfn.IFS(F106=H106,1,F106=G106,0,F106<>G106,(F106-G106)/(G106))} -> 0 | J106: =IF(ISERROR(I106),"Предупреждение", IF(I106<0,"Ниже минимума", IF(I106=0,"Минимум", IF(I106<1,"В диапазоне", IF(I106=1,"Максимум", "Выше максимума"))))) -> Минимум
A107: 102 | B107: 45979 | C107: Кислица Дмитрий Николаевич | D107: Гражданин | E107: ст.15.30 КоАП РФ | F107: 3000 | G107: 3000 | H107: 5000 | I107: {=_xlfn.IFS(F107=H107,1,F107=G107,0,F107<>G107,(F107-G107)/(G107))} -> 0 | J107: =IF(ISERROR(I107),"Предупреждение", IF(I107<0,"Ниже минимума", IF(I107=0,"Минимум", IF(I107<1,"В диапазоне", IF(I107=1,"Максимум", "Выше максимума"))))) -> Минимум
A108: 103 | B108: 45979 | C108: Гаспарян Сергей Эдуардович | D108: Гражданин | E108: ст.15.30 КоАП РФ | F108: 3000 | G108: 3000 | H108: 5000 | I108: {=_xlfn.IFS(F108=H108,1,F108=G108,0,F108<>G108,(F108-G108)/(G108))} -> 0 | J108: =IF(ISERROR(I108),"Предупреждение", IF(I108<0,"Ниже минимума", IF(I108=0,"Минимум", IF(I108<1,"В диапазоне", IF(I108=1,"Максимум", "Выше максимума"))))) -> Минимум
A109: 104 | B109: 45979 | C109: Ледник Мария Ивановна | D109: Гражданин | E109: ст.15.30 КоАП РФ | F109: 3000 | G109: 3000 | H109: 5000 | I109: {=_xlfn.IFS(F109=H109,1,F109=G109,0,F109<>G109,(F109-G109)/(G109))} -> 0 | J109: =IF(ISERROR(I109),"Предупреждение", IF(I109<0,"Ниже минимума", IF(I109=0,"Минимум", IF(I109<1,"В диапазоне", IF(I109=1,"Максимум", "Выше максимума"))))) -> Минимум
A110: 105 | B110: 45979 | C110: Финк Александр Яковлевич | D110: Гражданин | E110: ст.15.30 КоАП РФ | F110: 3000 | G110: 3000 | H110: 5000 | I110: {=_xlfn.IFS(F110=H110,1,F110=G110,0,F110<>G110,(F110-G110)/(G110))} -> 0 | J110: =IF(ISERROR(I110),"Предупреждение", IF(I110<0,"Ниже минимума", IF(I110=0,"Минимум", IF(I110<1,"В диапазоне", IF(I110=1,"Максимум", "Выше максимума"))))) -> Минимум
A111: 106 | B111: 45979 | C111: Когай Геннадий Григорьевич | D111: Гражданин | E111: ст.15.30 КоАП РФ | F111: 3000 | G111: 3000 | H111: 5000 | I111: {=_xlfn.IFS(F111=H111,1,F111=G111,0,F111<>G111,(F111-G111)/(G111))} -> 0 | J111: =IF(ISERROR(I111),"Предупреждение", IF(I111<0,"Ниже минимума", IF(I111=0,"Минимум", IF(I111<1,"В диапазоне", IF(I111=1,"Максимум", "Выше максимума"))))) -> Минимум
A112: 107 | B112: 45979 | C112: Багров Дмитрий Андреевич | D112: Гражданин | E112: ст.15.30 КоАП РФ | F112: 3000 | G112: 3000 | H112: 5000 | I112: {=_xlfn.IFS(F112=H112,1,F112=G112,0,F112<>G112,(F112-G112)/(G112))} -> 0 | J112: =IF(ISERROR(I112),"Предупреждение", IF(I112<0,"Ниже минимума", IF(I112=0,"Минимум", IF(I112<1,"В диапазоне", IF(I112=1,"Максимум", "Выше максимума"))))) -> Минимум
A113: 108 | B113: 45979 | C113: Денисов Павел Геннадьевич | D113: Гражданин | E113: ст.15.30 КоАП РФ | F113: 3000 | G113: 3000 | H113: 5000 | I113: {=_xlfn.IFS(F113=H113,1,F113=G113,0,F113<>G113,(F113-G113)/(G113))} -> 0 | J113: =IF(ISERROR(I113),"Предупреждение", IF(I113<0,"Ниже минимума", IF(I113=0,"Минимум", IF(I113<1,"В диапазоне", IF(I113=1,"Максимум", "Выше максимума"))))) -> Минимум
A114: 109 | B114: 45975 | C114: Бастракова Дарья Дмитриевна | D114: Гражданин | E114: ст.15.30 КоАП РФ | F114: 3000 | G114: 3000 | H114: 5000 | I114: {=_xlfn.IFS(F114=H114,1,F114=G114,0,F114<>G114,(F114-G114)/(G114))} -> 0 | J114: =IF(ISERROR(I114),"Предупреждение", IF(I114<0,"Ниже минимума", IF(I114=0,"Минимум", IF(I114<1,"В диапазоне", IF(I114=1,"Максимум", "Выше максимума"))))) -> Минимум
A115: 110 | B115: 45975 | C115: Трубина Наталья Владимировна | D115: Гражданин | E115: ст.15.30 КоАП РФ | F115: 3000 | G115: 3000 | H115: 5000 | I115: {=_xlfn.IFS(F115=H115,1,F115=G115,0,F115<>G115,(F115-G115)/(G115))} -> 0 | J115: =IF(ISERROR(I115),"Предупреждение", IF(I115<0,"Ниже минимума", IF(I115=0,"Минимум", IF(I115<1,"В диапазоне", IF(I115=1,"Максимум", "Выше максимума"))))) -> Минимум
A116: 111 | B116: 45974 | C116: Горячева Елена Петровна | D116: Гражданин | E116: ст.15.30 КоАП РФ | F116: 3000 | G116: 3000 | H116: 5000 | I116: {=_xlfn.IFS(F116=H116,1,F116=G116,0,F116<>G116,(F116-G116)/(G116))} -> 0 | J116: =IF(ISERROR(I116),"Предупреждение", IF(I116<0,"Ниже минимума", IF(I116=0,"Минимум", IF(I116<1,"В диапазоне", IF(I116=1,"Максимум", "Выше максимума"))))) -> Минимум
... A152: 139 | B152: 45966 | C152: Кемайкина Юлия Александровна | D152: Гражданин | E152: ст.15.30 КоАП РФ | F152: 3000 | G152: 3000 | H152: 5000 | I152: {=_xlfn.IFS(F152=H152,1,F152=G152,0,F152<>G152,(F152-G152)/(G152))} -> 0 | J152: =IF(ISERROR(I152),"Предупреждение", IF(I152<0,"Ниже минимума", IF(I152=0,"Минимум", IF(I152<1,"В диапазоне", IF(I152=1,"Максимум", "Выше максимума"))))) -> Минимум
...

Sheet чистые данные
A1: Номер случая | B1: Дата постановления | C1: Субъект | D1: Тип лица | E1: Статья КоАП | F1: Штраф факт | G1: мин | H1: макс | I1: вид штрафа | J1: Содержание статьи | K1: Описание
A2: 1 | B2: 46070 | C2: Акционерное общество «Негосударственный пенсионный фонд «Ростех» | D2: Юридическое лицо | E2: ч.9 ст.15.29 КоАП РФ | F2: 700000 | G2: 700000 | H2: 1000000 | I2: Минимум | J2: =VLOOKUP(E2,статьи!$G$2:$H$24,2,TRUE) -> 1. Неисполнение акционерным обществом, профессиональным участником рынка ценных бумаг, управляющей компанией акционерного инвестиционного фонда, паевого инвестиционного фонда или негосударственного пенсионного фонда либо специализированным депозитарием акционерного инвестиционного фонда, паевого инвестиционного фонда или негосударственного пенсионного фонда обязанности по хранению документов, которые предусмотрены законодательством об акционерных обществах, о рынке ценных бумаг, об инвестиционных фондах и принятыми в соответствии с ним нормативными правовыми актами и хранение которых является обязательным, а также нарушение установленных порядка и сроков хранения таких документов | K2: =VLOOKUP(A2,'компании+описание'!$A$1:$D$438,4,) -> По результатам рассмотрения материалов дела об административном правонарушении № ЦА-38-ЮЛ-26-258, возбуждённого за совершение административного правонарушения, ответственность за которое предусмотрена частью 9 статьи 15.29 Кодекса Российской Федерации об административных правонарушениях, АО «НПФ «Ростех» назначено административное наказание в виде штрафа в размере 700 000 рублей. Постановление вступило в законную силу 17.02.2026.
A3: 2 | B3: 46070 | C3: Общество с ограниченной ответственностью «Управляющая компания_x000D_ «Атон-менеджмент» | D3: Юридическое лицо | E3: ч.6 ст.15.29 КоАП РФ | F3: 700000 | G3: 700000 | H3: 1000000 | I3: Минимум | J3: =VLOOKUP(E3,статьи!$G$2:$H$24,2,TRUE) -> 1. Неисполнение акционерным обществом, профессиональным участником рынка ценных бумаг, управляющей компанией акционерного инвестиционного фонда, паевого инвестиционного фонда или негосударственного пенсионного фонда либо специализированным депозитарием акционерного инвестиционного фонда, паевого инвестиционного фонда или негосударственного пенсионного фонда обязанности по хранению документов, которые предусмотрены законодательством об акционерных обществах, о рынке ценных бумаг, об инвестиционных фондах и принятыми в соответствии с ним нормативными правовыми актами и хранение которых является обязательным, а также нарушение установленных порядка и сроков хранения таких документов | K3: =VLOOKUP(A3,'компании+описание'!$A$1:$D$438,4,) -> По результатам рассмотрения материалов дела об административном правонарушении № ЦА-38-ЮЛ-26-92, возбужденного за совершение административного правонарушения, ответственность за которое предусмотрена частью 6 статьи 15.29 КоАП РФ, Обществу с ограниченной ответственностью «Управляющая компания «Атон-менеджмент» назначено административное наказание в виде штрафа в размере 700 000 рублей. Постановление вступило в законную силу 17.02.2026.По результатам рассмотрения материалов дела об административном правонарушении № ЦА-38-ЮЛ-26-93, возбужденного за совершение административного правонарушения, ответственность за которое предусмотрена частью 12 статьи 15.29 КоАП РФ, Обществу с ограниченной ответственностью «Управляющая компания «Атон-менеджмент» назначено административное наказание в виде штрафа в размере 320 000 рублей. Постановление вступило в законную силу 17.02.2026.
A4: 2 | B4: 46070 | C4: Общество с ограниченной ответственностью «Управляющая компания_x000D_ «Атон-менеджмент» | D4: Юридическое лицо | E4: ч.12 ст.15.29 КоАП РФ | F4: 320000 | G4: 300000 | H4: 500000 | I4: В диапазоне | J4: =VLOOKUP(E4,статьи!$G$2:$H$24,2,TRUE) -> Незаконные действия по получению или предоставлению кредитного отчета либо информации, составляющей кредитную историю и входящей в кредитный отчет, если такие действия не содержат уголовно наказуемого деяния | K4: =VLOOKUP(A4,'компании+описание'!$A$1:$D$438,4,) -> По результатам рассмотрения материалов дела об административном правонарушении № ЦА-38-ЮЛ-26-92, возбужденного за совершение административного правонарушения, ответственность за которое предусмотрена частью 6 статьи 15.29 КоАП РФ, Обществу с ограниченной ответственностью «Управляющая компания «Атон-менеджмент» назначено административное наказание в виде штрафа в размере 700 000 рублей. Постановление вступило в законную силу 17.02.2026.По результатам рассмотрения материалов дела об административном правонарушении № ЦА-38-ЮЛ-26-93, возбужденного за совершение административного правонарушения, ответственность за которое предусмотрена частью 12 статьи 15.29 КоАП РФ, Обществу с ограниченной ответственностью «Управляющая компания «Атон-менеджмент» назначено административное наказание в виде штрафа в размере 320 000 рублей. Постановление вступило в законную силу 17.02.2026.
A5: 3 | B5: 46066 | C5: Акционерное общество_x000D_ Управляющая компания «Центр Эссет Менеджмент» | D5: Юридическое лицо | E5: ч.12 ст.15.29 КоАП РФ | F5: предупреждение | G5: 300000 | H5: 500000 | I5: Предупреждение | J5: =VLOOKUP(E5,статьи!$G$2:$H$24,2,TRUE) -> Незаконные действия по получению или предоставлению кредитного отчета либо информации, составляющей кредитную историю и входящей в кредитный отчет, если такие действия не содержат уголовно наказуемого деяния | K5: =VLOOKUP(A5,'компании+описание'!$A$1:$D$438,4,) -> По результатам рассмотрения материалов дела об административном правонарушении № ЦА-38-ЮЛ-26-12, возбужденного за совершение административного правонарушения, ответственность за которое предусмотрена частью 12 статьи 15.29 КоАП РФ, Акционерному обществу Управляющей компании «Центр Эссет Менеджмент» назначено административное наказание в виде предупреждения. Постановление вступило в законную силу 13.02.2026.
A6: 4 | B6: 46063 | C6: АО «ИК «РИКОМ-ТРАСТ» | D6: Юридическое лицо | E6: ч.9 ст.15.29 КоАП РФ | F6: 1000000 | G6: 700000 | H6: 1000000 | I6: Максимум | J6: =VLOOKUP(E6,статьи!$G$2:$H$24,2,TRUE) -> 1. Неисполнение акционерным обществом, профессиональным участником рынка ценных бумаг, управляющей компанией акционерного инвестиционного фонда, паевого инвестиционного фонда или негосударственного пенсионного фонда либо специализированным депозитарием акционерного инвестиционного фонда, паевого инвестиционного фонда или негосударственного пенсионного фонда обязанности по хранению документов, которые предусмотрены законодательством об акционерных обществах, о рынке ценных бумаг, об инвестиционных фондах и принятыми в соответствии с ним нормативными правовыми актами и хранение которых является обязательным, а также нарушение установленных порядка и сроков хранения таких документов | K6: =VLOOKUP(A6,'компании+описание'!$A$1:$D$438,4,) -> По результатам рассмотрения материалов дела об административном правонарушении № ЦА-34-ЮЛ-26-294, возбужденного за совершение административного правонарушения, ответственность за которое предусмотрена частью 9 статьи 15.29 КоАП РФ, акционерному обществу «Инвестиционная компания «РИКОМ-ТРАСТ» назначено административное наказание в виде штрафа размером 1 000 000 (один миллион) рублей. Постановление от 26.01.2026 № 26-294/3110-1 о назначении административного наказания вступило в законную силу 10.02.2026.
A7: 5 | B7: 46063 | C7: Акционерное общество ВИМ Инвестиции | D7: Юридическое лицо | E7: ч.12 ст.15.29 КоАП РФ | F7: 350000 | G7: 300000 | H7: 500000 | I7: В диапазоне | J7: =VLOOKUP(E7,статьи!$G$2:$H$24,2,TRUE) -> Незаконные действия по получению или предоставлению кредитного отчета либо информации, составляющей кредитную историю и входящей в кредитный отчет, если такие действия не содержат уголовно наказуемого деяния | K7: =VLOOKUP(A7,'компании+описание'!$A$1:$D$438,4,) -> По результатам рассмотрения материалов дела об административном правонарушении № ЦА-38-ЮЛ-26-19, возбуждённого за совершение административного правонарушения, ответственность за которое предусмотрена частью 12 статьи 15.29 Кодекса Российской Федерации об административных правонарушениях, АО ВИМ Инвестиции назначено административное наказание в виде штрафа в размере 350 000 рублей. Постановление вступило в законную силу 10.02.2026.
A8: 6 | B8: 46063 | C8: Общество с ограниченной_x000D_ ответственностью_x000D_ «Управляющая компания_x000D_ «Ресурс» | D8: Юридическое лицо | E8: ч.6 ст.15.29 КоАП РФ | F8: предупреждение | G8: 700000 | H8: 1000000 | I8: Предупреждение | J8: =VLOOKUP(E8,статьи!$G$2:$H$24,2,TRUE) -> 1. Неисполнение акционерным обществом, профессиональным участником рынка ценных бумаг, управляющей компанией акционерного инвестиционного фонда, паевого инвестиционного фонда или негосударственного пенсионного фонда либо специализированным депозитарием акционерного инвестиционного фонда, паевого инвестиционного фонда или негосударственного пенсионного фонда обязанности по хранению документов, которые предусмотрены законодательством об акционерных обществах, о рынке ценных бумаг, об инвестиционных фондах и принятыми в соответствии с ним нормативными правовыми актами и хранение которых является обязательным, а также нарушение установленных порядка и сроков хранения таких документов | K8: =VLOOKUP(A8,'компании+описание'!$A$1:$D$438,4,) -> По результатам рассмотрения материалов дела об административном правонарушении № ЦА-38-ЮЛ-26-2, возбужденного за совершение административного правонарушения, ответственность за которое предусмотрена частью 6 статьи 15.29 КоАП РФ, Обществу с ограниченной ответственностью «Управляющая компания «Ресурс» назначено административное наказание в виде предупреждения. Постановление вступило в законную силу 10.02.2026.
A9: 7 | B9: 46063 | C9: Общество с ограниченной ответственностью «ТрастЮнион Эссет Менеджмент» | D9: Юридическое лицо | E9: ч.12 ст.15.29 КоАП РФ | F9: предупреждение | G9: 300000 | H9: 500000 | I9: Предупреждение | J9: =VLOOKUP(E9,статьи!$G$2:$H$24,2,TRUE) -> Незаконные действия по получению или предоставлению кредитного отчета либо информации, составляющей кредитную историю и входящей в кредитный отчет, если такие действия не содержат уголовно наказуемого деяния | K9: =VLOOKUP(A9,'компании+описание'!$A$1:$D$438,4,) -> По результатам рассмотрения материалов дела об административном правонарушении № ЦА-38-ЮЛ-26-85, возбужденного за совершение административного правонарушения, ответственность за которое предусмотрена частью 12 статьи 15.29 КоАП РФ, Обществу с ограниченной ответственностью «ТрастЮнион Эссет Менеджмент» назначено административное наказание в виде предупреждения. Постановление вступило в законную силу 10.02.2026.
A10: 8 | B10: 46063 | C10: Акционерное общество «Управляющая Компания ТРИНФИКО» | D10: Юридическое лицо | E10: ч.5 ст.15.29 КоАП РФ | F10: 250000 | G10: 500000 | H10: 700000 | I10: Ниже минимума | J10: =VLOOKUP(E10,статьи!$G$2:$H$24,2,TRUE) -> 1. Неисполнение акционерным обществом, профессиональным участником рынка ценных бумаг, управляющей компанией акционерного инвестиционного фонда, паевого инвестиционного фонда или негосударственного пенсионного фонда либо специализированным депозитарием акционерного инвестиционного фонда, паевого инвестиционного фонда или негосударственного пенсионного фонда обязанности по хранению документов, которые предусмотрены законодательством об акционерных обществах, о рынке ценных бумаг, об инвестиционных фондах и принятыми в соответствии с ним нормативными правовыми актами и хранение которых является обязательным, а также нарушение установленных порядка и сроков хранения таких документов | K10: =VLOOKUP(A10,'компании+описание'!$A$1:$D$438,4,) -> По результатам рассмотрения материалов дела об административном правонарушении № ЦА-38-ЮЛ-26-6, возбужденного за совершение административного правонарушения, ответственность за которое предусмотрена частью 5 статьи 15.29 КоАП РФ, Акционерному обществу «Управляющая Компания ТРИНФИКО» назначено административное наказание в виде штрафа в размере 250 000 рублей. Постановление вступило в законную силу 10.02.2026.
A11: 9 | B11: 46062 | C11: ООО «Цифра брокер» | D11: Юридическое лицо | E11: ч.12 ст.15.29 КоАП РФ | F11: 300000 | G11: 300000 | H11: 500000 | I11: Минимум | J11: =VLOOKUP(E11,статьи!$G$2:$H$24,2,TRUE) -> Незаконные действия по получению или предоставлению кредитного отчета либо информации, составляющей кредитную историю и входящей в кредитный отчет, если такие действия не содержат уголовно наказуемого деяния | K11: =VLOOKUP(A11,'компании+описание'!$A$1:$D$438,4,) -> По результатам рассмотрения материалов дела об административном правонарушении № ЦА-34-ЮЛ-26-191, возбужденного за совершение административного правонарушения, ответственность за которое предусмотрена частью 12 статьи 15.29 КоАП РФ, ООО «Цифра брокер» назначено административное наказание в виде штрафа в размере 300 000 рублей. Постановление № 26-191/3110-1 о назначении административного наказания вступило в законную силу 07.02.2026.
A12: 10 | B12: 46059 | C12: Голубков Виктор Владимирович | D12: Гражданин | E12: ст.15.30 КоАП РФ | F12: 3000 | G12: 3000 | H12: 5000 | I12: Минимум | J12: =VLOOKUP(E12,статьи!$G$2:$H$24,2,TRUE) -> Незаконные действия по получению или предоставлению кредитного отчета либо информации, составляющей кредитную историю и входящей в кредитный отчет, если такие действия не содержат уголовно наказуемого деяния | K12: =VLOOKUP(A12,'компании+описание'!$A$1:$D$438,4,) -> По результатам рассмотрения материалов дела об административном правонарушении № ЦА-34-Гр-25-21433, возбужденного за совершение административного правонарушения, ответственность за которое предусмотрена статьей 15.30 Кодекса Российской Федерации об административных правонарушениях, Голубкову Виктору Владимировичу назначено административное наказание в виде штрафа в размере 3 000 рублей. Постановление от 18.12.2025 № 25-21433/3110-1 о назначении административного наказания вступило в законную силу 03.02.2026.
A13: 11 | B13: 46059 | C13: генеральный директор общества с ограниченной ответственностью «Тринити Шиппинг» Ярошенко Александр Иванович | D13: Должностное лицо | E13: ст.15.30 КоАП РФ | F13: 30000 | G13: 30000 | H13: 50000 | I13: Минимум | J13: =VLOOKUP(E13,статьи!$G$2:$H$24,2,TRUE) -> Незаконные действия по получению или предоставлению кредитного отчета либо информации, составляющей кредитную историю и входящей в кредитный отчет, если такие действия не содержат уголовно наказуемого деяния | K13: =VLOOKUP(A13,'компании+описание'!$A$1:$D$438,4,) -> По результатам рассмотрения материалов дела об административном правонарушении № ЦА-34-ДЛ-25-20686, возбужденного за совершение административного правонарушения, ответственность за которое предусмотрена статьей 15.30 Кодекса Российской Федерации об административных правонарушениях, генеральному директору общества с ограниченной ответственностью «Тринити Шиппинг» Ярошенко Александру Ивановичу назначено административное наказание в виде штрафа в размере 30 000 рублей. Постановление от 25.12.2025 № 25-20686/3110-1 о назначении административного наказания вступило в законную силу 31.01.2026.
A14: 12 | B14: 46059 | C14: Гальямова Наталья Александровна | D14: Гражданин | E14: ст.15.30 КоАП РФ | F14: 3000 | G14: 3000 | H14: 5000 | I14: Минимум | J14: =VLOOKUP(E14,статьи!$G$2:$H$24,2,TRUE) -> Незаконные действия по получению или предоставлению кредитного отчета либо информации, составляющей кредитную историю и входящей в кредитный отчет, если такие действия не содержат уголовно наказуемого деяния | K14: =VLOOKUP(A14,'компании+описание'!$A$1:$D$438,4,) -> По результатам рассмотрения материалов дела об административном правонарушении № ЦА-34-ГР-25-21130, возбужденного за совершение административного правонарушения, ответственность за которое предусмотрена статьей 15.30 Кодекса Российской Федерации об административных правонарушениях, Гальямовой Наталье Александровне назначено административное наказание в виде штрафа в размере 3 000 рублей. Постановление от 25.12.2025 № 25-21130/3110-1 о назначении административного наказания вступило в законную силу 06.02.2026.
A15: 13 | B15: 46056 | C15: Чмыхало Юлия Анатольевна | D15: Гражданин | E15: ст.15.30 КоАП РФ | F15: 3000 | G15: 3000 | H15: 5000 | I15: Минимум | J15: =VLOOKUP(E15,статьи!$G$2:$H$24,2,TRUE) -> Незаконные действия по получению или предоставлению кредитного отчета либо информации, составляющей кредитную историю и входящей в кредитный отчет, если такие действия не содержат уголовно наказуемого деяния | K15: =VLOOKUP(A15,'компании+описание'!$A$1:$D$438,4,) -> По результатам рассмотрения материалов дела об административном правонарушении № ЦА-34-Гр-25-21347, возбужденного за совершение административного правонарушения, ответственность за которое предусмотрена статьей 15.30 КоАП РФ, Чмыхало Юлии Анатольевне назначено административное наказание в виде штрафа в размере 3 000 рублей. Постановление о наложении штрафа по делу об административном правонарушении от 18.12.2025 № 25-21347/3110-1 вступило в законную силу 03.02.2026.
A16: 14 | B16: 46052 | C16: Усольцева Яна Германовна | D16: Гражданин | E16: ст.15.30 КоАП РФ | F16: 3000 | G16: 3000 | H16: 5000 | I16: Минимум | J16: =VLOOKUP(E16,статьи!$G$2:$H$24,2,TRUE) -> Незаконные действия по получению или предоставлению кредитного отчета либо информации, составляющей кредитную историю и входящей в кредитный отчет, если такие действия не содержат уголовно наказуемого деяния | K16: =VLOOKUP(A16,'компании+описание'!$A$1:$D$438,4,) -> По результатам рассмотрения материалов дела об административном правонарушении № ЦА-34-Гр-25-21234, возбужденного за совершение административного правонарушения, ответственность за которое предусмотрена статьей 15.30 КоАП РФ, Усольцевой Яне Германовне назначено административное наказание в виде штрафа в размере 3 000 рублей. Постановление о наложении штрафа по делу об административном правонарушении от 17.12.2025 № 25-21234/3110-1 вступило в законную силу 30.01.2026.
A17: 15 | B17: 46052 | C17: Краснова Галина Ивановна | D17: Гражданин | E17: ст.15.30 КоАП РФ | F17: 3000 | G17: 3000 | H17: 5000 | I17: Минимум | J17: =VLOOKUP(E17,статьи!$G$2:$H$24,2,TRUE) -> Незаконные действия по получению или предоставлению кредитного отчета либо информации, составляющей кредитную историю и входящей в кредитный отчет, если такие действия не содержат уголовно наказуемого деяния | K17: =VLOOKUP(A17,'компании+описание'!$A$1:$D$438,4,) -> По результатам рассмотрения материалов дела об административном правонарушении № ЦА-34-Гр-25-16976, возбужденного за совершение административного правонарушения, ответственность за которое предусмотрена статьей 15.30 КоАП РФ, Красновой Галине Ивановне назначено административное наказание в виде штрафа в размере 3 000 рублей. Постановление о наложении штрафа по делу об административном правонарушении от 16.10.2025 № 25-16976/3110-1 вступило в законную силу 30.01.2026.
A18: 16 | B18: 46052 | C18: Артамонов Валерий Геннадьевич | D18: Гражданин | E18: ст.15.30 КоАП РФ | F18: 3000 | G18: 3000 | H18: 5000 | I18: Минимум | J18: =VLOOKUP(E18,статьи!$G$2:$H$24,2,TRUE) -> Незаконные действия по получению или предоставлению кредитного отчета либо информации, составляющей кредитную историю и входящей в кредитный отчет, если такие действия не содержат уголовно наказуемого деяния | K18: =VLOOKUP(A18,'компании+описание'!$A$1:$D$438,4,) -> По результатам рассмотрения материалов дела об административном правонарушении № ЦА-34-Гр-25-19400, возбужденного за совершение административного правонарушения, ответственность за которое предусмотрена статьей 15.30 КоАП РФ, Артамонову Валерию Геннадьевичу назначено административное наказание в виде штрафа в размере 3 000 рублей. Постановление о наложении штрафа по делу об административном правонарушении от 20.11.2025 № 25-19400/3110-1 вступило в законную силу 24.01.2026.
A19: 17 | B19: 46052 | C19: Манюкова Татьяна Васильевна | D19: Гражданин | E19: ст.15.30 КоАП РФ | F19: 3000 | G19: 3000 | H19: 5000 | I19: Минимум | J19: =VLOOKUP(E19,статьи!$G$2:$H$24,2,TRUE) -> Незаконные действия по получению или предоставлению кредитного отчета либо информации, составляющей кредитную историю и входящей в кредитный отчет, если такие действия не содержат уголовно наказуемого деяния | K19: =VLOOKUP(A19,'компании+описание'!$A$1:$D$438,4,) -> По результатам рассмотрения материалов дела об административном правонарушении № ЦА-34-Гр-25-20359, возбужденного за совершение административного правонарушения, ответственность за которое предусмотрена статьей 15.30 КоАП РФ, Манюковой Татьяне Васильевне назначено административное наказание в виде штрафа в размере 3 000 рублей. Постановление о наложении штрафа по делу об административном правонарушении от 04.12.2025 № 25-20359/3110-1 вступило в законную силу 30.01.2026.
A20: 18 | B20: 46052 | C20: Доценко Марина Сергеевна | D20: Гражданин | E20: ст.15.30 КоАП РФ | F20: 3000 | G20: 3000 | H20: 5000 | I20: Минимум | J20: =VLOOKUP(E20,статьи!$G$2:$H$24,2,TRUE) -> Незаконные действия по получению или предоставлению кредитного отчета либо информации, составляющей кредитную историю и входящей в кредитный отчет, если такие действия не содержат уголовно наказуемого деяния | K20: =VLOOKUP(A20,'компании+описание'!$A$1:$D$438,4,) -> По результатам рассмотрения материалов дела об административном правонарушении № ЦА-34-Гр-25-20532, возбужденного за совершение административного правонарушения, ответственность за которое предусмотрена статьей 15.30 КоАП РФ, Доценко Марине Сергеевне назначено административное наказание в виде штрафа в размере 3 000 рублей. Постановление о наложении штрафа по делу об административном правонарушении от 08.12.2025 № 25-20532/3110-1 вступило в законную силу 30.01.2026.
A21: 19 | B21: 46052 | C21: Гальямов Марсель Геральдович | D21: Гражданин | E21: ст.15.30 КоАП РФ | F21: 3000 | G21: 3000 | H21: 5000 | I21: Минимум | J21: =VLOOKUP(E21,статьи!$G$2:$H$24,2,TRUE) -> Незаконные действия по получению или предоставлению кредитного отчета либо информации, составляющей кредитную историю и входящей в кредитный отчет, если такие действия не содержат уголовно наказуемого деяния | K21: =VLOOKUP(A21,'компании+описание'!$A$1:$D$438,4,) -> По результатам рассмотрения материалов дела об административном правонарушении № ЦА-34-Гр-25-21126, возбужденного за совершение административного правонарушения, ответственность за которое предусмотрена статьей 15.30 КоАП РФ, Гальямову Марселю Геральдовичу назначено административное наказание в виде штрафа в размере 3 000 рублей. Постановление о наложении штрафа по делу об административном правонарушении от 16.12.2025 № 25-21126/3110-1 вступило в законную силу 30.01.2026.
... A36: 34 | B36: 46041 | C36: Тихомиров Вадим Владимирович | D36: Гражданин | E36: ст.15.30 КоАП РФ | F36: 3000 | G36: 3000 | H36: 5000 | I36: Минимум | J36: =VLOOKUP(E36,статьи!$G$2:$H$24,2,TRUE) -> Незаконные действия по получению или предоставлению кредитного отчета либо информации, составляющей кредитную историю и входящей в кредитный отчет, если такие действия не содержат уголовно наказуемого деяния | K36: =VLOOKUP(A36,'компании+описание'!$A$1:$D$438,4,) -> По результатам рассмотрения материалов дела об административном правонарушении № ЦА-34-Гр-25-21119, возбужденного за совершение административного правонарушения, ответственность за которое предусмотрена статьей 15.30 Кодекса Российской Федерации об административных правонарушениях, Тихомирову Вадиму Владимировичу назначено административное наказание в виде штрафа в размере 3 000 рублей. Постановление от 16.12.2025 № 25-21119/3110-1 о назначении административного наказания вступило в законную силу 13.01.2026.
A37: 35 | B37: 46037 | C37: ООО "Тринити Шиппинг" | D37: Юридическое лицо | E37: ст.15.30 КоАП РФ | F37: 700000 | G37: 700000 | H37: в размере суммы излишнего дохода… но не менее 700 000 рублей | I37: Минимум | J37: =VLOOKUP(E37,статьи!$G$2:$H$24,2,TRUE) -> Незаконные действия по получению или предоставлению кредитного отчета либо информации, составляющей кредитную историю и входящей в кредитный отчет, если такие действия не содержат уголовно наказуемого деяния | K37: =VLOOKUP(A37,'компании+описание'!$A$1:$D$438,4,) -> По результатам рассмотрения материалов дела об административном правонарушении № ЦА-34-ЮЛ-25-20682, возбужденного за совершение административного правонарушения, ответственность за которое предусмотрена статьей 15.30 Кодекса Российской Федерации об административных правонарушениях, ООО "Тринити Шиппинг" назначено административное наказание в виде штрафа в размере 700 000 рублей. Постановление от 13.10.2025 № 25-20682/3110-1 о назначении административного наказания вступило в законную силу 30.12.2025.
A38: 36 | B38: 46037 | C38: Бурыкин Иван Терентьевич | D38: Гражданин | E38: ст.15.30 КоАП РФ | F38: 3000 | G38: 3000 | H38: 5000 | I38: Минимум | J38: =VLOOKUP(E38,статьи!$G$2:$H$24,2,TRUE) -> Незаконные действия по получению или предоставлению кредитного отчета либо информации, составляющей кредитную историю и входящей в кредитный отчет, если такие действия не содержат уголовно наказуемого деяния | K38: =VLOOKUP(A38,'компании+описание'!$A$1:$D$438,4,) -> По результатам рассмотрения материалов дела об административном правонарушении № ЦА-34-Гр-25-16635, возбужденного за совершение административного правонарушения, ответственность за которое предусмотрена статьей 15.30 Кодекса Российской Федерации об административных правонарушениях, Бурыкину Ивану Терентьевичу назначено административное наказание в виде штрафа в размере 3 000 рублей. Постановление от 13.10.2025 № 25-16635/3110-1 о назначении административного наказания вступило в законную силу 30.12.2025.
A39: 37 | B39: 46035 | C39: Колесникова Надежда Вячеславовна | D39: Гражданин | E39: ст.15.30 КоАП РФ | F39: 3000 | G39: 3000 | H39: 5000 | I39: Минимум | J39: =VLOOKUP(E39,статьи!$G$2:$H$24,2,TRUE) -> Незаконные действия по получению или предоставлению кредитного отчета либо информации, составляющей кредитную историю и входящей в кредитный отчет, если такие действия не содержат уголовно наказуемого деяния | K39: =VLOOKUP(A39,'компании+описание'!$A$1:$D$438,4,) -> По результатам рассмотрения материалов дела об административном правонарушении № ЦА-34-Гр-25-20369, возбужденного за совершение административного правонарушения, ответственность за которое предусмотрена статьей 15.30 Кодекса Российской Федерации об административных правонарушениях, Колесниковой Надежде Вячеславовне назначено административное наказание в виде штрафа в размере 3 000 рублей. Постановление от 04.12.2025 № 25-20369/3110-1 о назначении административного наказания вступило в законную силу 13.01.2026.
A40: 38 | B40: 46035 | C40: Мазнев Андрей Вячеславович | D40: Гражданин | E40: ст.15.30 КоАП РФ | F40: 3000 | G40: 3000 | H40: 5000 | I40: Минимум | J40: =VLOOKUP(E40,статьи!$G$2:$H$24,2,TRUE) -> Незаконные действия по получению или предоставлению кредитного отчета либо информации, составляющей кредитную историю и входящей в кредитный отчет, если такие действия не содержат уголовно наказуемого деяния | K40: =VLOOKUP(A40,'компании+описание'!$A$1:$D$438,4,) -> По результатам рассмотрения материалов дела об административном правонарушении № ЦА-34-Гр-25-20432, возбужденного за совершение административного правонарушения, ответственность за которое предусмотрена статьей 15.30 Кодекса Российской Федерации об административных правонарушениях, Мазневу Андрею Вячеславовичу назначено административное наказание в виде штрафа в размере 3 000 рублей. Постановление от 04.12.2025 № 25-20432/3110-1 о назначении административного наказания вступило в законную силу 13.01.2026.
A41: 39 | B41: 46035 | C41: Мазнев Сергей Вячеславович | D41: Гражданин | E41: ст.15.30 КоАП РФ | F41: 3000 | G41: 3000 | H41: 5000 | I41: Минимум | J41: =VLOOKUP(E41,статьи!$G$2:$H$24,2,TRUE) -> Незаконные действия по получению или предоставлению кредитного отчета либо информации, составляющей кредитную историю и входящей в кредитный отчет, если такие действия не содержат уголовно наказуемого деяния | K41: =VLOOKUP(A41,'компании+описание'!$A$1:$D$438,4,) -> По результатам рассмотрения материалов дела об административном правонарушении № ЦА-34-Гр-25-20433, возбужденного за совершение административного правонарушения, ответственность за которое предусмотрена статьей 15.30 Кодекса Российской Федерации об административных правонарушениях, Мазневу Сергею Вячеславовичу назначено административное наказание в виде штрафа в размере 3 000 рублей. Постановление от 04.12.2025 № 25-20433/3110-1 о назначении административного наказания вступило в законную силу 13.01.2026.
A42: 40 | B42: 46035 | C42: Дмитриев Андрей Николаевич | D42: Гражданин | E42: ст.15.30 КоАП РФ | F42: 3000 | G42: 3000 | H42: 5000 | I42: Минимум | J42: =VLOOKUP(E42,статьи!$G$2:$H$24,2,TRUE) -> Незаконные действия по получению или предоставлению кредитного отчета либо информации, составляющей кредитную историю и входящей в кредитный отчет, если такие действия не содержат уголовно наказуемого деяния | K42: =VLOOKUP(A42,'компании+описание'!$A$1:$D$438,4,) -> По результатам рассмотрения материалов дела об административном правонарушении № ЦА-34-Гр-25-20370, возбужденного за совершение административного правонарушения, ответственность за которое предусмотрена статьей 15.30 Кодекса Российской Федерации об административных правонарушениях, Дмитриеву Андрею Николаевичу назначено административное наказание в виде штрафа в размере 3 000 рублей. Постановление от 04.12.2025 № 25-20370/3110-1 о назначении административного наказания вступило в законную силу 13.01.2026.
A43: 41 | B43: 46035 | C43: Малык Герман Андреевич | D43: Гражданин | E43: ст.15.30 КоАП РФ | F43: 3000 | G43: 3000 | H43: 5000 | I43: Минимум | J43: =VLOOKUP(E43,статьи!$G$2:$H$24,2,TRUE) -> Незаконные действия по получению или предоставлению кредитного отчета либо информации, составляющей кредитную историю и входящей в кредитный отчет, если такие действия не содержат уголовно наказуемого деяния | K43: =VLOOKUP(A43,'компании+описание'!$A$1:$D$438,4,) -> По результатам рассмотрения материалов дела об административном правонарушении № ЦА-34-Гр-25-20681, возбужденного за совершение административного правонарушения, ответственность за которое предусмотрена статьей 15.30 Кодекса Российской Федерации об административных правонарушениях, Малыку Герману Андреевичу назначено административное наказание в виде штрафа в размере 3 000 рублей. Постановление от 09.12.2025 № 25-20681/3110-1 о назначении административного наказания вступило в законную силу 13.01.2026.
A44: 42 | B44: 46035 | C44: Усачев Андрей Николаевич | D44: Гражданин | E44: ст.15.30 КоАП РФ | F44: 3000 | G44: 3000 | H44: 5000 | I44: Минимум | J44: =VLOOKUP(E44,статьи!$G$2:$H$24,2,TRUE) -> Незаконные действия по получению или предоставлению кредитного отчета либо информации, составляющей кредитную историю и входящей в кредитный отчет, если такие действия не содержат уголовно наказуемого деяния | K44: =VLOOKUP(A44,'компании+описание'!$A$1:$D$438,4,) -> По результатам рассмотрения материалов дела об административном правонарушении № ЦА-34-Гр-25-20372, возбужденного за совершение административного правонарушения, ответственность за которое предусмотрена статьей 15.30 Кодекса Российской Федерации об административных правонарушениях, Усачеву Андрею Николаевичу назначено административное наказание в виде штрафа в размере 3 000 рублей. Постановление от 04.12.2025 № 25-20372/3110-1 о назначении административного наказания вступило в законную силу 13.01.2026.
A45: 43 | B45: 46035 | C45: Шушин Игорь Борисович | D45: Гражданин | E45: ст.15.30 КоАП РФ | F45: 3000 | G45: 3000 | H45: 5000 | I45: Минимум | J45: =VLOOKUP(E45,статьи!$G$2:$H$24,2,TRUE) -> Незаконные действия по получению или предоставлению кредитного отчета либо информации, составляющей кредитную историю и входящей в кредитный отчет, если такие действия не содержат уголовно наказуемого деяния | K45: =VLOOKUP(A45,'компании+описание'!$A$1:$D$438,4,) -> По результатам рассмотрения материалов дела об административном правонарушении № ЦА-34-Гр-25-19780, возбужденного за совершение административного правонарушения, ответственность за которое предусмотрена статьей 15.30 Кодекса Российской Федерации об административных правонарушениях, Шушину Игорю Борисовичу назначено административное наказание в виде штрафа в размере 3 000 рублей. Постановление от 26.11.2025 № 25-19780/3110-1 о назначении административного наказания вступило в законную силу 13.01.2026.
A46: 44 | B46: 46035 | C46: Шушина Татьяна Геннадьевна | D46: Гражданин | E46: ст.15.30 КоАП РФ | F46: 3000 | G46: 3000 | H46: 5000 | I46: Минимум | J46: =VLOOKUP(E46,статьи!$G$2:$H$24,2,TRUE) -> Незаконные действия по получению или предоставлению кредитного отчета либо информации, составляющей кредитную историю и входящей в кредитный отчет, если такие действия не содержат уголовно наказуемого деяния | K46: =VLOOKUP(A46,'компании+описание'!$A$1:$D$438,4,) -> По результатам рассмотрения материалов дела об административном правонарушении № ЦА-34-Гр-25-19781, возбужденного за совершение административного правонарушения, ответственность за которое предусмотрена статьей 15.30 Кодекса Российской Федерации об административных правонарушениях, Шушиной Татьяне Геннадьевне назначено административное наказание в виде штрафа в размере 3 000 рублей. Постановление от 26.11.2025 № 25-19781/3110-1 о назначении административного наказания вступило в законную силу 13.01.2026.
A47: 45 | B47: 46035 | C47: Богачев Вячеслав Анатольевич | D47: Гражданин | E47: ст.15.30 КоАП РФ | F47: 3000 | G47: 3000 | H47: 5000 | I47: Минимум | J47: =VLOOKUP(E47,статьи!$G$2:$H$24,2,TRUE) -> Незаконные действия по получению или предоставлению кредитного отчета либо информации, составляющей кредитную историю и входящей в кредитный отчет, если такие действия не содержат уголовно наказуемого деяния | K47: =VLOOKUP(A47,'компании+описание'!$A$1:$D$438,4,) -> По результатам рассмотрения материалов дела об административном правонарушении № ЦА-34-Гр-25-19034, возбужденного за совершение административного правонарушения, ответственность за которое предусмотрена статьей 15.30 Кодекса Российской Федерации об административных правонарушениях, Богачеву Вячеславу Анатольевичу назначено административное наказание в виде штрафа в размере 3 000 рублей. Постановление от 11.11.2025 № 25-19034/3110-1 о назначении административного наказания вступило в законную силу 13.01.2026.
A48: 46 | B48: 46035 | C48: Султанаева Эльвира Дамировна | D48: Гражданин | E48: ст.15.30 КоАП РФ | F48: 3000 | G48: 3000 | H48: 5000 | I48: Минимум | J48: =VLOOKUP(E48,статьи!$G$2:$H$24,2,TRUE) -> Незаконные действия по получению или предоставлению кредитного отчета либо информации, составляющей кредитную историю и входящей в кредитный отчет, если такие действия не содержат уголовно наказуемого деяния | K48: =VLOOKUP(A48,'компании+описание'!$A$1:$D$438,4,) -> По результатам рассмотрения материалов дела об административном правонарушении № ЦА-34-Гр-25-20133, возбужденного за совершение административного правонарушения, ответственность за которое предусмотрена статьей 15.30 Кодекса Российской Федерации об административных правонарушениях, Султанаевой Эльвире Дамировне назначено административное наказание в виде штрафа в размере 3 000 рублей. Постановление от 02.12.2025 № 25-20133/3110-1 о назначении административного наказания вступило в законную силу 13.01.2026.
A49: 47 | B49: 46035 | C49: Бурыкин Иван Иванович | D49: Гражданин | E49: ст.15.30 КоАП РФ | F49: 3000 | G49: 3000 | H49: 5000 | I49: Минимум | J49: =VLOOKUP(E49,статьи!$G$2:$H$24,2,TRUE) -> Незаконные действия по получению или предоставлению кредитного отчета либо информации, составляющей кредитную историю и входящей в кредитный отчет, если такие действия не содержат уголовно наказуемого деяния | K49: =VLOOKUP(A49,'компании+описание'!$A$1:$D$438,4,) -> По результатам рассмотрения материалов дела об административном правонарушении № ЦА-34-Гр-25-20728, возбужденного за совершение административного правонарушения, ответственность за которое предусмотрена статьей 15.30 Кодекса Российской Федерации об административных правонарушениях, Бурыкину Ивану Ивановичу назначено административное наказание в виде штрафа в размере 3 000 рублей. Постановление от 10.12.2025 № 25-20728/3110-1 о назначении административного наказания вступило в законную силу 13.01.2026.
... A53: 51 | B53: 46035 | C53: ООО «ПФЛ НОВЫЕ ИНВЕСТИЦИИ» | D53: Юридическое лицо | E53: ч.1 ст.19.7.3 КоАП РФ | F53: 350000 | G53: 500000 | H53: 700000 | I53: Ниже минимума | J53: =VLOOKUP(E53,статьи!$G$2:$H$24,2,TRUE) -> Незаконные действия по получению или предоставлению кредитного отчета либо информации, составляющей кредитную историю и входящей в кредитный отчет, если такие действия не содержат уголовно наказуемого деяния | K53: =VLOOKUP(A53,'компании+описание'!$A$1:$D$438,4,) -> По результатам рассмотрения материалов дела об административном правонарушении № ЦА-34-ЮЛ-25-21724, возбужденного за совершение административного правонарушения, ответственность за которое предусмотрена частью 1 статьи 19.7.3 Кодекса Российской Федерации об административных правонарушениях, ОБЩЕСТВУ С ОГРАНИЧЕННОЙ ОТВЕТСТВЕННОСТЬЮ «ПФЛ НОВЫЕ ИНВЕСТИЦИИ» назначено административное наказание в виде штрафа в размере 350 000 (триста пятьдесят тысяч) рублей. Постановление о наложении штрафа по делу об административном правонарушении от 18.12.2025 № 25-21724/3110-1 вступило в законную силу 13.01.2026.
A54: 52 | B54: 46035 | C54: ООО «ТОЧКА ИНВЕСТИЦИИ» | D54: Юридическое лицо | E54: ч.1 ст.19.7.3 КоАП РФ | F54: предупреждение | G54: 500000 | H54: 700000 | I54: Предупреждение | J54: =VLOOKUP(E54,статьи!$G$2:$H$24,2,TRUE) -> Незаконные действия по получению или предоставлению кредитного отчета либо информации, составляющей кредитную историю и входящей в кредитный отчет, если такие действия не содержат уголовно наказуемого деяния | K54: =VLOOKUP(A54,'компании+описание'!$A$1:$D$438,4,) -> По результатам рассмотрения материалов дела об административном правонарушении № ЦА-34-ЮЛ-25-21885, возбужденного за совершение административного правонарушения, ответственность за которое предусмотрена частью 1 статьи 19.7.3 Кодекса Российской Федерации об административных правонарушениях, ОБЩЕСТВУ С ОГРАНИЧЕННОЙ ОТВЕТСТВЕННОСТЬЮ «ТОЧКА ИНВЕСТИЦИИ» назначено административное наказание в виде предупреждения. Постановление о назначении административного наказания от 18.12.2025 № ЦА-34-ЮЛ-25-21885/3120-1 вступило в законную силу 13.01.2026.
A55: 53 | B55: 46035 | C55: Акционерное общество "Частные Активы" | D55: Юридическое лицо | E55: ч.12 ст.15.29 КоАП РФ | F55: предупреждение | G55: 300000 | H55: 500000 | I55: Предупреждение | J55: =VLOOKUP(E55,статьи!$G$2:$H$24,2,TRUE) -> Незаконные действия по получению или предоставлению кредитного отчета либо информации, составляющей кредитную историю и входящей в кредитный отчет, если такие действия не содержат уголовно наказуемого деяния | K55: =VLOOKUP(A55,'компании+описание'!$A$1:$D$438,4,) -> По результатам рассмотрения материалов дела об административном правонарушении № ЦА-38-ЮЛ-25-21237, возбуждённого за совершение административного правонарушения, ответственность за которое предусмотрена частью 12 статьи 15.29 Кодекса Российской Федерации об административных правонарушениях, АО "Частные Активы" назначено административное наказание в виде предупреждения. Постановление вступило в законную силу 13.01.2026.
A56: 54 | B56: 46035 | C56: Общество с ограниченной ответственностью Управляющая Компания "Юнион Инвест Групп" | D56: Юридическое лицо | E56: ч.9 ст.15.29 КоАП РФ | F56: 350000 | G56: 700000 | H56: 1000000 | I56: Ниже минимума | J56: =VLOOKUP(E56,статьи!$G$2:$H$24,2,TRUE) -> 1. Неисполнение акционерным обществом, профессиональным участником рынка ценных бумаг, управляющей компанией акционерного инвестиционного фонда, паевого инвестиционного фонда или негосударственного пенсионного фонда либо специализированным депозитарием акционерного инвестиционного фонда, паевого инвестиционного фонда или негосударственного пенсионного фонда обязанности по хранению документов, которые предусмотрены законодательством об акционерных обществах, о рынке ценных бумаг, об инвестиционных фондах и принятыми в соответствии с ним нормативными правовыми актами и хранение которых является обязательным, а также нарушение установленных порядка и сроков хранения таких документов | K56: =VLOOKUP(A56,'компании+описание'!$A$1:$D$438,4,) -> По результатам рассмотрения материалов дела об административном правонарушении № ЦА-38-ЮЛ-25-22094, возбуждённого за совершение административного правонарушения, ответственность за которое предусмотрена частью 9 статьи 15.29 Кодекса Российской Федерации об административных правонарушениях, ООО УК "Юнион Инвест Групп" назначено административное наказание в виде штрафа в размере 350 000 рублей. Постановление вступило в законную силу 13.01.2026.По результатам рассмотрения материалов дела об административном правонарушении № ЦА-38-ЮЛ-25-22095, возбуждённого за совершение административного правонарушения, ответственность за которое предусмотрена частью 12 статьи 15.29 Кодекса Российской Федерации об административных правонарушениях, ООО УК "Юнион Инвест Групп" назначено административное наказание в виде штрафа в размере 150 000 рублей. Постановление вступило в законную силу 13.01.2026.
A57: 54 | B57: 46035 | C57: Общество с ограниченной ответственностью Управляющая Компания "Юнион Инвест Групп" | D57: Юридическое лицо | E57: ч.12 ст.15.29 КоАП РФ | F57: 150000 | G57: 300000 | H57: 500000 | I57: Ниже минимума | J57: =VLOOKUP(E57,статьи!$G$2:$H$24,2,TRUE) -> Незаконные действия по получению или предоставлению кредитного отчета либо информации, составляющей кредитную историю и входящей в кредитный отчет, если такие действия не содержат уголовно наказуемого деяния | K57: =VLOOKUP(A57,'компании+описание'!$A$1:$D$438,4,) -> По результатам рассмотрения материалов дела об административном правонарушении № ЦА-38-ЮЛ-25-22094, возбуждённого за совершение административного правонарушения, ответственность за которое предусмотрена частью 9 статьи 15.29 Кодекса Российской Федерации об административных правонарушениях, ООО УК "Юнион Инвест Групп" назначено административное наказание в виде штрафа в размере 350 000 рублей. Постановление вступило в законную силу 13.01.2026.По результатам рассмотрения материалов дела об административном правонарушении № ЦА-38-ЮЛ-25-22095, возбуждённого за совершение административного правонарушения, ответственность за которое предусмотрена частью 12 статьи 15.29 Кодекса Российской Федерации об административных правонарушениях, ООО УК "Юнион Инвест Групп" назначено административное наказание в виде штрафа в размере 150 000 рублей. Постановление вступило в законную силу 13.01.2026.
A58: 55 | B58: 46035 | C58: Акционерное общество Негосударственный пенсионный фонд ВТБ Пенсионный фонд | D58: Юридическое лицо | E58: ч.9 ст.15.29 КоАП РФ | F58: 700000 | G58: 700000 | H58: 1000000 | I58: Минимум | J58: =VLOOKUP(E58,статьи!$G$2:$H$24,2,TRUE) -> 1. Неисполнение акционерным обществом, профессиональным участником рынка ценных бумаг, управляющей компанией акционерного инвестиционного фонда, паевого инвестиционного фонда или негосударственного пенсионного фонда либо специализированным депозитарием акционерного инвестиционного фонда, паевого инвестиционного фонда или негосударственного пенсионного фонда обязанности по хранению документов, которые предусмотрены законодательством об акционерных обществах, о рынке ценных бумаг, об инвестиционных фондах и принятыми в соответствии с ним нормативными правовыми актами и хранение которых является обязательным, а также нарушение установленных порядка и сроков хранения таких документов | K58: =VLOOKUP(A58,'компании+описание'!$A$1:$D$438,4,) -> По результатам рассмотрения материалов дела об административном правонарушении № ЦА-38-ЮЛ-25-21436, возбуждённого за совершение административного правонарушения, ответственность за которое предусмотрена частью 9 статьи 15.29 Кодекса Российской Федерации об административных правонарушениях, АО НПФ ВТБ Пенсионный фонд назначено административное наказание в виде штрафа в размере 700 000 рублей. Постановление вступило в законную силу 13.01.2026.
A59: 56 | B59: 46035 | C59: Акционерное общество «Управляющая Компания ТРИНФИКО» | D59: Юридическое лицо | E59: ч.2 ст.15.19 КоАП РФ | F59: предупреждение | G59: 700000 | H59: 1000000 | I59: Предупреждение | J59: =VLOOKUP(E59,статьи!$G$2:$H$24,2,TRUE) -> Незаконные действия по получению или предоставлению кредитного отчета либо информации, составляющей кредитную историю и входящей в кредитный отчет, если такие действия не содержат уголовно наказуемого деяния | K59: =VLOOKUP(A59,'компании+описание'!$A$1:$D$438,4,) -> По результатам рассмотрения материалов дела об административном правонарушении № ЦА-38-ЮЛ-25-21929, возбужденного за совершение административного правонарушения, ответственность за которое предусмотрена частью 2 статьи 15.19 КоАП РФ, Акционерному обществу «Управляющая Компания ТРИНФИКО» назначено административное наказание в виде предупреждения. Постановление вступило в законную силу 13.01.2026.
A60: 57 | B60: 46035 | C60: Акционерное общество «АБ Капитал» | D60: Юридическое лицо | E60: ч.2 ст.15.19 КоАП РФ | F60: предупреждение | G60: 700000 | H60: 1000000 | I60: Предупреждение | J60: =VLOOKUP(E60,статьи!$G$2:$H$24,2,TRUE) -> Незаконные действия по получению или предоставлению кредитного отчета либо информации, составляющей кредитную историю и входящей в кредитный отчет, если такие действия не содержат уголовно наказуемого деяния | K60: =VLOOKUP(A60,'компании+описание'!$A$1:$D$438,4,) -> По результатам рассмотрения материалов дела об административном правонарушении № ЦА-38-ЮЛ-25-21845, возбужденного за совершение административного правонарушения, ответственность за которое предусмотрена частью 2 статьи 15.19 КоАП РФ, Акционерному обществу «АБ Капитал» назначено административное наказание в виде предупреждения. Постановление вступило в законную силу 13.01.2026.
A61: 58 | B61: 46035 | C61: Акционерное общество «Инвестиционная компания «РИКОМ-ТРАСТ» | D61: Юридическое лицо | E61: ч.2 ст.15.29 КоАП РФ | F61: 500000 | G61: 500000 | H61: 700000 | I61: Минимум | J61: =VLOOKUP(E61,статьи!$G$2:$H$24,2,TRUE) -> Незаконные действия по получению или предоставлению кредитного отчета либо информации, составляющей кредитную историю и входящей в кредитный отчет, если такие действия не содержат уголовно наказуемого деяния | K61: =VLOOKUP(A61,'компании+описание'!$A$1:$D$438,4,) -> По результатам рассмотрения материалов дела об административном правонарушении № ЦА-38-ЮЛ-25-21513, возбужденного за совершение административного правонарушения, ответственность за которое предусмотрена частью 2 статьи 15.29 КоАП РФ, Акционерному обществу «Инвестиционная компания «РИКОМ-ТРАСТ» назначено административное наказание в виде штрафа в размере 500 000 рублей. Постановление вступило в законную силу 13.01.2026.
A62: 59 | B62: 46035 | C62: Общество с ограниченной ответственностью «Т-Капитал» | D62: Юридическое лицо | E62: ч.2 ст.15.19 КоАП РФ | F62: 700000 | G62: 700000 | H62: 1000000 | I62: Минимум | J62: =VLOOKUP(E62,статьи!$G$2:$H$24,2,TRUE) -> Незаконные действия по получению или предоставлению кредитного отчета либо информации, составляющей кредитную историю и входящей в кредитный отчет, если такие действия не содержат уголовно наказуемого деяния | K62: =VLOOKUP(A62,'компании+описание'!$A$1:$D$438,4,) -> По результатам рассмотрения материалов дела об административном правонарушении № ЦА-38-ЮЛ-25-21240, возбужденного за совершение административного правонарушения, ответственность за которое предусмотрена частью 2 статьи 15.19 КоАП РФ, Обществу с ограниченной ответственностью «Т-Капитал» назначено административное наказание в виде штрафа в размере 700 000 рублей. Постановление вступило в законную силу 13.01.2026.
A63: 60 | B63: 46035 | C63: Общество с ограниченной ответственностью «РСХБ Управление Активами» | D63: Юридическое лицо | E63: ч.12 ст.15.29 КоАП РФ | F63: 400000 | G63: 300000 | H63: 500000 | I63: В диапазоне | J63: =VLOOKUP(E63,статьи!$G$2:$H$24,2,TRUE) -> Незаконные действия по получению или предоставлению кредитного отчета либо информации, составляющей кредитную историю и входящей в кредитный отчет, если такие действия не содержат уголовно наказуемого деяния | K63: =VLOOKUP(A63,'компании+описание'!$A$1:$D$438,4,) -> По результатам рассмотрения материалов дела об административном правонарушении № ЦА-38-ЮЛ-25-21566, возбужденного за совершение административного правонарушения, ответственность за которое предусмотрена частью 12 статьи 15.29 КоАП РФ, Обществу с ограниченной ответственностью «РСХБ Управление Активами» назначено административное наказание в виде штрафа в размере 400 000 рублей. Постановление вступило в законную силу 13.01.2026.
A64: 61 | B64: 46021 | C64: Акционерное общество «Объединенное кредитное бюро» | D64: Юридическое лицо | E64: ч.1 ст.19.7.3 КоАП РФ | F64: 700000 | G64: 500000 | H64: 700000 | I64: Максимум | J64: =VLOOKUP(E64,статьи!$G$2:$H$24,2,TRUE) -> Незаконные действия по получению или предоставлению кредитного отчета либо информации, составляющей кредитную историю и входящей в кредитный отчет, если такие действия не содержат уголовно наказуемого деяния | K64: =VLOOKUP(A64,'компании+описание'!$A$1:$D$438,4,) -> По результатам рассмотрения материалов дела об административном правонарушении № ЦА-44-ЮЛ-25-21165, возбужденного за совершение административного правонарушения, ответственность за которое предусмотрена частью 1 статьи 19.7.3 КоАП РФ, акционерному обществу «Объединенное кредитное бюро» назначено административное наказание в виде штрафа в размере 700 000 рублей. Постановление о назначении административного наказания вступило в законную силу 30.12.2025.
A65: 62 | B65: 46021 | C65: Пивень Наталья Анатольевна | D65: Гражданин | E65: ст.15.30 КоАП РФ | F65: 3000 | G65: 3000 | H65: 5000 | I65: Минимум | J65: =VLOOKUP(E65,статьи!$G$2:$H$24,2,TRUE) -> Незаконные действия по получению или предоставлению кредитного отчета либо информации, составляющей кредитную историю и входящей в кредитный отчет, если такие действия не содержат уголовно наказуемого деяния | K65: =VLOOKUP(A65,'компании+описание'!$A$1:$D$438,4,) -> По результатам рассмотрения материалов дела об административном правонарушении № ЦА-34-Гр-25-18608, возбужденного за совершение административного правонарушения, ответственность за которое предусмотрена статьей 15.30 Кодекса Российской Федерации об административных правонарушениях, Пивень Наталье Анатольевне назначено административное наказание в виде штрафа в размере 3 000 рублей. Постановление от 21.11.2025 № 25-18608/3110-1 о назначении административного наказания вступило в законную силу 30.12.2025.
A66: 63 | B66: 46021 | C66: Акционерное общество «Объединенное кредитное бюро» | D66: Юридическое лицо | E66: ч.1 ст.19.7.3 КоАП РФ | F66: 700000 | G66: 500000 | H66: 700000 | I66: Максимум | J66: =VLOOKUP(E66,статьи!$G$2:$H$24,2,TRUE) -> Незаконные действия по получению или предоставлению кредитного отчета либо информации, составляющей кредитную историю и входящей в кредитный отчет, если такие действия не содержат уголовно наказуемого деяния | K66: =VLOOKUP(A66,'компании+описание'!$A$1:$D$438,4,) -> По результатам рассмотрения материалов дела об административном правонарушении № ЦА-44-ЮЛ-25-21166, возбужденного за совершение административного правонарушения, ответственность за которое предусмотрена частью 1 статьи 19.7.3 КоАП РФ, акционерному обществу «Объединенное кредитное бюро» назначено административное наказание в виде штрафа в размере 700 000 рублей. Постановление о назначении административного наказания вступило в законную силу 30.12.2025.
A67: 64 | B67: 46021 | C67: Пивень Демид Романович | D67: Гражданин | E67: ст.15.30 КоАП РФ | F67: 3000 | G67: 3000 | H67: 5000 | I67: Минимум | J67: =VLOOKUP(E67,статьи!$G$2:$H$24,2,TRUE) -> Незаконные действия по получению или предоставлению кредитного отчета либо информации, составляющей кредитную историю и входящей в кредитный отчет, если такие действия не содержат уголовно наказуемого деяния | K67: =VLOOKUP(A67,'компании+описание'!$A$1:$D$438,4,) -> По результатам рассмотрения материалов дела об административном правонарушении № ЦА-34-Гр-25-18606, возбужденного за совершение административного правонарушения, ответственность за которое предусмотрена статьей 15.30 Кодекса Российской Федерации об административных правонарушениях, Пивню Демиду Романовичу назначено административное наказание в виде штрафа в размере 3 000 рублей. Постановление от 21.11.2025 № 25-18606/3110-1 о назначении административного наказания вступило в законную силу 30.12.2025.
A68: 65 | B68: 46020 | C68: Акционерное общество "Инвестиционная компания "Лидер" | D68: Юридическое лицо | E68: ч.2 ст.15.29 КоАП РФ | F68: предупреждение | G68: 500000 | H68: 700000 | I68: Предупреждение | J68: =VLOOKUP(E68,статьи!$G$2:$H$24,2,TRUE) -> Незаконные действия по получению или предоставлению кредитного отчета либо информации, составляющей кредитную историю и входящей в кредитный отчет, если такие действия не содержат уголовно наказуемого деяния | K68: =VLOOKUP(A68,'компании+описание'!$A$1:$D$438,4,) -> По результатам рассмотрения материалов дела об административном правонарушении № ЦА-38-ЮЛ-25-20445, возбуждённого за совершение административного правонарушения, ответственность за которое предусмотрена частью 2 статьи 15.29 Кодекса Российской Федерации об административных правонарушениях, АО «ИК «Лидер» назначено административное наказание в виде предупреждения. Постановление вступило в законную силу 27.12.2025.
A69: 66 | B69: 46014 | C69: Кувшинова Анна Викторовна | D69: Гражданин | E69: ст.15.30 КоАП РФ | F69: 3000 | G69: 3000 | H69: 5000 | I69: Минимум | J69: =VLOOKUP(E69,статьи!$G$2:$H$24,2,TRUE) -> Незаконные действия по получению или предоставлению кредитного отчета либо информации, составляющей кредитную историю и входящей в кредитный отчет, если такие действия не содержат уголовно наказуемого деяния | K69: =VLOOKUP(A69,'компании+описание'!$A$1:$D$438,4,) -> По результатам рассмотрения материалов дела об административном правонарушении № ЦА-34-Гр-25-19266, возбужденного за совершение административного правонарушения, ответственность за которое предусмотрена статьей 15.30 Кодекса Российской Федерации об административных правонарушениях, Кувшиновой Анне Викторовне назначено административное наказание в виде штрафа в размере 3 000 рублей. Постановление от 19.11.2025 № 25-19266/3110-1 о назначении административного наказания вступило в законную силу 16.12.2025.
A70: 67 | B70: 46014 | C70: Кувшинов Роман Сергеевич | D70: Гражданин | E70: ст.15.30 КоАП РФ | F70: 3000 | G70: 3000 | H70: 5000 | I70: Минимум | J70: =VLOOKUP(E70,статьи!$G$2:$H$24,2,TRUE) -> Незаконные действия по получению или предоставлению кредитного отчета либо информации, составляющей кредитную историю и входящей в кредитный отчет, если такие действия не содержат уголовно наказуемого деяния | K70: =VLOOKUP(A70,'компании+описание'!$A$1:$D$438,4,) -> По результатам рассмотрения материалов дела об административном правонарушении № ЦА-34-Гр-25-19256, возбужденного за совершение административного правонарушения, ответственность за которое предусмотрена статьей 15.30 Кодекса Российской Федерации об административных правонарушениях, Кувшинову Роману Сергеевичу назначено административное наказание в виде штрафа в размере 3 000 рублей. Постановление от 19.11.2025 № 25-19256/3110-1 о назначении административного наказания вступило в законную силу 16.12.2025.
A71: 68 | B71: 46014 | C71: Чамкин Михаил Александрович | D71: Гражданин | E71: ст.15.30 КоАП РФ | F71: 30000 | G71: 3000 | H71: 5000 | I71: Выше максимума | J71: =VLOOKUP(E71,статьи!$G$2:$H$24,2,TRUE) -> Незаконные действия по получению или предоставлению кредитного отчета либо информации, составляющей кредитную историю и входящей в кредитный отчет, если такие действия не содержат уголовно наказуемого деяния | K71: =VLOOKUP(A71,'компании+описание'!$A$1:$D$438,4,) -> По результатам рассмотрения материалов дела об административном правонарушении № ЦА-34-ДЛ-25-19399, возбужденного за совершение административного правонарушения, ответственность за которое предусмотрена статьей 15.30 Кодекса Российской Федерации об административных правонарушениях, директору Общества с ограниченной ответственностью «ТОСОЛ-СИНТЕЗ ТРЕЙДИНГ» Чамкину Михаилу Александровичу назначено административное наказание в виде штрафа в размере 30 000 рублей. Постановление от 20.11.2025 № 25-19399/3110-1 о назначении административного наказания вступило в законную силу 12.12.2025.
A72: 69 | B72: 46014 | C72: ОБЩЕСТВО С ОГРАНИЧЕННОЙ ОТВЕТСТВЕННОСТЬЮ "НАРОДНАЯ ИНВЕСТИЦИОННАЯ ПЛАТФОРМА" | D72: Юридическое лицо | E72: ч.9 ст.19.5 КоАП РФ | F72: 250000 | G72: 500000 | H72: 700000 | I72: Ниже минимума | J72: =VLOOKUP(E72,статьи!$G$2:$H$24,2,TRUE) -> 1. Неисполнение акционерным обществом, профессиональным участником рынка ценных бумаг, управляющей компанией акционерного инвестиционного фонда, паевого инвестиционного фонда или негосударственного пенсионного фонда либо специализированным депозитарием акционерного инвестиционного фонда, паевого инвестиционного фонда или негосударственного пенсионного фонда обязанности по хранению документов, которые предусмотрены законодательством об акционерных обществах, о рынке ценных бумаг, об инвестиционных фондах и принятыми в соответствии с ним нормативными правовыми актами и хранение которых является обязательным, а также нарушение установленных порядка и сроков хранения таких документов | K72: =VLOOKUP(A72,'компании+описание'!$A$1:$D$438,4,) -> По результатам рассмотрения материалов дела об административном правонарушении № ЦА-34-ЮЛ-25-20912, возбужденного за совершение административного правонарушения, ответственность за которое предусмотрена частью 9 статьи 19.5 Кодекса Российской Федерации об административных правонарушениях, ОБЩЕСТВУ С ОГРАНИЧЕННОЙ ОТВЕТСТВЕННОСТЬЮ «НАРОДНАЯ ИНВЕСТИЦИОННАЯ ПЛАТФОРМА» назначено административное наказание в виде штрафа в размере 250 000 (двести пятьдесят тысяч) рублей. Постановление о наложении штрафа по делу об административном правонарушении от 08.12.2025 № 25-20912/3110-1 вступило в законную силу 23.12.2025.
A73: 70 | B73: 46014 | C73: Акционерное общество «Управляющая компания «Первая» | D73: Юридическое лицо | E73: ч.6 ст.15.29 КоАП РФ | F73: 700000 | G73: 700000 | H73: 1000000 | I73: Минимум | J73: =VLOOKUP(E73,статьи!$G$2:$H$24,2,TRUE) -> 1. Неисполнение акционерным обществом, профессиональным участником рынка ценных бумаг, управляющей компанией акционерного инвестиционного фонда, паевого инвестиционного фонда или негосударственного пенсионного фонда либо специализированным депозитарием акционерного инвестиционного фонда, паевого инвестиционного фонда или негосударственного пенсионного фонда обязанности по хранению документов, которые предусмотрены законодательством об акционерных обществах, о рынке ценных бумаг, об инвестиционных фондах и принятыми в соответствии с ним нормативными правовыми актами и хранение которых является обязательным, а также нарушение установленных порядка и сроков хранения таких документов | K73: =VLOOKUP(A73,'компании+описание'!$A$1:$D$438,4,) -> По результатам рассмотрения материалов дела об административном правонарушении № ЦА-38-ЮЛ-25-20491, возбужденного за совершение административного правонарушения, ответственность за которое предусмотрена частью 6 статьи 15.29 КоАП РФ, Акционерному обществу «Управляющая компания «Первая» назначено административное наказание в виде штрафа в размере 700 000 рублей. Постановление вступило в законную силу 23.12.2025.
A74: 71 | B74: 46014 | C74: Акционерное общество_x000D_ «Контрада Капитал» | D74: Юридическое лицо | E74: ч.12 ст.15.29 КоАП РФ | F74: 150000 | G74: 300000 | H74: 500000 | I74: Ниже минимума | J74: =VLOOKUP(E74,статьи!$G$2:$H$24,2,TRUE) -> Незаконные действия по получению или предоставлению кредитного отчета либо информации, составляющей кредитную историю и входящей в кредитный отчет, если такие действия не содержат уголовно наказуемого деяния | K74: =VLOOKUP(A74,'компании+описание'!$A$1:$D$438,4,) -> По результатам рассмотрения материалов дела об административном правонарушении № ЦА-38-ЮЛ-25-20149, возбужденного за совершение административного правонарушения, ответственность за которое предусмотрена частью 12 статьи 15.29 КоАП РФ, Акционерному обществу «Контрада Капитал» назначено административное наказание в виде штрафа в размере 150 000 рублей. Постановление вступило в законную силу 23.12.2025._x000D_ По результатам рассмотрения материалов дела об административном правонарушении № ЦА-38-ЮЛ-25-20147, возбужденного за совершение административного правонарушения, ответственность за которое предусмотрена частью 6 статьи 15.29 КоАП РФ, Акционерному обществу «Контрада Капитал» назначено административное наказание в виде штрафа в размере 350 000 рублей. Постановление вступило в законную силу 23.12.2025.
A75: 71 | B75: 46014 | C75: Акционерное общество_x000D_ «Контрада Капитал» | D75: Юридическое лицо | E75: ч.6 ст.15.29 КоАП РФ | F75: 350000 | G75: 700000 | H75: 1000000 | I75: Ниже минимума | J75: =VLOOKUP(E75,статьи!$G$2:$H$24,2,TRUE) -> 1. Неисполнение акционерным обществом, профессиональным участником рынка ценных бумаг, управляющей компанией акционерного инвестиционного фонда, паевого инвестиционного фонда или негосударственного пенсионного фонда либо специализированным депозитарием акционерного инвестиционного фонда, паевого инвестиционного фонда или негосударственного пенсионного фонда обязанности по хранению документов, которые предусмотрены законодательством об акционерных обществах, о рынке ценных бумаг, об инвестиционных фондах и принятыми в соответствии с ним нормативными правовыми актами и хранение которых является обязательным, а также нарушение установленных порядка и сроков хранения таких документов | K75: =VLOOKUP(A75,'компании+описание'!$A$1:$D$438,4,) -> По результатам рассмотрения материалов дела об административном правонарушении № ЦА-38-ЮЛ-25-20149, возбужденного за совершение административного правонарушения, ответственность за которое предусмотрена частью 12 статьи 15.29 КоАП РФ, Акционерному обществу «Контрада Капитал» назначено административное наказание в виде штрафа в размере 150 000 рублей. Постановление вступило в законную силу 23.12.2025._x000D_ По результатам рассмотрения материалов дела об административном правонарушении № ЦА-38-ЮЛ-25-20147, возбужденного за совершение административного правонарушения, ответственность за которое предусмотрена частью 6 статьи 15.29 КоАП РФ, Акционерному обществу «Контрада Капитал» назначено административное наказание в виде штрафа в размере 350 000 рублей. Постановление вступило в законную силу 23.12.2025.
A76: 72 | B76: 46010 | C76: Общество с ограниченной ответственностью "ТОРГОВАЯ СИСТЕМА" | D76: Юридическое лицо | E76: ст.15.30 КоАП РФ | F76: 350000 | G76: 700000 | H76: в размере суммы излишнего дохода… но не менее 700 000 рублей | I76: Ниже минимума | J76: =VLOOKUP(E76,статьи!$G$2:$H$24,2,TRUE) -> Незаконные действия по получению или предоставлению кредитного отчета либо информации, составляющей кредитную историю и входящей в кредитный отчет, если такие действия не содержат уголовно наказуемого деяния | K76: =VLOOKUP(A76,'компании+описание'!$A$1:$D$438,4,) -> По результатам рассмотрения материалов дела об административном правонарушении № ЦА-34-ЮЛ-25-17527, возбужденного за совершение административного правонарушения, ответственность за которое предусмотрена статьей 15.30 КоАП РФ, обществу с ограниченной ответственностью "ТОРГОВАЯ СИСТЕМА" назначено административное наказание в виде штрафа в размере 350 000 рублей. Постановление о наложении штрафа по делу об административном правонарушении от 23.10.2025 № 25-17527/3110-1 вступило в законную силу 19.12.2025.
A77: 73 | B77: 46010 | C77: Кривова Надежда Юнусовна | D77: Гражданин | E77: ст.15.30 КоАП РФ | F77: 3000 | G77: 3000 | H77: 5000 | I77: Минимум | J77: =VLOOKUP(E77,статьи!$G$2:$H$24,2,TRUE) -> Незаконные действия по получению или предоставлению кредитного отчета либо информации, составляющей кредитную историю и входящей в кредитный отчет, если такие действия не содержат уголовно наказуемого деяния | K77: =VLOOKUP(A77,'компании+описание'!$A$1:$D$438,4,) -> По результатам рассмотрения материалов дела об административном правонарушении № ЦА-34-Гр-25-19385, возбужденного за совершение административного правонарушения, ответственность за которое предусмотрена статьей 15.30 КоАП РФ, Кривовой Надежде Юнусовне назначено административное наказание в виде штрафа в размере 3 000 рублей. Постановление о наложении штрафа по делу об административном правонарушении от 19.11.2025 № 25-19385/3110-1 вступило в законную силу 19.12.2025.
A78: 74 | B78: 46010 | C78: Кривов Вадим Иванович | D78: Гражданин | E78: ст.15.30 КоАП РФ | F78: 3000 | G78: 3000 | H78: 5000 | I78: Минимум | J78: =VLOOKUP(E78,статьи!$G$2:$H$24,2,TRUE) -> Незаконные действия по получению или предоставлению кредитного отчета либо информации, составляющей кредитную историю и входящей в кредитный отчет, если такие действия не содержат уголовно наказуемого деяния | K78: =VLOOKUP(A78,'компании+описание'!$A$1:$D$438,4,) -> По результатам рассмотрения материалов дела об административном правонарушении № ЦА-34-Гр-25-19383, возбужденного за совершение административного правонарушения, ответственность за которое предусмотрена статьей 15.30 КоАП РФ, Кривову Вадиму Ивановичу назначено административное наказание в виде штрафа в размере 3 000 рублей. Постановление о наложении штрафа по делу об административном правонарушении от 19.11.2025 № 25-19383/3110-1 вступило в законную силу 19.12.2025.
A79: 75 | B79: 46010 | C79: Общество с ограниченной_x000D_ ответственностью_x000D_ «Совкомбанк Управление_x000D_ Активами» | D79: Юридическое лицо | E79: ч.12 ст.15.29 КоАП РФ | F79: предупреждение | G79: 300000 | H79: 500000 | I79: Предупреждение | J79: =VLOOKUP(E79,статьи!$G$2:$H$24,2,TRUE) -> Незаконные действия по получению или предоставлению кредитного отчета либо информации, составляющей кредитную историю и входящей в кредитный отчет, если такие действия не содержат уголовно наказуемого деяния | K79: =VLOOKUP(A79,'компании+описание'!$A$1:$D$438,4,) -> По результатам рассмотрения материалов дела об административном правонарушении № ЦА-38-ЮЛ-25-19928, возбужденного за совершение административного правонарушения, ответственность за которое предусмотрена частью 12 статьи 15.29 КоАП РФ, Обществу с ограниченной ответственностью «Совкомбанк Управление Активами» назначено административное наказание в виде предупреждения. Постановление вступило в законную силу 19.12.2025.
A80: 76 | B80: 46007 | C80: Общество с ограниченной ответственностью "Зитрон" | D80: Юридическое лицо | E80: ст.15.30 КоАП РФ | F80: 350000 | G80: 700000 | H80: в размере суммы излишнего дохода… но не менее 700 000 рублей | I80: Ниже минимума | J80: =VLOOKUP(E80,статьи!$G$2:$H$24,2,TRUE) -> Незаконные действия по получению или предоставлению кредитного отчета либо информации, составляющей кредитную историю и входящей в кредитный отчет, если такие действия не содержат уголовно наказуемого деяния | K80: =VLOOKUP(A80,'компании+описание'!$A$1:$D$438,4,) -> По результатам рассмотрения материалов дела об административном правонарушении № ЦА-34-ЮЛ-25-1083, возбужденного за совершение административного правонарушения, ответственность за которое предусмотрена статьей 15.30 КоАП РФ, обществу с ограниченной ответственностью "Зитрон" назначено административное наказание в виде штрафа в размере 350 000 рублей. Постановление о наложении штрафа по делу об административном правонарушении от 05.03.2025 № 25-1083/3110-1 вступило в законную силу 04.12.2025.
A81: 77 | B81: 46007 | C81: Акционерное общество «НРК-Р.О.С.Т.» | D81: Юридическое лицо | E81: ч.7 ст.15.29 КоАП РФ | F81: 500000 | G81: 500000 | H81: 700000 | I81: Минимум | J81: =VLOOKUP(E81,статьи!$G$2:$H$24,2,TRUE) -> 1. Неисполнение акционерным обществом, профессиональным участником рынка ценных бумаг, управляющей компанией акционерного инвестиционного фонда, паевого инвестиционного фонда или негосударственного пенсионного фонда либо специализированным депозитарием акционерного инвестиционного фонда, паевого инвестиционного фонда или негосударственного пенсионного фонда обязанности по хранению документов, которые предусмотрены законодательством об акционерных обществах, о рынке ценных бумаг, об инвестиционных фондах и принятыми в соответствии с ним нормативными правовыми актами и хранение которых является обязательным, а также нарушение установленных порядка и сроков хранения таких документов | K81: =VLOOKUP(A81,'компании+описание'!$A$1:$D$438,4,) -> По результатам рассмотрения материалов дела об административном правонарушении № ЦА-34-ЮЛ-25-17383, возбужденного за совершение административного правонарушения, ответственность за которое предусмотрена частью 7 статьи 15.29 КоАП РФ, АО «НРК-Р.О.С.Т.» назначено административное наказание в виде штрафа в размере 500 000 рублей. Постановление № 25-17383/3110-1 о назначении административного наказания вступило в законную силу 16.12.2025.
A82: 78 | B82: 46007 | C82: Общество с ограниченной ответственностью «Бюро кредитных историй КредитИнфо» | D82: Юридическое лицо | E82: ч.1 ст.19.7.3 КоАП РФ | F82: 500000 | G82: 500000 | H82: 700000 | I82: Минимум | J82: =VLOOKUP(E82,статьи!$G$2:$H$24,2,TRUE) -> Незаконные действия по получению или предоставлению кредитного отчета либо информации, составляющей кредитную историю и входящей в кредитный отчет, если такие действия не содержат уголовно наказуемого деяния | K82: =VLOOKUP(A82,'компании+описание'!$A$1:$D$438,4,) -> По результатам рассмотрения материалов дела об административном правонарушении № ЦА-44-ЮЛ-25-20280, возбужденного за совершение административного правонарушения, ответственность за которое предусмотрена частью 1 статьи 19.7.3 КоАП РФ, обществу с ограниченной ответственностью «Бюро кредитных историй КредитИнфо» назначено административное наказание в виде штрафа в размере 500 000 рублей. Постановление о назначении административного наказания вступило в законную силу 16.12.2025.
A83: 79 | B83: 46007 | C83: Общество с ограниченной ответственностью «Апрель Капитал Брокер» | D83: Юридическое лицо | E83: ч.2 ст.15.29 КоАП РФ | F83: предупреждение | G83: 500000 | H83: 700000 | I83: Предупреждение | J83: =VLOOKUP(E83,статьи!$G$2:$H$24,2,TRUE) -> Незаконные действия по получению или предоставлению кредитного отчета либо информации, составляющей кредитную историю и входящей в кредитный отчет, если такие действия не содержат уголовно наказуемого деяния | K83: =VLOOKUP(A83,'компании+описание'!$A$1:$D$438,4,) -> По результатам рассмотрения материалов дела об административном правонарушении № ЦА-38-ЮЛ-25-19829, возбужденного за совершение административного правонарушения, ответственность за которое предусмотрена частью 2 статьи 15.29 КоАП РФ, Обществу с ограниченной ответственностью «Апрель Капитал Брокер» назначено административное наказание в виде предупреждения. Постановление вступило в законную силу 16.12.2025.
